Workbook

Sheet Leia-me
A1: MOSAICO · A Manhã do Carro-Forte · O Impostor — Matriz do caso
A3: O que é | B3: A "bíblia antes do código" (Guia técnico, seção 18): tudo o que o jogo precisa saber da história, em tabelas. Fonte única: A_Manha_do_Carro_Forte_-_O_impostor_revisao2.docx (revisão 2, 4/10/2026). Nada aqui é texto para o jogador.
A4: Partidas lógicas | B4: Três: S (impostor: Subgerente, versão de referência), G (Gerente) e V (Caixa Veterano). O ato é o mesmo; mudam só os pontos A1–A10.
A5: Casas | B5: Núcleo 6 → +1º bloco = 8 → +2º = 10 → +3º = 12 → +Transportador = 13 personagens jogáveis. O oculto (Monitor Remoto), o vigia de fora (Operador de Rádio) e os três de apoio (Motorista, Segurança Interno, Caixa Novato) estão em toda casa, sempre do sistema.
A6: Abas de estrutura | B6: Partidas · Ajustes A1–A10 · Elenco · Casas · Linha do tempo · Janela 87 s · Postos na janela · Perspectivas · Lugares · Rotas e visão · Acessos · Capítulos · Seis eixos · Provas e cobertura · Perguntas · Plantações · RA
A7: Abas de falas | B7: Prólogo e Cap 1 a Cap 8: cada fala do texto público (diretas e indiretas), com quem fala, canal, função, prova, ponto de ajuste, variação G/V e se sai quando o personagem não está na casa. As 6 colunas de personalidade estão vazias: é a próxima passada.
A8: Variantes Cap 8 | B8: Confissão, saída (A10), mudanças na acusação e no epílogo de cada partida.
A9: Pendências | B9: Contradições e buracos encontrados ao montar a matriz, com proposta e a decisão do Mario. Verde = decidido ou aplicado no jogo.
A10: Mudanças no docx | B10: Lista do que mudar no docx da revisão 2 para a revisão 3: texto atual, texto novo e motivo. O docx não foi alterado.
A11: Cores | B11: Amarelo = linha com ponto de ajuste (muda por partida). Laranja = falta fonte / pendência. Verde = coberto.
A12: Ids | B12: Personagens pela função, minúsculas, sem acento (gerente, caixa_veterano…). Lugares com hífen (sala-gerencia, arquivo-morto…). Falas: cN-NNN.
A13: Rascunho | B13: As perguntas por capítulo são proposta minha a partir das fichas dos capítulos; precisam da sua aprovação.

Sheet Resumo
A1: Aba | B1: Linhas | C1: Com ajuste | D1: Saem se ausente
A2: Prólogo | B2: =COUNTA('Prólogo'!A2:A15) | C2: =COUNTIF('Prólogo'!J2:J15,"A*") | D2: =COUNTIF('Prólogo'!M2:M15,"sim")
A3: Cap 1 | B3: =COUNTA('Cap 1'!A2:A45) | C3: =COUNTIF('Cap 1'!J2:J45,"A*") | D3: =COUNTIF('Cap 1'!M2:M45,"sim")
A4: Cap 2 | B4: =COUNTA('Cap 2'!A2:A47) | C4: =COUNTIF('Cap 2'!J2:J47,"A*") | D4: =COUNTIF('Cap 2'!M2:M47,"sim")
A5: Cap 3 | B5: =COUNTA('Cap 3'!A2:A35) | C5: =COUNTIF('Cap 3'!J2:J35,"A*") | D5: =COUNTIF('Cap 3'!M2:M35,"sim")
A6: Cap 4 | B6: =COUNTA('Cap 4'!A2:A41) | C6: =COUNTIF('Cap 4'!J2:J41,"A*") | D6: =COUNTIF('Cap 4'!M2:M41,"sim")
A7: Cap 5 | B7: =COUNTA('Cap 5'!A2:A37) | C7: =COUNTIF('Cap 5'!J2:J37,"A*") | D7: =COUNTIF('Cap 5'!M2:M37,"sim")
A8: Cap 6 | B8: =COUNTA('Cap 6'!A2:A28) | C8: =COUNTIF('Cap 6'!J2:J28,"A*") | D8: =COUNTIF('Cap 6'!M2:M28,"sim")
A9: Cap 7 | B9: =COUNTA('Cap 7'!A2:A37) | C9: =COUNTIF('Cap 7'!J2:J37,"A*") | D9: =COUNTIF('Cap 7'!M2:M37,"sim")
A10: Cap 8 | B10: =COUNTA('Cap 8'!A2:A39) | C10: =COUNTIF('Cap 8'!J2:J39,"A*") | D10: =COUNTIF('Cap 8'!M2:M39,"sim")
A11: Total | B11: =SUM(B2:B10) | C11: =SUM(C2:C10) | D11: =SUM(D2:D10)
A13: Pendências abertas | B13: =COUNTA(Pendências!A2:A60)-COUNTA(Pendências!F2:F60)
A14: Perguntas (rascunho) | B14: =COUNTA(Perguntas!A2:A26)
A15: Provas com FALTA na casa 6 | B15: =COUNTIF('Provas e cobertura'!F2:F24,"FALTA")
A16: Mudanças no docx (para a revisão 3) | B16: =COUNTA('Mudanças no docx'!A2:A60)

Sheet Partidas
A1: Partida | B1: Impostor (sempre do sistema) | C1: Ajudante (A2) | D1: Falso culpado | E1: Casa mínima | F1: Lugares para humanos (casa − impostor) | G1: Onde disse estar na janela (A5) | H1: Quem o viu não estar (A5) | I1: Rastros (A3, A6, A7) | J1: Origem dos R$ 96.000 (A8) | K1: Confissão (A9)
A2: S | B2: O Subgerente | C2: O Caixa Veterano (inconsciente: assinou o malote sem contar) | D2: O Técnico | E2: 8 | F2: casa 8: 7; casa 10: 9; casa 12: 11; casa 13: 12 | G2: Nos Guichês, buscando a guia | H2: Câmera 2 (só o mostra às 8h00:05); reforço: Estagiária | I2: fita no indicador (A3), farinha na barra (A6), cartão do rádio (A7) | J2: joias da família empenhadas (A8) | K2: Texto público do Cap. 8 (versão de referência)
A3: G | B3: O Gerente | C3: O Subgerente (inconsciente: assinou o malote sem contar) | D3: O Técnico | E3: 8 | F3: casa 8: 7; casa 10: 9; casa 12: 11; casa 13: 12 | G3: "Ao telefone" | H3: Ramal da Gerência sem chamada entre 7h50 e 8h10; câmera 1 o mostra entrando na divisória às 7h57:50 | I3: fita (A3: tabela diz indicador, Variante G diz indicador), farinha (A6), cartão (A7) | J3: resgate antecipado da previdência privada (A8) | K3: Variante G, no fim do Cap. 8
A4: V | B4: O Caixa Veterano | C4: O Subgerente (inconsciente: assinou o malote sem contar) | D4: O Técnico | E4: 8 | F4: casa 8: 7; casa 10: 9; casa 12: 11; casa 13: 12 | G4: "Na Mesa" | H4: Câmera 2 mostra a Mesa vazia até 8h00:02; reforço: Segurança do Veículo | I4: fita no indicador (A3), farinha (A6), cartão (A7) | J4: economias guardadas para a aposentadoria (A8) | K4: Variante V, no fim do Cap. 8
A6: Fixo nas três partidas
A7: Falso culpado (fixo) | B7: O Técnico — conta admin.local, chave da porta lateral, passagem, "no Rack", atualização que travou o sistema. Exclusão na virada do fim do Cap. 6: Segurança Interno + registro do aplicativo de entregas (7h58:51); reforço: fotografias do Padeiro.
A8: Ajudantes involuntários (fixos) | B8: Segurança Interno (rádio fora do carregador), Segurança do Veículo (conferiu o lacre pela tela), Funcionário da Limpeza (transformou o descarte em cena).
A9: Encobrimento (fixo) | B9: O Gerente, às 8h31, encosta um cabo na grade quente do exaustor do Rack (curto às 8h51) para apagar o ajuste_96. Na partida G é encobrimento e autoria.
A10: O oculto (fixo) | B10: O Monitor Remoto: denúncia anônima, mensagem das 8h10, reimpressão das 8h35, mensagem do epílogo. Nunca aparece, nunca é o impostor, nunca é humano.
A11: O vigia de fora (fixo) | B11: O Operador de Rádio: antecipação das 6h52, canal fechado às 7h49, registro bruto das 8h29, contagem das 9h31, suprimento à 0392 (9h56). Não mente; nunca é humano.
A12: Pistas menores (fixas) | B12: Estagiária (senha e cópia da 17-B), Funcionário da Limpeza (chave e saco no chão), Operadora (esmalte), Caixa Novato (pasta, pânico, banheiro).
A13: Ato do impostor (fixo nas 3) | B13: 8 dias antes percebe a duplicidade e cala; 5 dias antes agenda saque de R$ 96.000 na 0392; véspera 15h50 lacra o malote 41 com R$ 384.000 sob guia de R$ 480.000; 16h30 retira os R$ 96.000; 6h28–7h06 entra pela porta lateral, guarda o dinheiro na caixa de 1998, pede a antecipação (6h52), troca o lacre no registro (6h58), afrouxa o conector da câmera 3; 7h57:55 pareia o rádio; 7h58:05 ordem falsa; troca pela passagem; volta à Gerência às 7h59:54.

Sheet Ajustes A1–A10
A1: Ponto | B1: Partida S — Subgerente (referência) | C1: Partida G — Gerente | D1: Partida V — Caixa Veterano | E1: Observação
A2: A1. Quem percebeu a duplicidade oito dias antes, e como | B2: Ao reler o espelho do reprocessamento | C2: Ao assinar o balancete semanal do Cofre | D2: Ao refazer de cabeça a soma do frigorífico
A3: A2. Malote 41 na véspera, 15h50: quem contou e lacrou; quem assinou sem contar (o ajudante) | B3: Contou o Subgerente; assinou o Caixa Veterano | C3: Contou o Gerente; assinou o Subgerente | D3: Contou o Caixa Veterano; assinou o Subgerente
A4: A3. O corte coberto por fita microporosa estreita (1,2 cm) | B4: No indicador do Subgerente | C4: No indicador do Gerente | D4: No indicador do Caixa Veterano | E4: DECIDIDO 05/10: indicador nas três partidas (o docx ainda diz polegar).
A5: A4. Na Gerência, às 7h57:50 | B5: O Caixa Veterano assina primeiro e sai para a Mesa; o Subgerente fica “para fechar o livro” | C5: Os dois assinam e saem; o Gerente deixa a Auditora “para um telefonema” e entra | D5: O Subgerente assina primeiro e sai para os Guichês; o Caixa Veterano fica
A6: A5. Onde disse estar na janela, e quem o viu não estar | B6: “Nos Guichês, buscando a guia”: a câmera 2 só o mostra às 8h00:05 (reforço: a Estagiária) | C6: “Ao telefone”: o ramal da Gerência não tem chamada entre 7h50 e 8h10, e a câmera 1 o mostra entrando na divisória às 7h57:50 | D6: “Na Mesa”: a câmera 2 mostra a Mesa vazia até 8h00:02 (reforço: o Segurança do Veículo)
A7: A5b. Álibis dos dois inocentes | B7: Gerente na Porta Giratória (Auditora, Cliente, câmera 1); Caixa Veterano na Mesa (câmera 2) | C7: Subgerente nos Guichês (câmera 2); Caixa Veterano na Mesa (câmera 2) | D7: Gerente na Porta Giratória (Auditora, Cliente, câmera 1); Subgerente nos Guichês (câmera 2)
A8: A6. Farinha seca na barra da calça | B8: Do Subgerente | C8: Do Gerente | D8: Do Caixa Veterano
A9: A7. Dígitos completos do cartão que pareou o rádio | B9: Do Subgerente | C9: Do Gerente | D9: Do Caixa Veterano
A10: A8. Titular do saque e origem do dinheiro | B10: Subgerente: joias da família empenhadas para cobrir o saque | C10: Gerente: resgate antecipado da previdência privada | D10: Caixa Veterano: as economias guardadas para a aposentadoria
A11: A9. Confissão e motivo (Cap. 8) | B11: Texto público | C11: Variante G, no fim do Cap. 8 | D11: Variante V, no fim do Cap. 8
A12: A10. O impostor no epílogo | B12: Sai acompanhado; deixa a fita no balcão | C12: Tira o anel, deixa o crachá na mesa e sai acompanhado | D12: Pendura a fotografia de volta e sai acompanhado
A13: A5-G4 | B13: Declaração do Gerente no Cap. 4 (não marcada no texto): "Diante da Porta Giratória, com a Auditora e a Cliente" (verdade) | C13: "Ao telefone" (mentira) | D13: "Diante da Porta Giratória" (verdade) | E13: APLICADO 05/10 (jogo, Cap. 4: declarações; Cap. 7: gavetas). Marcar A5 no docx.
A14: A5-crachá | B14: Crachá de chegada citado na revelação (Cap. 8): 7h16 (Subgerente) | C14: 7h12 (Gerente) | D14: 7h21 (Caixa Veterano) | E14: APLICADO 05/10 (jogo, Cap. 8). Marcar A5 no docx.
A15: Ordem falsa | B15: Voz da ordem "Porta lateral. Possível tentativa." (Cap. 2): Subgerente | C15: Gerente | D15: Caixa Veterano | E15: O texto é fixo e a voz é irreconhecível; nenhuma mudança de texto, só registro.

Sheet Elenco
A1: id | B1: Personagem | C1: Função | D1: Bloco | E1: Entra a partir da casa | F1: Pode ser humano? | G1: Candidato a impostor? | H1: Canal | I1: Quem é | J1: Por que está ali | K1: Segredo inocente | L1: Rastro | M1: Voz | N1: "Nunca diria" (limite das 6 versões) | O1: O que vê | P1: O que tem a perder | Q1: Personalidade (Big Five) | R1: Curiosidade (5DC)
A2: auditora | B2: A Auditora | C2: O olhar de fora | D2: Núcleo | E2: 6 | F2: Sim | G2: Não | H2: presencial | I2: auditora de custódia da regional. | J2: a auditoria surpresa exige alguém sem vínculo com a agência. | K2: já reprovou a gestão do Gerente em outra agência, o que a faz parecer movida por vingança; tem um guarda-chuva de cabo claro e comprou café na padaria às 7h38. | L2: perfume cítrico, grafite nas margens, farinha na ponteira do guarda-chuva. | M2: perguntas curtas ("Fato ou interpretação?"); nunca promete certeza antes da prova. | N2: nunca promete certeza antes da prova | O2: da Porta Giratória, a divisória da Gerência e as silhuetas atrás dela; antes de rostos, assinaturas. | P2: a identidade de profissional justa. | Q2: muito consciente, pouco expansiva, moderadamente afável, aberta a hipóteses, vulnerável ao medo de errar; honesta a ponto de não suavizar conclusões, lenta na humildade. Sob pressão, transforma afeto em método. | R2: explora detalhes com prazer, não abandona lacunas, suporta bem o desconhecido, escuta escolhas de palavras, evita riscos físicos.
A3: caixa_veterano | B3: O Caixa Veterano | C3: O laço de sangue | D3: Núcleo | E3: 6 | F3: Sim, exceto na partida V | G3: Sim (V) | H3: presencial | I3: tesoureiro há vinte e sete anos, o arquivo vivo da agência. | J3: integra a dupla de abertura do Cofre e a escala de fechamento. | K3: tirou da parede uma fotografia antiga da equipe e pretende pedir transferência; onze dias antes, assinou a consolidação sem recontar o Cofre para ir ao velório de um ex-colega. | L3: pó de talco das luvas nas cédulas. | M3: fala por lembranças ("Antigamente, isso tinha outro ruído"); nunca acusa sem antes refazer uma conta. | N3: nunca acusa sem antes refazer uma conta | O3: o que mudou, porque lembra do que costumava estar ali. | P3: o nome limpo e a aposentadoria. | Q3: consciente, reservado, afável por hábito, pouco aberto a mudanças, vulnerável à culpa; honesto, mas a humildade falha quando a experiência é contestada. | R3: sente prazer em diferenças mínimas, persegue contas incompletas, tolera mal o desconhecido, escuta sem invadir, evita riscos.
A4: tecnico | B4: O Técnico | C4: Quem conhece a estrutura | D4: Núcleo | E4: 6 | F4: Sim (preferência: é o falso culpado) | G4: Não (falso culpado fixo) | H4: presencial | I4: prestador de manutenção de rede e câmeras. | J4: chamado pelo Erro 17 às 7h25; chegou às 7h40 pela porta lateral. | K4: usa peças reaproveitadas sem nota; às 7h55 saiu pela porta lateral para receber uma delas de um motoboy e mente que estava no Rack durante a janela. | L4: cheiro de estanho, limalha no punho, fita isolante em dois dedos. | M4: fala em causas, nunca em culpas; jamais chama improviso de solução. | N4: nunca em culpas | O4: às 7h45, o conector da câmera 3 puxado e a poeira do fundo do Rack riscada em arco. | P4: o contrato e o sustento. | Q4: aberto a mecanismos, muito consciente no diagnóstico, pouco expansivo, direto a ponto de parecer hostil, ansioso quando tocam suas ferramentas; honesto sobre resultados, pouco humilde sobre método. | R4: explora sistemas, não larga uma falha sem origem, tolera a incerteza técnica, lê mal intenções, aceita riscos que pode medir.
A5: operadora | B5: A Operadora da Central | C5: O registro | D5: Núcleo | E5: 6 | F5: Sim | G5: Não | H5: presencial (Central, interfone) | I5: operadora das câmeras e do rádio. | J5: conserva chamadas, horários e imagens. | K5: na noite anterior, depois de testar o rádio às 19h12, ouviu uma discussão do Gerente com o Subgerente e apagou a linha da ocorrência; às 7h43 anotou a piscada da câmera 3 num bloco particular. | L5: lascas de esmalte lilás no botão do rádio. | M5: "No canal, ficou assim"; nunca diz que uma gravação explica um motivo. | N5: nunca diz que uma gravação explica um motivo | O5: dezesseis quadros, respirações e silêncios. | P5: a carreira. | Q5: consciente, introvertida, moderadamente aberta, afável com quem respeita limites, tensa diante do confronto; honesta, mas cede quando privacidade e dever colidem. | R5: distingue vozes, persegue lacunas de horário, suporta o desconhecido enquanto pode arquivá-lo, alta curiosidade social, baixa busca por emoção.
A6: gerente | B6: O Gerente | C6: A autoridade | D6: Núcleo | E6: 6 | F6: Sim, exceto na partida G | G6: Sim (G) | H6: presencial | I6: responsável pela agência. | J6: recebe a auditoria e trava a agência. | K6: onze dias antes, saiu às 19h00 para encontrar quem ameaçava denunciar um favorecimento numa concessão de crédito e autorizou o fechamento por telefone; às 8h31 queima o cabo do Rack (encobrimento, fixo). | L6: loção amadeirada; marcas quadradas do anel nos papéis. | M6: fala no plural ("Nós seguiremos o protocolo"); nunca admite descontrole diante da equipe. | N6: nunca admite descontrole diante da equipe | O6: condutas antes de evidências. | P6: o cargo e o nome. | Q6: consciente com hierarquias, expansivo quando comanda, pouco aberto a contestação, cordial por conveniência, instável quando perde autoridade; a honestidade enfraquece diante da ameaça à instituição. | R6: pouca exploração; a dúvida só cresce quando afeta sua posição; tolera mal a incerteza; lê bem relações; aceita riscos de reputação.
A7: cliente_cofre | B7: A Cliente do Cofre | C7: O conhecedor do acervo | D7: Núcleo | E7: 6 | F7: Sim | G7: Não | H7: presencial | I7: filha do engenheiro que construiu o prédio da agência em 1987. | J7: veio retirar do cofre alugado cartas e a planta original da obra. | K7: as cartas mostram que o pai recebeu pagamento por fora para construir uma passagem que não constaria da planta oficial; ela quer proteger o nome dele. Na véspera, às 15h55, esperava na Antecâmara e viu o malote 41 cheio na plataforma, com um vinco diagonal. | L7: fios de lã vermelha, cheiro de cânfora. | M7: fala baixo, com datas impecáveis; nunca reduz uma lembrança a preço. | N7: nunca reduz uma lembrança a preço | O7: vincos, procedências, gestos herdados; da Porta Giratória, quantas silhuetas entram e saem da Gerência; barras e bainhas. | P7: a memória da família. | Q7: aberta a histórias, organizada, reservada, seletivamente afável, ansiosa quando a intimidade é ameaçada; preserva a verdade, mas controla o momento. | R7: explora objetos, insiste em lacunas biográficas, tolera mal a exposição, forte curiosidade social, baixa busca por emoção.
A8: subgerente | B8: O Subgerente | C8: O guardião do rito | D8: 1º bloco | E8: 8 | F8: Sim, exceto na partida S | G8: Sim (S, referência) | H8: presencial | I8: responsável pelos procedimentos, horários e assinaturas da tesouraria. | J8: integra a dupla de abertura e a escala de fechamento. | K8: onze dias antes, reprocessou a fila que duplicou o depósito e, desde então, desconfia de algo; às 7h35, pediu a chave 17-B ao Funcionário da Limpeza para tirar do armário do Arquivo o espelho daquele reprocessamento e relê-lo antes da auditoria. | L8: papel térmico entre os dedos, cheiro quase apagado de chuva. | M8: cortesia precisa; oferece soluções antes que peçam; nunca diz "não sei". | N8: nunca diz "não sei" | O8: a agência como sistema que pode ser corrigido. | P8: a identidade profissional e o cargo. | Q8: extremamente consciente, reservado, pouco aberto a perder o controle, cordial por estratégia, instável diante da vergonha. | R8: explora mecanismos com habilidade, persegue obsessivamente problemas sem solução, tolera alto estresse, lê as vulnerabilidades dos colegas, aceita riscos crescentes para preservar a aparência.
A9: limpeza | B9: O Funcionário da Limpeza | C9: Quem cuida da rotina | D9: 1º bloco | E9: 8 | F9: Sim | G9: Não | H9: presencial | I9: conhece o prédio pela sola, pelos cheiros e pelo lugar exato de cada objeto. | J9: chega às 7h10 e limpa antes da abertura. | K9: emprestou a chave 17-B ao Subgerente das 7h35 às 7h47, para quitar uma cadeia de favores (um adiantamento para a cirurgia da irmã); às 8h01 tirou o saco do cesto e o largou no chão. | L9: cheiro de eucalipto, semicírculo de água limpa, a roda do balde que range. | M9: fala por objetos ("Isso não estava aqui"); nunca comenta conversa entreouvida. | N9: nunca comenta conversa entreouvida | O9: às 7h46, o Arquivo limpo, o cesto vazio e a caixa de 1998 dois dedos para fora. | P9: o emprego. | Q9: consciente com o espaço, discreto, muito afável, ansioso diante da autoridade; honesto, com uma humildade explorada como submissão. | R9: nota mudanças concretas, insiste em coisas fora do lugar, age diante do desconhecido, ouve sem parecer ouvir, evita riscos.
A10: seguranca_veiculo | B10: O Segurança do Veículo | C10: O intérprete das regras | D10: 2º bloco | E10: 10 | F10: Sim | G10: Não | H10: presencial (Eclusa) e rádio | I10: responsável pela custódia na Eclusa. | J10: chega com o carro-forte. | K10: a certificação vence naquela semana; às 8h00, com pressa e diante da auditoria, conferiu o lacre pela tela da Mesa, e não pela via de papel, onde constava ML-8842. | L10: fibras negras do colete. | M10: fala por proibições ("Sem dupla conferência, não atravessa"); nunca diz que uma regra está errada. | N10: nunca diz que uma regra está errada | O10: da Eclusa, pelo vidro, a Mesa de Recebimento. | P10: o emprego. | Q10: consciente, reservado, pouco aberto a exceções, cooperativo com ordens claras, tenso diante de autoridades incompatíveis; honesto, mas o medo do posto reduz a coragem de contestar. | R10: pouca exploração, insiste até fechar divergências de protocolo, suporta perigo concreto, lê mal o subtexto.
A11: padeiro | B11: O Padeiro | C11: Quem conhece o exterior | D11: 2º bloco | E11: 10 | F11: Sim | G11: Não | H11: só telefone (fora da agência) | I11: dono da padaria da esquina oposta. | J11: abre antes das cinco; a porta de serviço dá para a rua de trás, de frente para a porta lateral da agência. | K11: vende café pela porta de serviço antes do horário licenciado, por isso hesita em entregar imagens. | L11: farinha nos sapatos; os sacos empilhados na porta de serviço sujam a barra de quem passa. | M11: mede o tempo por fornadas ("Foi depois do segundo pão"); nunca descreve um rosto que não viu. | N11: nunca descreve um rosto que não viu | O11: às 6h28, uma figura de capa atravessando sua porta de serviço com uma sacola; pela câmera, a porta lateral às 6h36, às 7h06, às 7h58:47 e às 7h59:51; nunca rostos sob guarda-chuva. | P11: a licença. | Q11: observador, disciplinado pela rotina, sociável com clientes, pouco ansioso diante do que é distante; honesto, mas teme que a verdade exponha o próprio desvio. | R11: explora mudanças da rua, persegue discrepâncias de horário, evita riscos.
A12: farmaceutica | B12: A Farmacêutica | C12: Quem conhece o consumo | D12: 3º bloco | E12: 12 | F12: Sim | G12: Não | H12: presencial | I12: farmacêutica do plantão da esquina. | J12: às 7h50 atravessa para entregar discretamente um calmante ao Caixa Novato. | K12: forneceu o calmante sem receita; às 6h31 vendeu luvas tamanho G e fita microporosa a uma figura de capa e guarda-chuva de cabo claro, que pagou em dinheiro. | L12: álcool em gel com lavanda. | M12: fala em quantidades ("Quanto havia? Quanto falta?"); nunca culpa quem está em crise. | N12: nunca culpa quem está em crise | O12: da Porta Giratória, quantas silhuetas entram e saem da Gerência; curativos, respirações, tremores. | P12: a licença. | Q12: atenta, organizada, sociável sem intimidade, muito afável, vulnerável à culpa; honesta, mas cede quando uma regra ameaça alguém em sofrimento. | R12: sinais corporais, insiste até compreender uma discrepância, tolera emergências, alta curiosidade social.
A13: estagiaria | B13: A Estagiária | C13: Quem conhece os sistemas | D13: 3º bloco | E13: 12 | F13: Sim | G13: Não | H13: presencial | I13: estagiária que alimenta planilhas e telas. | J13: imprime etiquetas e organiza as pastas da Mesa. | K13: anotou num papel a senha admin.local, ditada numa pane, e mandou copiar a chave 17-B depois de ficar presa no corredor; os dois estão na pasta azul trocada com a do Caixa Novato às 7h52. | L13: tinta de caneta na lateral da mão. | M13: fala depressa quando sabe e devagar quando teme; nunca admite de imediato que uma descoberta começou por curiosidade. | N13: nunca admite de imediato que uma descoberta começou por curiosidade | O13: dos Guichês, quem chega ou não chega à Mesa; reconhece o pulsar do estabilizador da Gerência. | P13: a chance de ficar. | Q13: muito aberta, aplicada, expansiva quando domina o assunto, cooperativa, ansiosa por não parecer incapaz. | R13: explora sistemas, persegue lacunas até a exaustão, tolera mal a incerteza social, observa reações, aceita riscos digitais.
A14: transportador | B14: O Transportador | C14: A testemunha técnica | D14: Completa | E14: 13 | F14: Sim | G14: Não | H14: rádio (carro-forte) | I14: move os malotes dentro do carro-forte. | J14: recebe o malote 41 na Eclusa. | K14: uma hérnia que o faz alternar as mãos. | L14: graxa clara nos fechos. | M14: fala só do que tocou ("Pesava como o declarado"); nunca opina sobre pessoas. | N14: nunca opina sobre pessoas | O14: lacres, alças, peso, esforço. | P14: o sustento da família. | Q14: disciplinado, reservado, cooperativo, inquieto quando o corpo ameaça denunciá-lo. | R14: diferenças de peso e equilíbrio, baixa curiosidade social.
A15: monitor_remoto | B15: O Monitor Remoto | C15: O oculto | D15: Sempre (sistema) | E15: toda casa | F15: Nunca | G15: Nunca | H15: mensagem sem origem; reimpressão remota | I15: operador da central de segurança regional; nunca aparece. | J15: vê as câmeras da 0688 à distância e tem acesso remoto de suporte à rede da agência. | K15: onze dias antes, às 19h20, silenciou sem registrar o alerta "fechamento sem contagem física", porque estava fora do posto. | L15: nenhum físico; mensagens sem identificação e a origem "rede de segurança regional" na reimpressão das 8h35. | M15: frases curtas, sem sujeito ("Procurem quem abriu antes"); nunca diz o próprio nome nem a palavra "eu". | N15: nunca diz o próprio nome nem a palavra "eu" | O15: imagens e sensores, nunca o que acontece fora das câmeras. | P15: o posto. | Q15: consciente, solitário, culpado, mais corajoso no anonimato do que diante de alguém. | R15: observação paciente, sensibilidade à privação alta.
A16: operador_radio | B16: O Operador de Rádio | C16: O vigia de fora | D16: Sempre (sistema) | E16: toda casa | F16: Nunca | G16: Nunca | H16: rádio da base | I16: operador da base da transportadora; nunca entra na agência. | K16: autorizou a antecipação das 6h52 com confirmação incompleta. | L16: registros digitais e pausas da voz. | M16: horários e protocolos ("Confirme origem e destino"); nunca transforma suposição em identificação. | N16: nunca transforma suposição em identificação | O16: horários, códigos, rotas e suprimentos, nunca rostos nem motivos. | P16: a função. | Q16: consciente, estável sob pressão, cooperativo; demora a admitir a própria falha.
A17: motorista | B17: O Motorista | C17: Apoio | D17: Apoio (sistema) | E17: toda casa | F17: Nunca | G17: Não | H17: rádio (carro-forte) | I17: Conduz o carro-forte. | K17: Uma filha prestando vestibular e uma advertência guardada por ter aceitado outra alteração sem confirmação dupla. | M17: Fala depois de consultar a prancheta ("O que vale é o carimbo").
A18: seguranca_interno | B18: O Segurança Interno | C18: Apoio | D18: Apoio (sistema) | E18: toda casa | F18: Nunca | G18: Não | H18: presencial | I18: Guarda o Corredor Restrito. | K18: Às 7h20 testou o rádio reserva na Gerência, ouviu uma respiração no canal e deixou o aparelho fora do carregador. Na janela, foi à porta lateral pela ordem falsa e viu, pelo vidro, um homem de capa, de costas, com um motoboy. | L18: O couro do coldre range quando ele se vira.
A19: caixa_novato | B19: O Caixa Novato | C19: Apoio | D19: Apoio (sistema) | E19: toda casa | F19: Nunca | G19: Não | H19: presencial | I19: Caixa novo; conta cédulas movendo os lábios. | K19: Esconde a crise de ansiedade e o calmante sem receita. Usa no indicador uma tira larga de fita microporosa do kit da Gerência. Às 7h52 trocou de pasta com a Estagiária; na janela estava no banheiro, de onde ouviu a parede raspar duas vezes; às 8h02 abriu o Arquivo Morto. | L19: Fita larga (2,5 cm) encardida no indicador.

Sheet Casas
A1: Casa | B1: Composição | C1: Personagens jogáveis | D1: Quem está | E1: Sempre presentes (sistema) | F1: Partidas que cabem | G1: Máx. humanos
A2: 6 | B2: Núcleo | C2: 6 | D2: A Auditora, O Caixa Veterano, O Técnico, A Operadora da Central, O Gerente, A Cliente do Cofre | E2: Monitor Remoto (oculto), Operador de Rádio (vigia), Motorista, Segurança Interno, Caixa Novato | F2: nenhuma (todas pedem casa 8) | G2: 5
A3: 8 | B3: Núcleo + 1º bloco | C3: 8 | D3: A Auditora, O Caixa Veterano, O Técnico, A Operadora da Central, O Gerente, A Cliente do Cofre, O Subgerente, O Funcionário da Limpeza | E3: Monitor Remoto (oculto), Operador de Rádio (vigia), Motorista, Segurança Interno, Caixa Novato | F3: S, G, V | G3: 7
A4: 10 | B4: + 2º bloco | C4: 10 | D4: A Auditora, O Caixa Veterano, O Técnico, A Operadora da Central, O Gerente, A Cliente do Cofre, O Subgerente, O Funcionário da Limpeza, O Segurança do Veículo, O Padeiro | E4: Monitor Remoto (oculto), Operador de Rádio (vigia), Motorista, Segurança Interno, Caixa Novato | F4: S, G, V | G4: 9
A5: 12 | B5: + 3º bloco | C5: 12 | D5: A Auditora, O Caixa Veterano, O Técnico, A Operadora da Central, O Gerente, A Cliente do Cofre, O Subgerente, O Funcionário da Limpeza, O Segurança do Veículo, O Padeiro, A Farmacêutica, A Estagiária | E5: Monitor Remoto (oculto), Operador de Rádio (vigia), Motorista, Segurança Interno, Caixa Novato | F5: S, G, V | G5: 11
A6: 13 | B6: Casa cheia (+ Transportador) | C6: 13 | D6: A Auditora, O Caixa Veterano, O Técnico, A Operadora da Central, O Gerente, A Cliente do Cofre, O Subgerente, O Funcionário da Limpeza, O Segurança do Veículo, O Padeiro, A Farmacêutica, A Estagiária, O Transportador | E6: Monitor Remoto (oculto), Operador de Rádio (vigia), Motorista, Segurança Interno, Caixa Novato | F6: S, G, V | G6: 12

Sheet Linha do tempo
A1: Dia | B1: Hora | C1: Onde | D1: Quem | E1: O quê | F1: Como se sabe (fonte) | G1: Revelado no cap. | H1: Fixo / ajuste
A2: Onze dias antes | B2: 18h54 | C2: Guichê 2 | D2: Caixa Veterano | E2: Depósito do frigorífico de R$ 96.000, recibo único | F2: Recibo (Caixa Veterano); consolidações (Operadora) | G2: 5 | H2: Fixo
A3: Onze dias antes | B3: 19h00 | C3: — | D3: Gerente | E3: Sai para encontrar quem ameaçava denunciar favorecimento; autoriza o fechamento por telefone | F3: ajuste_96 ("G sai"); confissão do Gerente | G3: 6 | H3: Fixo
A4: Onze dias antes | B4: 19h03 | C4: Terminal (acesso remoto) | D4: Técnico | E4: Sistema congela durante atualização remota (admin.local) | F4: Registro do sistema (Operadora); Técnico admite | G4: 5 | H4: Fixo
A5: Onze dias antes | B5: 19h11 | C5: Terminal | D5: Subgerente | E5: Reprocessa manualmente a fila: o depósito entra duas vezes | F5: Consolidações; ajuste_96; Subgerente confirma | G5: 5–6 | H5: Fixo
A6: Onze dias antes | B6: 19h12 | C6: Central / Gerência | D6: Operadora | E6: Testa o rádio | F6: Operadora (Cap. 2) | G6: 2 | H6: Fixo
A7: Onze dias antes | B7: 19h20 | C7: Cofre | D7: Subgerente e Caixa Veterano | E7: Consolidação assinada sem recontagem física (Veterano vai ao velório) | F7: ajuste_96; confissão do Veterano | G7: 6 | H7: Fixo
A8: Onze dias antes | B8: 19h20 | C8: Central regional | D8: Monitor Remoto | E8: Alerta "fechamento sem contagem física"; fora do posto, silencia sem registrar | F8: Mensagem do epílogo | G8: 8 (epílogo) | H8: Fixo
A9: Oito dias antes | B9: — | C9: — | D9: Impostor | E9: Percebe a duplicidade e cala | F9: Confissão | G9: 8 | H9: A1
A10: Cinco dias antes | B10: — | C10: Agência 0392 | D10: Impostor | E10: Agenda saque em espécie de R$ 96.000 (recursos próprios) | F10: Regional, pela Auditora (10h41) | G10: 7 | H10: A8
A11: Véspera | B11: 15h50 | C11: Cofre / Antecâmara | D11: Impostor + cossignatário | E11: Malote 41 lacrado com R$ 384.000 sob guia de R$ 480.000; o cossignatário assina sem contar | F11: Livro de lacres (Operadora) | G11: 7 | H11: A2
A12: Véspera | B12: 15h55 | C12: Antecâmara | D12: Cliente do Cofre | E12: Vê o malote 41 cheio na plataforma, com vinco diagonal | F12: Cliente do Cofre | G12: 1 | H12: Fixo
... A74: Manhã seguinte | B74: 8h10 | C74: Central | D74: Monitor Remoto | E74: "Onze dias atrás. Dezenove e vinte. Alarme de fechamento sem contagem. Posto vazio. Silenciado depois. Por isso a auditoria." | F74: — | G74: 8 (epílogo) | H74: Fixo

Sheet Janela 87 s
A1: A janela crítica, segundo a segundo (ordem às 7h58:05; câmera 3 cega de 7h58:12 a 7h59:39)
A3: +s desde a ordem | B3: Hora | C3: O que acontece | D3: Fonte
A4: +0 | B4: 7h58:05 | C4: Ordem falsa pelo rádio: "Porta lateral. Possível tentativa." O Segurança Interno corre à porta lateral | D4: Gravação (Operadora, 8h18)
A5: +1 | B5: 7h58:06 | C5: Impostor sai da Gerência pela passagem — 1º raspado do painel (ouvido do banheiro) | D5: Caixa Novato
A6: +7 | B6: 7h58:12 | C6: Câmera 3 cai (vibração do exaustor completa a queda) | D6: Central; microfone (estalo)
A7: +16 | B7: 7h58:21 | C7: Impostor no interior do Rack | D7: Rota (cânone)
A8: +20 | B8: 7h58:25 | C8: Impostor entra no Arquivo Morto; pega a caixa de 1998 e o saco reserva | D8: Rota
A9: +42 | B9: 7h58:47 | C9: Padeiro (câmera da porta de serviço): o Técnico recebe a caixa do motoboy | D9: Fotografia do Padeiro
A10: +46 | B10: 7h58:51 | C10: Aplicativo de entregas registra a entrega ao Técnico | D10: App do Técnico (Cap. 6)
A11: ~+25…+65 | B11: 7h58:31–7h59:11 | C11: Na Antecâmara: troca de 40 s (abre ML-8842, passa 6 blocos + 2, fecha com ML-8847 e etiqueta); corta a mão na grapa através da luva | D11: Simulação (Cap. 4); luva (Cap. 6)
A12: +79 | B12: 7h59:24 | C12: Tampa metálica do cesto de descarte bate (saco ML-8842 e luva rasgada) | D12: Microfone da Central (Operadora, Cap. 5)
A13: +94 | B13: 7h59:39 | C13: Impostor recoloca o conector; câmera 3 volta | D13: Central
A14: +106 | B14: 7h59:51 | C14: Técnico volta empurrando a porta lateral (sensor: fechada) | D14: Sensor; fotografia do Padeiro
... A21: — | B21: 8h03 | C21: Gerente trava a Porta Giratória | D21: Todos

Sheet Postos na janela
A1: Personagem | B1: Partida S | C1: Partida G | D1: Partida V | E1: Quem o situa (exclusão)
A2: A Auditora | B2: Porta Giratória | C2: Porta Giratória (o Gerente a deixa às 7h57:50) | D2: Porta Giratória | E2: Câmera 1; Cliente e Farmacêutica
A3: O Gerente | B3: Porta Giratória | C3: IMPOSTOR: Gerência → passagem → Rack → Arquivo → Antecâmara (diz "ao telefone") | D3: Porta Giratória | E3: S/V: Auditora, Cliente, câmera 1 (A5b)
A4: O Subgerente | B4: IMPOSTOR: Gerência → passagem… (diz "nos Guichês") | C4: Guichês | D4: Guichês | E4: G/V: câmera 2 (A5b)
A5: O Caixa Veterano | B5: Mesa de Recebimento | C5: Mesa de Recebimento | D5: IMPOSTOR: Gerência → passagem… (diz "na Mesa") | E5: S/G: câmera 2; Segurança do Veículo (A5b)
A6: A Cliente do Cofre | B6: Porta Giratória | C6: Porta Giratória | D6: Porta Giratória | E6: Câmera 1
A7: A Farmacêutica | B7: Porta Giratória | C7: Porta Giratória | D7: Porta Giratória | E7: Câmera 1
A8: A Operadora da Central | B8: Central (console, mão no rádio) | C8: idem | D8: idem | E8: Câmera interna da Central
A9: O Técnico | B9: Rua de trás, com o motoboy (diz "no Rack") | C9: idem | D9: idem | E9: Segurança Interno; app de entregas 7h58:51; fotografias do Padeiro
A10: O Funcionário da Limpeza | B10: Saguão, com o balde | C10: idem | D10: idem | E10: Câmera 1
A11: A Estagiária | B11: Guichês | C11: idem | D11: idem | E11: Câmera 2
A12: O Caixa Novato | B12: Banheiro dos Funcionários (diz "almoxarifado", depois admite) | C12: idem | D12: idem | E12: Ninguém o vê (banheiro sem câmera); só o raspado da parede o situa
... A19: O Monitor Remoto | B19: Central regional (vê a câmera 3 cair) | C19: idem | D19: idem | E19: Fora da agência

Sheet Perspectivas
A1: Momento | B1: Personagem | C1: Onde estava | D1: O que percebeu | E1: O que concluiu
A2: 7h57:40 a 7h57:55, a Gerência | B2: (vários) | D2: A Cliente do Cofre conta dois entrando e um saindo **A4**, e a Farmacêutica confirma. A câmera 1 registra o mesmo. A Auditora vê silhuetas e não as distingue. O Segurança do Veículo vê quem chega à Mesa **A4**.
A3: 7h53, a impressora da Gerência | B3: (vários) | D3: A Auditora, na Porta Giratória, ouve um gemido atrás da divisória e anota sem saber por quê. A Estagiária, nos Guichês, reconhece o som e conclui que alguém imprimiu uma etiqueta. O Caixa Veterano e o Subgerente, na Antecâmara, não ouvem. O Gerente, ao lado da Auditora, ouve e não comenta.
A4: 7h58:05–7h59:39 (a janela) | B4: Auditora | C4: Porta Giratória | D4: A mudança simultânea de atenção quando o rádio chamou | E4: Algo foi provocado
A5: 7h58:05–7h59:39 (a janela) | B5: Gerente | C5: Porta Giratória A5b | D5: A ordem pelo rádio do Segurança Interno | E5: Desorganização da equipe
A6: 7h58:05–7h59:39 (a janela) | B6: Farmacêutica | C6: Porta Giratória | D6: A Gerência com uma pessoa dentro A4 | E6: Nada, ainda
A7: 7h58:05–7h59:39 (a janela) | B7: Cliente do Cofre | C7: Porta Giratória | D7: Dois entrarem na Gerência e um sair A4 ; ninguém mais entrar | E7: Nada, ainda
A8: 7h58:05–7h59:39 (a janela) | B8: Caixa Veterano | C8: Mesa de Recebimento A5b | D8: O silêncio da Eclusa antes da travessia | E8: Atraso
A9: 7h58:05–7h59:39 (a janela) | B9: Subgerente | C9: Na Gerência e na passagem A5 | D9: — | E9: —
A10: 7h58:05–7h59:39 (a janela) | B10: Estagiária | C10: Guichês | D10: Quem chega e não chega à Mesa | E10: Que o malote estava demorando
A11: 7h58:05–7h59:39 (a janela) | B11: Operadora | C11: Central (a câmera interna a mostra no console) | D11: A câmera 3 cair e voltar; a tampa do cesto no microfone | E11: Falha técnica
A12: 7h58:05–7h59:39 (a janela) | B12: Segurança Interno | C12: Porta Lateral | D12: Um homem de capa com um motoboy, de costas | E12: Sem tentativa
A13: 7h58:05–7h59:39 (a janela) | B13: Técnico | C13: Rua de trás | D13: O motoboy, a caixa, a batida no vidro | E13: Que precisava esconder a caixa
A14: 7h58:05–7h59:39 (a janela) | B14: Funcionário da Limpeza | C14: Saguão, com o balde | D14: Nada no corredor | E14: —
A15: 7h58:05–7h59:39 (a janela) | B15: Caixa Novato | C15: Banheiro | D15: A parede raspar duas vezes | E15: Que estava enlouquecendo
... A20: 7h58:05–7h59:39 (a janela) | B20: Monitor Remoto (oculto) | C20: Central regional | D20: A câmera 3 cair; o sensor da porta lateral já registrara 6h36 e 7h06 | E20: Que alguém abrira antes
A21: 8h01 e 8h02, o saco | B21: (vários) | D21: O Funcionário da Limpeza tira o saco do cesto, ouve passos e o larga no chão. O Caixa Novato sai do banheiro, entra no corredor procurando um lugar quieto, vê a Limpeza afastar-se do Arquivo para o fundo e abre a porta: conclui roubo. A Cliente do Cofre reconhece o vinco. O Caixa Veterano pensa no conteúdo. A Auditora separa objeto, declaração e prova. O impostor compreende que o descarte virou cena.
A22: 8h31, o cabo | B22: (vários) | D22: O Gerente entra atrás da divisória; ninguém o acompanha. O oculto vê a câmera 1 e, às 8h35, reimprime a etiqueta. O Técnico está na Central, sob os olhos de todos.

Sheet Lugares
A1: id | B1: Lugar | C1: O que tem / o que importa
A2: porta-giratoria | B2: Porta Giratória | C2: Entrada; o Gerente a trava às 8h03 e destrava às 11h12
A3: saguao | B3: Saguão | C3: Granito que guarda pegadas; cheiro de papel, lã molhada e café
A4: guiches | B4: Guichês | C4: Três, em linha de vidro, à direita
A5: mesa-recebimento | B5: Mesa de Recebimento | C5: Atrás dos Guichês, a 12 passos da porta, de frente para a Eclusa
A6: sala-gerencia | B6: Sala da Gerência | C6: Atrás da divisória fosca; impressora térmica + estabilizador (3 rápidos, 1 lento), carregador do rádio reserva, terminal compartilhado, telefone; painel atrás do armário de aço
A7: banheiro-funcionarios | B7: Banheiro dos Funcionários | C7: Parede comum com a Gerência; tranca; sem câmera; ouve-se o painel raspar
A8: porta-lateral | B8: Porta Lateral | C8: Rua de trás; chave por fora, barra por dentro; sem câmera; sensor só na central regional; na chuva a lingueta não trava
A9: corredor-restrito | B9: Corredor Restrito | C9: 24 passos; porta de aço (crachá e chave); ladrilho oco diante da Central
A10: central-monitoramento | B10: Central de Monitoramento | C10: 16 quadros; câmera interna; microfone ambiente que capta o corredor
A11: arquivo-morto | B11: Arquivo Morto | C11: Caixas por ano (a de 1998 na prateleira baixa), sacos reserva, armário de espelhos (17-B), cesto com tampa metálica, canto de infiltração
A12: nicho-rack | B12: Nicho do Rack | C12: Fora da visão da câmera 3; poeira atrás do armário
... A20: farmacia | B20: Farmácia de plantão | C20: Esquina; vitrine reflete a Vaga Blindada (fora da agência)

Sheet Rotas e visão
A1: De | B1: Até | C1: Tempo | D1: Nota
A2: Mesa de Recebimento | B2: porta do Corredor Restrito | C2: 8 s
A3: porta do Corredor | B3: Arquivo Morto | C3: 10 s | D3: Da Mesa ao Arquivo: 26 s sem pressa, 18 correndo
A4: Arquivo Morto | B4: Nicho do Rack | C4: 4 s
A5: Nicho do Rack | B5: Antecâmara | C5: 2 s | D5: Arquivo → Antecâmara: 6 s
A6: Sala da Gerência | B6: interior do Rack (pela passagem) | C6: 15 s | D6: Sem câmera
A7: Porta Giratória | B7: Sala da Gerência | C7: 6 s
A8: Antecâmara | B8: porta do Corredor (correndo) | C8: 12 s
A9: Saguão | B9: Porta Lateral | C9: 8 s
A10: Vaga Blindada | B10: Mesa | C10: 42 s | D10: Duas pausas da Eclusa
A11: Sala da Gerência | B11: Cofre (pelo Saguão e corredor) | C11: 34 s
A12: Troca completa pelo corredor | B12: — | C12: ~98 s | D12: NÃO cabe na janela de 87 s
A13: Troca pela passagem (exposição à câmera 3) | B13: 7h58:25–7h59:34 | C13: 69 s | D13: Cabe
A15: Linhas de visão e de som
A16: Posto / sensor | B16: Vê ou ouve | C16: Não vê / limite
A17: Câmera 3 | B17: Vê a entrada do Corredor, a porta da Central e metade da porta do Arquivo | C17: Não vê o Nicho do Rack nem a curva da Antecâmara
A18: Câmera 2 | B18: Vê os Guichês e a Mesa | C18: Não caiu em momento algum
A19: Câmera 1 | B19: Vê o Saguão e a divisória da Gerência (quem entra e sai) | C19: Não vê o interior da sala
A20: Câmera interna da Central | B20: Vê o console | C20: —
A21: Microfone da Central | B21: Capta o corredor (tampa do cesto às 7h59:24; estalo às 7h58:12) | C21: —
A22: Saguão (ouvido) | B22: Campainha da Eclusa, baque do Cofre, gemido da impressora atrás da divisória | C22: Não ouve conversa baixa no Arquivo
A23: Banheiro (ouvido) | B23: O painel da passagem raspar | C23: —
A24: Eclusa (visão) | B24: A Mesa, pelo vidro | C24: —
A25: Câmera da porta de serviço da padaria | B25: A Porta Lateral da agência e a rua de trás | C25: Nunca rostos sob guarda-chuva
A26: Sistema de câmeras antes das 7h30 | B26: Modo economia: só grava movimento na Porta Giratória e no Cofre | C26: —

Sheet Acessos
A1: Acesso | B1: Quem tem
A2: Porta Lateral (chave mecânica) | B2: Gerente, Subgerente, Caixa Veterano, Funcionário da Limpeza, Técnico
A3: Chave 17-B (Rack e armário de espelhos) | B3: Original com a Limpeza (emprestada ao Subgerente 7h35–7h47); cópia da Estagiária na pasta azul; a do Técnico no molho
A4: Cofre | B4: Duas chaves e duas pessoas; dupla de abertura: Subgerente e Caixa Veterano
A5: Faixa administrativa (cartão de proximidade) | B5: Gerente, Subgerente, Caixa Veterano (tesoureiro), Técnico (manutenção); 2 últimos dígitos corrompidos no pareamento
A6: Conta admin.local | B6: Criada pelo Técnico; senha ditada numa pane diante do Gerente, Subgerente, Caixa Veterano e Estagiária (que a anotou)
A7: Passagem de Serviço | B7: "Conhecimento exclusivo das três chaves da tesouraria" (planta 1987, manual 1990); o Técnico a descobriu sozinho
A8: Sensor da Porta Lateral, no dia | B8: 6h36 chave (impostor entra); 7h06 barra (sai); 7h40 chave (Técnico); 7h55 barra (Técnico sai); 7h55–7h59:51 "não travada"; 7h59:51 fechada

Sheet Capítulos
A1: Cap. | B1: Título | C1: Momento / arco | D1: Degrau da escada | E1: Grande questão | F1: Peça para o mistério maior | G1: Pergunta principal (varia) | H1: Perguntas secundárias | I1: Âncoras de hora | J1: Peça central | K1: Gancho de abertura | L1: Revelação que abre duas | M1: Subtrama que avança | N1: Efeito teia | O1: Pista genuína e falsa pista | P1: Obstáculo | Q1: Curiosidade (5DC) | R1: Pontos de ajuste | S1: Virada
A2: 0 | B2: Duas manhãs antes da mesma porta | C2: 6h28–8h03 | D2: 1 | E2: Os dois começos (quem chega × quem já estava) se encontram às 7h50 na campainha da Eclusa | S2: —
A3: 1 | B3: O malote murcho | C3: 8h02 a 8h10. Arco: o encontro e a primeira anomalia | D3: 1 | E3: O saco do Arquivo Morto é o malote que atravessou a Eclusa? | F3: Invólucro, lacre e conteúdo seguiram caminhos distintos: ML-8842 ficou, ML-8847 partiu | G3: Quem tinha acesso ao Corredor Restrito e ao Arquivo Morto naquela manhã? A lista de chaves e crachás muda de peso conforme o impostor sorteado | H3: Quando o saco foi deixado no Arquivo? Por que o malote entregue tinha outro lacre? | I3: 8h05 (câmera sem sinal), 8h07 (ML-8847 confirmado), 8h10 (a mensagem) | J3: O malote murcho | K3: O saco vazio que parece respirar | L3: O malote entregue tinha ML-8847. Quem trocou? Por que largou o antigo no caminho? | M3: A Limpeza mente sobre a chave; a Cliente quer sair antes de abrirem a pasta | N3: O piso limpo às 7h46 transforma a chave 17-B de detalhe em suspeita | O3: Genuína: a ilha seca sob o saco e a tampa torta do cesto. Falsa: a pasta do Novato com chave e senha | P3: O isolamento e o Gerente impedindo o Técnico de examinar o circuito; o perigo na rua para o carro-forte retido | Q3: Exploração: o malote e o fragmento térmico. Privação: qual saco atravessou. Estresse: o isolamento e o carro retido. Social: a mentira da Limpeza, a pressa da Cliente. Emoção: a mensagem sem origem | R3: Nenhum
A4: 2 | B4: A voz a mais | C4: 8h12 a 8h35. Arco: alguém que não deveria estar | D4: 1 | E4: De onde veio a ordem que tirou o Segurança Interno da Antecâmara? | F4: A ordem falsa partiu de dentro, da Sala da Gerência, autenticada por um cartão da faixa administrativa | G4: De quem é o cartão que pareou o rádio? Nesta altura, quatro pessoas cabem na faixa; a resposta, que fecha no Cap. 7, é a do impostor sorteado | H4: Por que o Segurança Interno obedeceu? Quem estava na agência às 6h52? | I4: 8h18 (a gravação), 8h29 (o registro da base), 8h35 (a impressora) | J4: O rádio reserva | K4: Uma gravação com a voz de um homem que ninguém reconhece | L4: A ordem saiu da Gerência. Quem estava lá às 7h58? Quem estava na agência às 6h52, antes de qualquer crachá? | M4: A Operadora entrega o bloco e a frase omitida; a Farmacêutica cala o que reconhece | N4: A frase “não cai só você” passa a pesar sobre o Gerente e o Subgerente | O4: Genuína: o pulsar do estabilizador e o horário dos crachás. Falsa: a lasca lilás no botão | P4: O Gerente transforma a falha do Segurança Interno em acusação; a Cliente recusa abrir a pasta | Q4: Exploração: o rádio e o espectro. Privação: de quem é o cartão. Estresse: o perigo na rua continua. Social: a frase omitida e as duas respostas. Emoção: a impressora que imprime sozinha | R4: A3 (a mão com fita microporosa)
A5: 3 | B5: O papel que nasceu quente | C5: 8h35 a 8h50. Arco: o objeto. Fecha com a primeira grande virada | D5: 2 (virada no fim) | E5: Por que a etiqueta nova existia antes de a câmera cair? | F5: A troca foi preparada às 6h58, não improvisada; e o malote entregue pesava o que a guia declara | G5: Quem conhecia a senha admin.local? Cinco pessoas a ouviram; a resposta só se estreita com a passagem e a escala de fechamento | H5: De onde veio a reimpressão das 8h35? O que é o arquivo ajuste_96? | I5: 8h38 (a fila), 8h44 (o carro na esquina), 8h48 (o peso) | J5: A impressora térmica de etiquetas | K5: A etiqueta no chão “como uma resposta oferecida por uma máquina que ninguém interrogara” | L5: O malote entregue pesava o que devia: nada saiu. Por que alguém trocaria um malote sem levar nada? E o que estava escrito na página que acompanhou a etiqueta? | M5: A Estagiária confessa a senha anotada; o Técnico tem a maleta revistada | N5: O peso desmonta a leitura de roubo que o grito das 8h02 tinha imposto ao saco, à pasta do Novato e à câmera | O5: Genuína: a tarefa criada às 6h58 e o “96.000” fantasma. Falsa: o roteador e os adaptadores da maleta | P5: Duas ordens incompatíveis para o Motorista; a revista humilhante da maleta | Q5: Exploração: a impressora e o verso da etiqueta. Privação: o que é ajuste_96. Estresse: as duas ordens para o Motorista. Social: a revista da maleta. Emoção: o peso que derruba o roubo | R5: Nenhum | S5: O caso parecia roubo durante a janela. A balança e a mão do Transportador mostram que o malote saiu completo. O que cai é a leitura de subtração
A6: 4 | B6: Vinte e seis segundos | C6: 8h51 a 9h25. Arco: o espaço | D6: 3 | E6: Por onde alguém faria a troca dentro de oitenta e sete segundos? | F6: Pelo corredor, a troca não cabe; pela Passagem de Serviço, entre a Gerência e o Rack, cabe | G6: Quem conhecia a passagem? Nesta altura, só o Técnico admite; a resposta completa (as três chaves da tesouraria) chega no Cap. 7 | H6: Quem queimou o cabo durante o isolamento? Onde o dinheiro poderia ter esperado? | I6: 8h51 (o curto), 9h05 (a simulação), 9h25 (a base abre o malote) | J6: O mapa físico da agência, medido pelo corpo | K6: O terminal morre no instante em que ajuste_96 vai abrir | L6: A passagem existe. Quem mais a conhece? Quem saiu da Gerência para o Rack sem atravessar o Saguão? | M6: A Limpeza confessa o empréstimo da chave; a Farmacêutica confessa o calmante | N6: A passagem muda o peso da origem da ordem falsa (Gerência) e da resposta do Técnico (“no Rack”) | O6: Genuína: as pegadas que terminam no fundo do Rack; o raspar ouvido no banheiro. Falsa: a farinha no guarda-chuva da Auditora | P6: O Gerente quer revistar todos; o Novato precisa confessar a crise e o banheiro | Q6: Exploração: o corredor medido pelo corpo e a parede que abre. Privação: quem conhece a passagem. Estresse: o cabo queimado com todos trancados. Social: as declarações lado a lado. Emoção: a lanterna rente ao chão | R6: A5 (onde cada candidato declarou estar; aqui só se registram as declarações, sem confirmação)
A7: 5 | B7: Oitenta e sete segundos | C7: 9h25 a 9h58. Arco: a janela crítica | D7: 3 | E7: Durante os oitenta e sete segundos, dinheiro saiu ou entrou? | F7: O Cofre tinha R$ 96.000 que só existiam no sistema; o malote da véspera pode ter saído curto, e alguém pode ter completado a diferença na janela | G7: Quem tinha chave da porta lateral e esteve na agência às 6h36? Cinco chaves; a resposta só se fecha no Cap. 7 | H7: Onde o dinheiro esperou? O que causou a duplicidade? | I7: 9h31 (a contagem), 9h43 (as fotografias), 9h56 (o suprimento) | J7: O peso e a contagem do malote 41 | K7: “Quatrocentos e oitenta mil. Todas verdadeiras.” | L7: Havia R$ 96.000 sem corpo no Cofre. De onde vieram os R$ 96.000 que completaram o malote? Quem entrou às 6h36? | M7: O Técnico admite a atualização; a Limpeza encontra a cinta na caixa | N7: A duplicidade dá sentido ao “96.000” do Cap. 3 e à frase do oculto no Cap. 1 | O7: Genuína: o sensor da porta lateral e a cinta rasgada. Falsa: a atualização do Técnico como prova de autoria | P7: O Gerente quer encerrar o caso no Técnico; a Auditora resiste a acusar antes da prova | Q7: Exploração: a caixa de 1998 e a cinta. Privação: de onde vieram os R$ 96.000. Estresse: o caso que se fecha rápido demais no Técnico. Social: a confissão do Novato sobre os vinte reais. Emoção: a janela ouvida pelo som | R7: Nenhum
A8: 6 | B8: O número sem corpo | C8: 9h58 a 10h25. Arco: o documento. Fecha com a segunda grande virada | D8: 3 (virada no fim) | E8: Como nasceu o número sem corpo, e quem tinha razões para escondê-lo? | F8: A duplicidade foi uma corrente de quatro falhas (saída, trava, reprocessamento, assinatura sem contagem), e o arquivo ajuste_96 é a reconstrução privada dessa noite feita por quem pretendia cobri-la | G8: Quem, entre os que falharam naquela noite, percebeu a diferença depois? A resposta é a do impostor sorteado (A1) e só aparece no Cap. 8 | H8: Por que o saco estava no chão e não no cesto? Onde o Técnico estava de fato? | I8: 10h04 (o arquivo recuperado), 10h12 (a imagem das 8h01), 10h21 (as fotografias) | J8: O arquivo ajuste_96 | K8: Um arquivo que existe porque alguém precisou escrever a noite para conseguir corrigi-la | L8: O Técnico estava lá fora na janela. Quem mais passa da Gerência ao Rack? Quem queimou o cabo às 8h31, se o Técnico estava sob vigilância? | M8: O Gerente revela a saída; a Limpeza confessa o saco; o Técnico confessa a peça sem nota | N8: A frase “não cai só você” deixa de ligar o Subgerente ao malote e passa a revelar a crise do Gerente | O8: Genuína: a luva rasgada com sangue. Falsa: a fita isolante do Técnico | P8: A Auditora diante do próprio trauma: registrar tudo e destruir inocentes, ou filtrar e repetir a omissão | Q8: Exploração: o arquivo ajuste_96 e o cesto. Privação: onde estava o Técnico. Estresse: a Auditora diante do próprio trauma. Social: cada falha da noite com o seu dono. Emoção: a capa pingando ao lado da porta | R8: Nenhum | S8: O caso parecia ser do Técnico: conta, chave, passagem, motivo, “no Rack”. As fotografias do Padeiro o põem do lado de fora. O que cai é a leitura que o colocava na rota
A9: 7 | B9: Quinze versões para um fato | C9: 10h25 a 10h50. Arco: o confronto das versões | D9: 4 | E9: Quais versões pertencem ao ato e quais protegem só vergonhas particulares? | F9: Só as três chaves da tesouraria conheciam a passagem; as versões convergem sobre uma delas, mas a autoria ainda admite disputa até o Cap. 8 | G9: Qual das três chaves da tesouraria não estava onde disse? É o ponto A5 | H9: Quem queimou o cabo? Quem assinou o malote da véspera sem contar? | I9: 10h28 (o quadro), 10h41 (a regional responde), 10h46 (o checksum) | J9: O quadro das quinze funções | K9: A Auditora escreve funções no quadro e se recusa a escrever nomes | L9: O cabo foi o Gerente. Ele também esteve no malote? E quem vê a agência de longe e reimprimiu a etiqueta? | M9: Gerente, Cliente, Farmacêutica e Veterano entregam o que escondiam | N9: A planta da Cliente converte a passagem de indício do Técnico em privilégio da tesouraria | O9: Genuína: o checksum e o titular do saque. Falsa, desfeita: a farinha da Auditora | P9: O Gerente tenta conservar uma versão útil; a Cliente precisa expor o pai | Q9: Exploração: a planta de 1987 e as câmeras. Privação: qual das três chaves. Estresse: a resposta da regional. Social: o confronto das versões. Emoção: a fita estreita contra a larga | R9: A2, A3, A4, A5, A5b, A6, A7, A8
A10: 8 | B10: A soma impossível | C10: 10h52–11h12; epílogo na manhã seguinte, 8h10 | D10: 5 e 6 (epílogo) | E10: Função. Retomar as sete grandes questões; a acusação de todos; a revelação em seis movimentos, escrita em uma variante por candidato; o epílogo na manhã seguinte, com a última mensagem do oculto; a pergunta de valor. O texto público abaixo é a variante de referência (impostor: o Subgerente). As variantes G (Gerente) e V (Caixa Veterano) estão depois do quadro. As sete grandes questões e as respostas. 1. O saco do Arquivo era o malote da véspera, esvaziado na troca e largado no chão pela Limpeza. 2. A voz saiu da Gerência, pelo rádio pareado com o cartão do impostor. 3. A etiqueta foi preparada às 6h58, antes da janela. 4. A rota foi a passagem entre a Gerência e o Rack. 5. Nos 87 segundos, o dinheiro entrou. 6. O número sem corpo nasceu de quatro falhas, onze dias antes. 7. As outras versões protegiam vergonhas reais e periféricas. | S10: —

Sheet Seis eixos
A1: Id | B1: Cap. | C1: Eixo | D1: Fato | E1: Fixo ou varia | F1: Degrau
A2: E1-1 | B2: 1 | C2: Há quanto tempo | D2: Arquivo limpo às 7h46; travessia às 8h00; achado às 8h02; confirmação às 8h07 | E2: Fixo | F2: 1
A3: E1-2 | B3: 1 | C3: Onde | D3: Arquivo Morto, Mesa de Recebimento, Eclusa | E3: Fixo | F3: 1
A4: E1-3 | B4: 1 | C4: Como | D4: Troca de invólucro e de lacre numa janela sem imagem | E4: Fixo | F4: 1
A5: E1-4 | B5: 1 | C5: Quem | D5: Quem tinha crachá do corredor, chave 17-B ou acesso à Mesa | E5: Fixo | F5: 1
A6: E1-5 | B6: 1 | C6: Qual e que tipo | D6: Um invólucro vazio, um lacre rompido, um fragmento térmico; violação de procedimento, sem prova de subtração | E6: Fixo | F6: 1
A7: E1-6 | B7: 1 | C7: Perspectiva | D7: Novato: roubo. Cliente: é o mesmo saco. Auditora: invólucro não é conteúdo. Limpeza: o saco veio depois das 7h46 (e se cala sobre a chave). Motorista: a via diz ML-8842; Segurança do Veículo: conferiu a tela. Operadora: ninguém entrou no Arquivo entre 7h46 e 7h58. Gerente: subtração | E7: Fixo | F7: 1
A8: E2-1 | B8: 2 | C8: Há quanto tempo | D8: Pareamento às 7h57:55; ordem às 7h58:05; antecipação às 6h52; primeiro crachá do dia às 7h10 | E8: Fixo | F8: 1
A9: E2-2 | B9: 2 | C9: Onde | D9: Sala da Gerência (estabilizador), Porta Lateral, Central | E9: Fixo | F9: 1
A10: E2-3 | B10: 2 | C10: Como | D10: Rádio pareado por cartão de proximidade e código verbal correto | E10: Fixo | F10: 1
A11: E2-4 | B11: 2 | C11: Quem | D11: Os quatro da faixa administrativa: Gerente, Subgerente, Caixa Veterano, Técnico | E11: Varia (A3 (a mão com fita microporosa)) | F11: 1
A12: E2-5 | B12: 2 | C12: Qual e que tipo | D12: Voz comprimida, pulsar do estabilizador, lasca de esmalte, registro com dígitos corrompidos | E12: Fixo | F12: 1
A13: E2-6 | B13: 2 | C13: Perspectiva | D13: Segurança Interno: viu pelo vidro um homem de capa com um motoboy. Estagiária: reconhece o estabilizador. Operadora: o esmalte é dela, de ontem. Farmacêutica: duas mãos com fita. Operador de Rádio: a chamada saiu da Gerência | E13: Varia (A3 (a mão com fita microporosa)) | F13: 1
A14: E3-1 | B14: 3 | C14: Há quanto tempo | D14: Tarefa criada às 6h58; executada às 7h53; reimpressão às 8h35; registro de peso às 8h00 | E14: Fixo | F14: 2 (virada no fim)
A15: E3-2 | B15: 3 | C15: Onde | D15: Sala da Gerência (terminal e impressora), Rack, Eclusa | E15: Fixo | F15: 2 (virada no fim)
A16: E3-3 | B16: 3 | C16: Como | D16: Conta de manutenção, tarefa agendada, edição do registro da remessa; reimpressão por acesso remoto | E16: Fixo | F16: 2 (virada no fim)
A17: E3-4 | B17: 3 | C17: Quem | D17: Quem ouviu a senha numa pane: Gerente, Subgerente, Caixa Veterano, Técnico, Estagiária | E17: Fixo | F17: 2 (virada no fim)
A18: E3-5 | B18: 3 | C18: Qual e que tipo | D18: Etiqueta legítima usada fora do rito; impressão fantasma “96.000”; peso de 7,0 kg | E18: Fixo | F18: 2 (virada no fim)
A19: E3-6 | B19: 3 | C19: Perspectiva | D19: Operadora: a fila prova preparo. Técnico: a conta é dele, o conector foi preparado. Caixa Veterano: lembra uma reimpressão de onze dias antes. Transportador: o peso é o declarado. Gerente: papel no lugar de dinheiro | E19: Fixo | F19: 2 (virada no fim)
A20: E4-1 | B20: 4 | C20: Há quanto tempo | D20: Janela de 7h58:12 a 7h59:39; curto às 8h51; simulação às 9h05 | E20: Fixo | F20: 3
A21: E4-2 | B21: 4 | C21: Onde | D21: Rack Técnico, Arquivo Morto, Nicho do Rack, Banheiro, Passagem de Serviço | E21: Fixo | F21: 3
A22: E4-3 | B22: 4 | C22: Como | D22: Rota cronometrada; pegadas na umidade; painel removível | E22: Fixo | F22: 3
A23: E4-4 | B23: 4 | C23: Quem | D23: Quem declarou estar perto do Rack; quem ouviu a parede | E23: Varia (A5 (onde cada candidato declarou estar; aqui só se registram as declarações, sem confirmação)) | F23: 3
A24: E4-5 | B24: 4 | C24: Qual e que tipo | D24: Pegadas em meia-lua, cabo derretido, o raspar da parede; indícios de oportunidade, não de autoria | E24: Fixo | F24: 3
A25: E4-6 | B25: 4 | C25: Perspectiva | D25: Técnico: diz que estava no Rack, a pior resposta possível. Novato: ouviu a parede raspar duas vezes. Limpeza: o canto úmido guarda pegadas. Gerente: “minha sala não é minha culpa”. Padeiro: a figura das 6h28 | E25: Varia (A5 (onde cada candidato declarou estar; aqui só se registram as declarações, sem confirmação)) | F25: 3
A26: E5-1 | B26: 5 | C26: Há quanto tempo | D26: Contagem da base às 9h31; duplicidade de onze dias antes (18h54 e 19h11); porta lateral às 6h36 e 7h06 | E26: Fixo | F26: 3
A27: E5-2 | B27: 5 | C27: Onde | D27: Base, Arquivo Morto (caixa de 1998), Porta Lateral, rua de trás | E27: Fixo | F27: 3
A28: E5-3 | B28: 5 | C28: Como | D28: Reconstrução da janela pelo som; sensor da porta; caixa de arquivo como esconderijo | E28: Fixo | F28: 3
A29: E5-4 | B29: 5 | C29: Quem | D29: Quem tem chave da porta lateral: Gerente, Subgerente, Caixa Veterano, Limpeza, Técnico | E29: Fixo | F29: 3
A30: E5-5 | B30: 5 | C30: Qual e que tipo | D30: Cédulas verdadeiras e completas; R$ 96.000 sem lastro; cinta de maço rasgada | E30: Fixo | F30: 3
A31: E5-6 | B31: 5 | C31: Perspectiva | D31: Caixa Novato: “e se alguém colocou?”. Caixa Veterano: o recibo é um só. Operadora: a tampa do cesto às 7h59:24 e o sensor da porta. Caixa Veterano: a caixa de 1998. Novato: os raspados batem com os horários. Técnico: admite a atualização de onze dias antes. Gerente: tudo aponta o Técnico | E31: Fixo | F31: 3
A32: E6-1 | B32: 6 | C32: Há quanto tempo | D32: Onze dias antes: 18h54, 19h00, 19h03, 19h11, 19h20; hoje: 8h01 (o saco), 10h21 (as fotografias) | E32: Fixo | F32: 3 (virada no fim)
A33: E6-2 | B33: 6 | C33: Onde | D33: Guichê 2, Cofre, terminal, Arquivo Morto, rua de trás | E33: Fixo | F33: 3 (virada no fim)
A34: E6-3 | B34: 6 | C34: Como | D34: Cópia automática do servidor; imagem parcial das 8h01; fotografias da porta de serviço da padaria | E34: Fixo | F34: 3 (virada no fim)
A35: E6-4 | B35: 6 | C35: Quem | D35: Gerente (saída), Técnico (trava), Subgerente (reprocessamento), Caixa Veterano e Subgerente (assinatura); a Limpeza (o saco no chão) | E35: Fixo | F35: 3 (virada no fim)
A36: E6-5 | B36: 6 | C36: Qual e que tipo | D36: Duplicidade contábil; luva rasgada com sangue; fotografias com hora | E36: Fixo | F36: 3 (virada no fim)
A37: E6-6 | B37: 6 | C37: Perspectiva | D37: Caixa Veterano: a assinatura e o velório. Gerente: a saída e a ameaça de denúncia. Operadora: a frase de ontem era sobre outra crise. Limpeza: “o grito criou o roubo”. Segurança Interno: o homem de capa era o Técnico; o aplicativo de entregas confirma | E37: Fixo | F37: 3 (virada no fim)
A38: E7-1 | B38: 7 | C38: Há quanto tempo | D38: 8h31 (o cabo); 7h57:50 (a Gerência); véspera, 15h50 (o lacre); 6h31 (a venda); 10h46 (o checksum) | E38: Fixo | F38: 4
A39: E7-2 | B39: 7 | C39: Onde | D39: Todo o mapa, reduzido ao quadro das funções; a Gerência no centro | E39: Fixo | F39: 4
A40: E7-3 | B40: 7 | C40: Como | D40: Cruzamento de declarações, imagens, livros e registros | E40: Fixo | F40: 4
A41: E7-4 | B41: 7 | C41: Quem | D41: As três chaves da tesouraria; o Gerente no encobrimento | E41: Varia (A2, A3, A4, A5, A5b, A6, A7, A8) | F41: 4
A42: E7-5 | B42: 7 | C42: Qual e que tipo | D42: Planta de 1987, manual de 1990, livro de lacres, cupom de venda, farinha, checksum, titular do saque: provas convergentes, ainda sem confissão | E42: Fixo | F42: 4
A43: E7-6 | B43: 7 | C43: Perspectiva | D43: Cliente: a obra do pai e as silhuetas. Operadora: câmeras 2, 1 e da Central A5 . Auditora: a fita estreita e a farinha. Reforços nas casas maiores: Farmacêutica, Estagiária, Segurança do Veículo, Padeiro | E43: Varia (A2, A3, A4, A5, A5b, A6, A7, A8) | F43: 4

Sheet Provas e cobertura
A1: Prova | B1: Cap. | C1: Fonte primária (toda casa) | D1: Reforço (casas maiores) | E1: Quem diz isso nas falas (todas as casas) | F1: Casa 6 | G1: Casa 8 | H1: Casa 10 | I1: Casa 12 | J1: Casa 13
A2: Arquivo limpo e vazio às 7h46 | B2: 1 | C2: Câmera 3 (Operadora) | D2: Funcionário da Limpeza | E2: A Operadora da Central, O Funcionário da Limpeza | F2: ok | G2: ok | H2: ok | I2: ok | J2: ok
A3: Lacre ML-8842 na via de papel | B3: 1 | C3: Motorista, pelo rádio | D3: Segurança do Veículo | E3: A Auditora, O Motorista, O Segurança do Veículo | F3: ok | G3: ok | H3: ok | I3: ok | J3: ok
A4: A ordem saiu da Gerência (estabilizador) | B4: 2 | C4: Técnico | D4: Estagiária | E4: A Estagiária, O Operador de Rádio, O Subgerente, O Técnico | F4: ok | G4: ok | H4: ok | I4: ok | J4: ok
A5: Tarefa das 6h58 e lacre trocado no registro | B5: 3 | C5: Operadora | D5: — | E5: A Operadora da Central | F5: ok | G5: ok | H5: ok | I5: ok | J5: ok
A6: Senha ditada diante da tesouraria | B6: 3 | C6: Técnico | D6: Estagiária | E6: A Auditora, A Estagiária, O Caixa Novato, O Técnico | F6: ok | G6: ok | H6: ok | I6: ok | J6: ok
A7: Peso de 7,0 kg e composição | B7: 3 | C7: Balança, pelo Motorista; guia, pelo Caixa Veterano | D7: Transportador | E7: A Auditora, O Caixa Veterano, O Motorista, O Operador de Rádio, O Transportador | F7: ok | G7: ok | H7: ok | I7: ok | J7: ok
A8: Pegadas até o fundo do Rack | B8: 4 | C8: Auditora (lanterna) | D8: Funcionário da Limpeza | E8: A Auditora, O Funcionário da Limpeza | F8: ok | G8: ok | H8: ok | I8: ok | J8: ok
A9: A passagem | B9: 4 | C9: Técnico | D9: — | E9: A Auditora, O Técnico | F9: ok | G9: ok | H9: ok | I9: ok | J9: ok
A10: A parede raspou duas vezes | B10: 4 | C10: Caixa Novato (apoio) | D10: — | E10: O Caixa Novato, O Gerente | F10: ok | G10: ok | H10: ok | I10: ok | J10: ok
A11: “E se alguém colocou?” | B11: 5 | C11: Caixa Novato (apoio) | D11: Farmacêutica | E11: O Caixa Novato | F11: ok | G11: ok | H11: ok | I11: ok | J11: ok
A12: Duplicidade de R$ 96.000 | B12: 5 | C12: Caixa Veterano e Operadora | D12: — | E12: A Operadora da Central, O Caixa Veterano, O Gerente | F12: ok | G12: ok | H12: ok | I12: ok | J12: ok
... A24: Livro de lacres A2 , titular A8 , cartão A7 | B24: 7 | C24: Operadora; regional, pela Auditora | D24: — | E24: A Auditora, A Operadora da Central, O Caixa Veterano, Registro / sistema | F24: ok | G24: ok | H24: ok | I24: ok | J24: ok

Sheet Perguntas
A1: Cap. | B1: Tipo | C1: Resposta | D1: Pergunta | E1: Opções | F1: Gabarito S | G1: Gabarito G | H1: Gabarito V | I1: Como se sabe (fonte no capítulo) | J1: Degrau | K1: Status
A2: 1 | B2: principal | C2: uma | D2: O saco vazio no chão do Arquivo Morto é o volume que atravessou a Eclusa às 8h00? | E2: Sim, é o mesmo malote, esvaziado | Não: é o invólucro com o lacre ML-8842; o volume que atravessou tinha o lacre ML-8847 | Não dá para saber ainda | F2: Não: invólucro ML-8842; atravessou ML-8847 | G2: idem | H2: idem | I2: Caixa Veterano (folhas da Mesa) e Operadora às 8h07; Motorista lê ML-8842 na via | J2: 1 | K2: rascunho
A3: 1 | B3: secundária | C3: uma | D3: Quando o saco foi parar no chão do Arquivo? | E3: Antes das 7h46 | Depois das 7h46 | Na noite anterior | F3: Depois das 7h46 | G3: idem | H3: idem | I3: Câmera 3 (Operadora): balde sai às 7h46; ilha seca sob a lona | J3: 1 | K3: rascunho
A4: 1 | B4: secundária | C4: uma | D4: Como o volume passou pela Eclusa com o lacre ML-8847? | E4: O lacre foi trocado fisicamente na Eclusa | A troca já constava no sistema, sem nome, e foi conferida pela tela | A base mandou o lacre novo | F4: A troca constava no sistema, sem nome, e foi conferida pela tela | G4: idem | H4: idem | I4: Operadora às 8h07; Segurança do Veículo conferiu a tela (reforço) | J4: 1 | K4: rascunho
A5: 2 | B5: principal | C5: uma | D5: De onde saiu a ordem que mandou o Segurança Interno à porta lateral? | E5: Da base da transportadora | Da porta lateral | De trás da divisória da Sala da Gerência | Da Central | F5: Da Sala da Gerência | G5: idem | H5: idem | I5: Operador de Rádio (a base não transmitiu); pulsar do estabilizador (Técnico) | J5: 1 | K5: rascunho
A6: 2 | B6: secundária | C6: todos | D6: Quem tem cartão na faixa administrativa que pareou o rádio? (marque todos) | E6: Gerente | Subgerente | Caixa Veterano | Técnico | Operadora | Estagiária | F6: Gerente, Subgerente, Caixa Veterano, Técnico | G6: idem | H6: idem | I6: Histórico do rádio (proposta: lido pela Operadora na casa de 6); cartões no balcão | J6: 1 | K6: rascunho
A7: 2 | B7: secundária | C7: uma | D7: De onde partiu o pedido de antecipação da coleta, às 6h52? | E7: Do celular de um funcionário | Do telefone da Sala da Gerência | Da Central | Da agência 0392 | F7: Do telefone da Sala da Gerência, antes de qualquer crachá do dia | G7: idem | H7: idem | I7: Registro bruto da base (8h29); crachás (Operadora) | J7: 1 | K7: rascunho
A8: 3 | B8: principal | C8: uma | D8: O volume que partiu às 8h50 tinha o valor declarado na guia? | E8: Não: faltava dinheiro | Sim: pesava 7,0 kg, o que a guia declara | Tinha papel no lugar das cédulas | F8: Sim: 7,0 kg, o que a guia declara | G8: idem | H8: idem | I8: Balança (Motorista) + composição (Caixa Veterano) + Transportador | J8: 2 | K8: rascunho
A9: 3 | B9: secundária | C9: uma | D9: Quando a troca do lacre foi preparada? | E9: Às 7h53, quando a etiqueta saiu | Às 6h58, no terminal da Gerência, pela conta admin.local | Durante os 87 segundos | F9: Às 6h58, pela conta admin.local | G9: idem | H9: idem | I9: Fila da impressora (Operadora, 8h38) | J9: 2 | K9: rascunho
A10: 3 | B10: secundária | C10: todos | D10: Quem ouviu a senha da conta admin.local numa pane? (marque todos) | E10: Gerente | Subgerente | Caixa Veterano | Técnico | Estagiária | Operadora | F10: Gerente, Subgerente, Caixa Veterano, Técnico, Estagiária | G10: idem | H10: idem | I10: Técnico | J10: 2 | K10: rascunho
A11: 4 | B11: principal | C11: uma | D11: Por onde a troca cabe nos 87 segundos? | E11: Pelo Corredor Restrito, correndo | Pela Passagem de Serviço, entre a Gerência e o Rack | Pela porta lateral | F11: Pela Passagem de Serviço | G11: idem | H11: idem | I11: Simulação do Técnico (9h05); pegadas até o fundo do Rack (Auditora) | J11: 3 | K11: rascunho
A12: 4 | B12: secundária | C12: uma | D12: Quando o cabo do Rack foi encostado no exaustor? | E12: Durante os 87 segundos | Durante o isolamento, depois das 8h03 | Na noite anterior | F12: Durante o isolamento | G12: idem | H12: idem | I12: Técnico: "Isso foi agora há pouco. Com a gente trancado aqui." | J12: 3 | K12: rascunho
A13: 4 | B13: secundária | C13: uma | D13: O que o Caixa Novato ouviu do banheiro durante a janela? | E13: Nada | A parede raspar duas vezes | O Cofre bater | F13: A parede raspar duas vezes | G13: idem | H13: idem | I13: Caixa Novato (apoio) | J13: 3 | K13: rascunho
... A26: 8 | B26: final (intenção) | C26: uma | D26: Por que fez isso? | E26: Para roubar | Para cobrir em segredo os R$ 96.000 que só existiam no sistema, antes da auditoria | Para incriminar o Técnico | F26: Cobrir em segredo a duplicidade de R$ 96.000 | G26: idem | H26: idem | I26: ajuste_96 ("própria"); saque na 0392; confissão (A9) | J26: 5 | K26: rascunho

Sheet Plantações
A1: Cap. | B1: O que planta | C1: O que colhe | D1: Pista genuína × falsa
A2: 0 | B2: a coleta antecipada sem nome; a figura das 6h28 e a farinha da porta de serviço; a venda das 6h31; a caixa de 1998 fora do lugar; a piscada das 7h43; o conector e a poeira riscada em arco no fundo do Rack; a mensagem "chego em quinze" no telefone do Técnico; o rádio fora do carregador e a respiração no canal; a pasta trocada; o vinco do malote visto na véspera. | C2: — | D2: —
A3: 1 | B3: A diferença de lacres, o fragmento térmico, a pasta com chave e senha, a tampa do cesto torta, a mentira da Limpeza | C3: O piso limpo das 7h46, a piscada da câmera, a coleta antecipada, o vinco visto na véspera | D3: Genuína: a ilha seca sob o saco e a tampa torta do cesto. Falsa: a pasta do Novato com chave e senha
A4: 2 | B4: O homem de capa lá fora; a conversa omitida; o cartão do Técnico na maleta; a fita microporosa A3 | C4: O rádio fora do carregador; a respiração no canal; a coleta antecipada; o gemido da impressora às 7h53 | D4: Genuína: o pulsar do estabilizador e o horário dos crachás. Falsa: a lasca lilás no botão
A5: 3 | B5: A impressão fantasma “96.000”; o nome ajuste_96; o Técnico dizendo que estava no Rack; o ciclo do exaustor; a origem remota das 8h35 | C5: O fragmento térmico do lacre; a senha da pasta; a etiqueta das 8h35 | D5: Genuína: a tarefa criada às 6h58 e o “96.000” fantasma. Falsa: o roteador e os adaptadores da maleta
A6: 4 | B6: A passagem; as declarações de onde cada um estava na janela A5 ; o guarda-chuva e a farinha da Auditora | C6: A poeira riscada em arco do prólogo; os tempos do mapa; a chave 17-B | D6: Genuína: as pegadas que terminam no fundo do Rack; o raspar ouvido no banheiro. Falsa: a farinha no guarda-chuva da Auditora
A7: 5 | B7: O saque agendado; a cinta rasgada; a motivação aparente do Técnico | C7: A mensagem “quem abriu antes”; o “96.000” fantasma; as pegadas; o raspar da parede; a figura das 6h28 | D7: Genuína: o sensor da porta lateral e a cinta rasgada. Falsa: a atualização do Técnico como prova de autoria
A8: 6 | B8: A luva tamanho G com sangue; a pergunta sobre o cabo queimado | C8: O “96.000” fantasma; a frase omitida; o homem de capa do Cap. 2; a mensagem “chego em quinze” do prólogo | D8: Genuína: a luva rasgada com sangue. Falsa: a fita isolante do Técnico
A9: 7 | B9: A distinção entre falha, encobrimento e autoria; a presença de quem vê de longe | C9: Todos os segredos inocentes; a passagem; a luva; a farinha; a fita; o suprimento à 0392 | D9: Genuína: o checksum e o titular do saque. Falsa, desfeita: a farinha da Auditora

Sheet RA
A1: Cap. | B1: Matéria para a peça (da história) | C1: Gesto novo ensinado | D1: Saída se o jogador não agir | E1: Status
A2: 0 | B2: a maquete da agência nasce da planta de evacuação que a Auditora recebe; todos os lugares do glossário aparecem no texto do prólogo antes dela (o Banheiro dos Funcionários e o Nicho do Rack inclusive), exceto a Passagem de Serviço, que fica oculta até o Cap. 4. Plantação nova: a denúncia sem assinatura, colhida no epílogo; a fita larga do kit no dedo do Novato, colhida no Cap. 7. | E2: a definir
A3: 1 | B3: o malote murcho, com o vinco diagonal, o lacre ML-8842 rompido pela grapa, o fragmento térmico branco na cola e a área seca sob o saco. Dados que a peça pode mostrar neste capítulo: ML-8842 no saco do chão; ML-8847 no malote que atravessou às 8h00; o fragmento térmico. O horário do lacre (véspera, 15h50) só entra no Cap. 7, e o registro das 6h58 só no Cap. 3. A peça separa invólucro, lacre e conteúdo, sem concluir subtração. | E3: a definir
A4: 2 | B4: o rádio reserva, o cartão de proximidade, o registro de pareamento com os dois últimos dígitos corrompidos, a transcrição da ordem e o espectro com o pulsar do estabilizador (três rápidos, um lento). Mostra origem interna e faixa administrativa, não quem operou. | E4: a definir
A5: 3 | B5: a impressora sobre o aparador, o rolo, as etiquetas ML-8842 e ML-8847, o fragmento térmico do lacre e a impressão fantasma "96.000" no verso. Dados: tarefa criada às 6h58 (admin.local, terminal da Gerência), executada às 7h53; reimpressão às 8h35 por "acesso remoto de suporte". A peça prova preparo, não autoria. | E5: a definir
A6: 4 | B6: o armário de vestígios com a planta do corredor, os tempos, o molde das pegadas, o cabo derretido e o painel da passagem. Dados: rota pelo corredor, cerca de 98 s; rota pela passagem, 69 s de exposição. Mostra oportunidade e incompatibilidades; nunca nomeia. | E6: a definir
A7: 5 | B7: a balança de custódia, com o registro de 7,0 kg e a composição declarada (41 × R\$ 100, 12 × R\$ 50, 5 × R\$ 20; 5.800 cédulas; 1 g por cédula; saco 1,2 kg). Cartões: R\$ 384.000 (5,8 kg) e R\$ 480.000 (7,0 kg). Prova que o malote saiu completo, não quem o completou. | E7: a definir
A8: 6 | B8: a linha do tempo da noite de onze dias antes, montada sobre o balcão do Guichê 2: o jogador ordena por arraste os cartões do depósito (18h54), da saída (19h00), da trava (19h03), do reprocessamento (19h11) e da assinatura (19h20), e liga cada falha à sua consequência. Ao fechar a sequência, libera a folha ajuste_96. Mecânica nova (ordenar e encadear), diferente da sobreposição do Cap. 3. Prova a origem da duplicidade e o plano de cobertura, não o autor. | E8: a definir
A9: 7 | B9: a escrivaninha das quinze versões, com gavetas por função; cada gaveta guarda só o que aquela posição podia saber. Separa fato observado, conclusão pessoal e segredo periférico, sem escolher o impostor pelo jogador. | E9: a definir
A10: 8 | B10: a mesa final de reconstrução reúne, como cartões já validados, o mapa, o saco ML-8842, o rádio, as etiquetas, a fotografia do conector, a balança, o livro-caixa, a cinta, a luva, o registro do saque e as quinze versões. Três trilhas: o ato, as condições que o permitiram e os atos posteriores. Cada conclusão decisiva exige evidência material e confirmação independente. | E10: a definir

Sheet Prólogo
A1: ID | B1: Hora | C1: Quem fala | D1: Com quem | E1: Canal | F1: Tipo | G1: Fala original | H1: Função | I1: Prova | J1: Ajuste | K1: Variação G / V | L1: Condição (casa mínima) | M1: Sai se ausente | N1: Explosivo | O1: Calmo opaco | P1: Ingênuo | Q1: Leal cego | R1: Evasivo | S1: Burocrata | T1: Nota
A2: c0-001 | B2: ~7h47 | C2: O Motorista | D2: operador_radio | E2: rádio | F2: direta | G2: Base, confirme a antecipação. | H2: prova | L2: toda casa | M2: não | T2: Atribuição inferida: o texto não diz se é o Motorista ou o Segurança do Veículo (ambos no painel).
A3: c0-002 | B3: ~7h47 | C3: O Operador de Rádio | D3: motorista | E3: rádio | F3: direta | G3: Confirmada no sistema. Pedido às seis e cinquenta e dois, código de tesouraria válido. | H3: prova | L3: toda casa | M3: não | T3: Plantação da antecipação das 6h52 (colhida no Cap. 2). Operador de Rádio é do bloco 'completa': na casa 6 precisa de canal substituto (registro/prancheta do Motorista).
A4: c0-003 | B4: ~7h47 | C4: O Motorista | D4: operador_radio | E4: rádio | F4: direta | G4: Quem pediu? | H4: prova | L4: toda casa | M4: não | T4: Atribuição inferida, como c0-001.
A5: c0-004 | B5: ~7h47 | C5: O Operador de Rádio | D5: motorista | E5: rádio | F5: direta | G5: O campo veio sem nome. | H5: prova | L5: toda casa | M5: não | T5: Coleta antecipada sem nome. Mesma ressalva de casa 6 de c0-002.
A6: c0-005 | B6: ~7h48 | C6: O Gerente | D6: auditora | E6: presencial | F6: direta | G6: Que surpresa. | H6: ambiente | L6: toda casa | M6: não
A7: c0-006 | B7: ~7h48 | C7: A Auditora | D7: gerente | E7: presencial | F7: direta | G7: Auditoria costuma funcionar melhor assim. | H7: ambiente | L7: toda casa | M7: não
A8: c0-007 | B8: ~7h48 | C8: O Gerente | D8: auditora | E8: presencial | F8: direta | G8: Quem pediu? | H8: ambiente | L8: toda casa | M8: não
A9: c0-008 | B9: ~7h48 | C9: A Auditora | D9: gerente | E9: presencial | F9: direta | G9: Uma denúncia sem assinatura. | H9: subtrama | L9: toda casa | M9: não | T9: Plantação da denúncia anônima (colhida no epílogo; autor = Monitor Remoto).
A10: c0-009 | B10: madrugada | C10: O Caixa Novato | D10: farmaceutica | E10: telefone | F10: indireta | G10: Meu coração não cabe no peito. | H10: subtrama | L10: toda casa | M10: não | T10: Telefonema relatado (crise do Novato). Novato é apoio, mas a destinatária é do bloco 3: sem a Farmacêutica, a ligação perde o par.
A11: c0-010 | B11: véspera ~19h12 | C11: O Gerente | D11: subgerente | E11: presencial | F11: direta | G11: Se isso aparecer amanhã, não cai só você. | H11: subtrama | L11: toda casa | M11: não | T11: Discussão entreouvida pela Operadora (lembrança). O texto não atribui qual frase é de quem; atribuição ao Gerente é inferida.
A12: c0-011 | B12: véspera ~19h12 | C12: O Subgerente | D12: gerente | E12: presencial | F12: direta | G12: Eu resolvo antes de abrir. | H12: subtrama | L12: casa ≥ 8 | M12: sim | T12: Atribuição inferida (voz do Subgerente: oferece solução). Nas casas sem Subgerente a fala sai, mas a discussão Gerente×Subgerente é fato fixo: decidir se fica como lembrança da Operadora.
A13: c0-012 | B13: ~7h45 | C13: Registro / sistema | D13: tecnico | E13: telefone | F13: direta | G13: chego em quinze | H13: subtrama | I13: O Técnico estava fora | L13: toda casa | M13: não | T13: Mensagem do motoboy (não é personagem) no telefone do Técnico; plantação da saída das 7h55.
A14: c0-013 | B14: 7h58:05 | C14: O Subgerente | D14: seguranca_interno | E14: rádio | F14: indireta | G14: Verifique a porta lateral. | H14: prova | I14: A ordem saiu da Gerência (estabilizador) | L14: casa ≥ 8 | M14: não | T14: Ordem falsa pelo rádio reserva (texto exato aparece no Cap. 2). Falante = impostor sorteado (G: gerente; V: caixa_veterano), mas o texto não marca ponto de ajuste.
A15: c0-014 | B15: 8h02 | C15: O Caixa Novato | D15: todos | E15: presencial | F15: direta | G15: Roubaram o dinheiro. | H15: pista falsa | L15: toda casa | M15: não

Sheet Cap 1
A1: ID | B1: Hora | C1: Quem fala | D1: Com quem | E1: Canal | F1: Tipo | G1: Fala original | H1: Função | I1: Prova | J1: Ajuste | K1: Variação G / V | L1: Condição (casa mínima) | M1: Sai se ausente | N1: Explosivo | O1: Calmo opaco | P1: Ingênuo | Q1: Leal cego | R1: Evasivo | S1: Burocrata | T1: Nota
A2: c1-001 | B2: ~8h02 | C2: A Auditora | D2: caixa_novato | E2: presencial | F2: direta | G2: O que você viu antes de gritar? | H2: ambiente | L2: toda casa | M2: não
A3: c1-002 | B3: ~8h02 | C3: O Caixa Novato | D3: auditora | E3: presencial | F3: direta | G3: Isso. | H3: ambiente | L3: toda casa | M3: não
A4: c1-003 | B4: ~8h02 | C4: A Auditora | D4: caixa_novato | E4: presencial | F4: direta | G4: Isso é uma conclusão. Quero uma imagem. | H4: ambiente | L4: toda casa | M4: não
A5: c1-004 | B5: ~8h02 | C5: O Caixa Novato | D5: auditora | E5: presencial | F5: indireta | G5: Vi a porta entreaberta, a luz fria, a lona no chão, o lacre partido. | H5: ambiente | L5: toda casa | M5: não
A6: c1-005 | B6: ~8h03 | C6: O Gerente | D6: todos | E6: presencial | F6: indireta | G6: Recuem todos. Segurança, feche o corredor; Caixa Veterano, confira os registros da Mesa; Operadora, preserve as imagens. | H6: ambiente | L6: toda casa | M6: não
A7: c1-006 | B7: ~8h03 | C7: O Gerente | D7: todos | E7: presencial | F7: direta | G7: A agência fica isolada até segunda ordem. Ninguém entra, ninguém sai, ninguém telefona sem autorização. | H7: ambiente | L7: toda casa | M7: não
A8: c1-007 | B8: ~8h03 | C8: A Cliente do Cofre | D8: gerente | E8: presencial | F8: direta | G8: Meus documentos estão naquela sala. | H8: subtrama | L8: toda casa | M8: não
A9: c1-008 | B9: ~8h03 | C9: O Gerente | D9: cliente_cofre | E9: presencial | F9: direta | G9: Seus documentos estão seguros. | H9: subtrama | L9: toda casa | M9: não
A10: c1-009 | B10: ~8h03 | C10: A Cliente do Cofre | D10: gerente | E10: presencial | F10: direta | G10: Foi o que disseram sobre o dinheiro. | H10: subtrama | L10: toda casa | M10: não
A11: c1-010 | B11: 8h05 | C11: A Operadora da Central | D11: todos | E11: interfone | F11: indireta | G11: A câmera 3 ficou sem sinal durante oitenta e sete segundos. | H11: prova | L11: toda casa | M11: não | T11: Âncora 8h05 (janela sem imagem); fato fora da tabela de cobertura, fonte de núcleo.
A12: c1-011 | B12: ~8h05 | C12: O Técnico | D12: gerente | E12: presencial | F12: indireta | G12: Preciso passar. | H12: ambiente | L12: toda casa | M12: não | T12: 'O Técnico pediu passagem'.
A13: c1-012 | B13: ~8h05 | C13: O Gerente | D13: tecnico | E13: presencial | F13: direta | G13: Ninguém toca em nada. | H13: ambiente | L13: toda casa | M13: não
A14: c1-013 | B14: ~8h05 | C14: O Técnico | D14: gerente | E14: presencial | F14: direta | G14: Se o circuito está instável, o registro pode continuar se perdendo. | H14: ambiente | L14: toda casa | M14: não
A15: c1-014 | B15: ~8h05 | C15: O Gerente | D15: tecnico | E15: presencial | F15: direta | G15: Ou pode ser alterado por quem entende dele. | H15: pista falsa | L15: toda casa | M15: não | T15: Primeira insinuação contra o falso culpado (Técnico).
A16: c1-015 | B16: ~8h05 | C16: O Funcionário da Limpeza | D16: todos | E16: presencial | F16: direta | G16: Passei o rodo aqui às sete e quarenta e seis. | H16: reforço | I16: Arquivo limpo e vazio às 7h46 | L16: casa ≥ 8 | M16: sim | T16: Fonte primária na casa 6: Operadora (c1-020).
A17: c1-016 | B17: ~8h05 | C17: O Gerente | D17: limpeza | E17: presencial | F17: direta | G17: Tem certeza da hora? | H17: ambiente | L17: toda casa | M17: não | T17: Réplica a personagem de bloco: fica órfã sem a Limpeza.
A18: c1-017 | B18: ~8h05 | C18: O Funcionário da Limpeza | D18: gerente | E18: presencial | F18: direta | G18: A Central tocou a troca de turno. Eu estava terminando. | H18: reforço | I18: Arquivo limpo e vazio às 7h46 | L18: casa ≥ 8 | M18: sim
A19: c1-018 | B19: ~8h05 | C19: O Gerente | D19: limpeza | E19: presencial | F19: direta | G19: E o saco? | H19: ambiente | L19: toda casa | M19: não | T19: Fica órfã sem a Limpeza.
A20: c1-019 | B20: ~8h05 | C20: O Funcionário da Limpeza | D20: gerente | E20: presencial | F20: direta | G20: Não estava. | H20: reforço | I20: Arquivo limpo e vazio às 7h46 | L20: casa ≥ 8 | M20: sim
A21: c1-020 | B21: ~8h06 | C21: A Operadora da Central | D21: todos | E21: interfone | F21: indireta | G21: Confirmo a hora: na câmera 3, às sete e quarenta e seis, o balde saía do Arquivo Morto, e até a imagem cair, às sete e cinquenta e oito, ninguém mais entrou ali. | H21: prova | I21: Arquivo limpo e vazio às 7h46 | L21: toda casa | M21: não | T21: Fonte primária. Silencia que a câmera 3 voltou às 7h59:39 e deveria mostrar a Limpeza entrando no Arquivo às 8h01.
A22: c1-021 | B22: ~8h06 | C22: O Gerente | D22: limpeza | E22: presencial | F22: direta | G22: Quem tem a chave do armário daqui? | H22: subtrama | L22: toda casa | M22: não | T22: Pergunta dirigida à Limpeza; órfã sem ela (chave 17-B).
A23: c1-022 | B23: ~8h06 | C23: O Funcionário da Limpeza | D23: gerente | E23: presencial | F23: direta | G23: Eu. | H23: subtrama | L23: casa ≥ 8 | M23: sim
A24: c1-023 | B24: ~8h06 | C24: O Gerente | D24: limpeza | E24: presencial | F24: direta | G24: Só você? | H24: subtrama | L24: toda casa | M24: não | T24: Órfã sem a Limpeza.
A25: c1-024 | B25: ~8h06 | C25: O Funcionário da Limpeza | D25: gerente | E25: presencial | F25: direta | G25: Só eu. | H25: subtrama | L25: casa ≥ 8 | M25: sim | T25: Mentira (emprestou a 17-B ao Subgerente 7h35-7h47). Sem bloco 1, a pista da 17-B não é plantada aqui.
A26: c1-025 | B26: ~8h06 | C26: A Auditora | D26: todos | E26: presencial | F26: indireta | G26: Preciso de uma lanterna. | H26: ambiente | L26: toda casa | M26: não
A27: c1-026 | B27: ~8h06 | C27: A Cliente do Cofre | D27: todos | E27: presencial | F27: direta | G27: Eu vi esse saco ontem, na Antecâmara. Cheio. Tinha esse vinco perto da costura, como uma boca torta. | H27: prova | L27: toda casa | M27: não | T27: Reconhecimento do invólucro (vinco da véspera); fonte única, de núcleo.
A28: c1-027 | B28: ~8h06 | C28: O Gerente | D28: todos | E28: presencial | F28: direta | G28: Então é o malote. Houve subtração. | H28: pista falsa | L28: toda casa | M28: não
A29: c1-028 | B29: ~8h06 | C29: A Auditora | D29: gerente | E29: presencial | F29: direta | G29: Houve o reconhecimento de um invólucro. Ainda não sabemos o que havia dentro, quando saiu, nem se foi este o volume entregue. | H29: ambiente | L29: toda casa | M29: não
A30: c1-029 | B30: ~8h06 | C30: O Gerente | D30: auditora | E30: presencial | F30: direta | G30: Quatrocentos e oitenta mil. O sistema... | H30: ambiente | L30: toda casa | M30: não
A31: c1-030 | B31: ~8h06 | C31: A Auditora | D31: gerente | E31: presencial | F31: direta | G31: O sistema declara. Não testemunha. | H31: ambiente | L31: toda casa | M31: não
A32: c1-031 | B32: ~8h07 | C32: O Caixa Veterano | D32: todos | E32: presencial | F32: direta | G32: O malote que passou para a Eclusa estava com o lacre ML-8847. | H32: prova | L32: toda casa | M32: não | T32: Diferença de lacres (ML-8847 partiu); fonte de núcleo, confirmada pela Operadora às 8h07.
A33: c1-032 | B33: ~8h07 | C33: O Gerente | D33: todos | E33: presencial | F33: indireta | G33: Isso deve ser uma reetiquetagem operacional. | H33: pista falsa | L33: toda casa | M33: não
A34: c1-033 | B34: ~8h07 | C34: O Motorista | D34: todos | E34: rádio | F34: direta | G34: Na via está ML-8842. | H34: prova | I34: Lacre ML-8842 na via de papel | L34: toda casa | M34: não | T34: Fonte primária (apoio).
A35: c1-034 | B35: ~8h07 | C35: A Auditora | D35: seguranca_veiculo | E35: presencial | F35: direta | G35: E o senhor conferiu o quê? | H35: reforço | I35: Lacre ML-8842 na via de papel | L35: toda casa | M35: não | T35: Pergunta órfã sem o Segurança do Veículo.
A36: c1-035 | B36: ~8h07 | C36: O Segurança do Veículo | D36: auditora | E36: presencial | F36: direta | G36: A tela da Mesa. | H36: reforço | I36: Lacre ML-8842 na via de papel | L36: casa ≥ 10 | M36: sim
A37: c1-036 | B37: ~8h07 | C37: O Motorista | D37: todos | E37: rádio | F37: indireta | G37: Um carro parou duas vezes na esquina. A base recomenda retirada. | H37: subtrama | L37: toda casa | M37: não | T37: Perigo na rua; protocolo impede partida.
A38: c1-037 | B38: ~8h07 | C38: A Auditora | D38: todos | E38: presencial | F38: direta | G38: Quem imprimiu etiquetas esta manhã? | H38: prova | L38: toda casa | M38: não | T38: Fragmento térmico na cola do lacre.
A39: c1-038 | B39: ~8h07 | C39: O Caixa Veterano | D39: auditora | E39: presencial | F39: indireta | G39: A impressora de etiquetas fica na Gerência e só sai do modo de economia às sete e cinquenta e três. Eu não imprimi nada. | H39: prova | L39: toda casa | M39: não | T39: Fala fixa; na partida V é dita pelo impostor (impressão foi agendada às 6h58, não 'impressa' por ele) — tecnicamente não se desmente.
A40: c1-039 | B40: ~8h07 | C40: O Caixa Novato | D40: auditora | E40: presencial | F40: indireta | G40: Eu nem sei a senha. | H40: pista falsa | L40: toda casa | M40: não
A41: c1-040 | B41: ~8h07 | C41: A Operadora da Central | D41: auditora | E41: interfone | F41: indireta | G41: Preciso de tempo para consultar a fila. | H41: ambiente | L41: toda casa | M41: não
A42: c1-041 | B42: 8h07 | C42: A Operadora da Central | D42: todos | E42: interfone | F42: indireta | G42: Confirmo: o malote 41 atravessou a Eclusa às oito horas com ML-8847, e a troca de lacre consta no sistema, sem nome. | H42: prova | L42: toda casa | M42: não | T42: Âncora 8h07; fonte primária (registro via Operadora). Canal não explicitado (interfone inferido).
A43: c1-042 | B43: ~8h08 | C43: O Caixa Novato | D43: todos | E43: presencial | F43: direta | G43: Essa pasta não é minha. | H43: pista falsa | L43: toda casa | M43: não | T43: Pasta azul trocada (chave 17-B e senha da Estagiária).
A44: c1-043 | B44: ~8h08 | C44: O Gerente | D44: caixa_novato | E44: presencial | F44: direta | G44: Então é de quem? | H44: pista falsa | L44: toda casa | M44: não | T44: A resposta é gestual (Estagiária abre a própria pasta); sem bloco 3 a troca de pastas fica sem dona.
A45: c1-044 | B45: 8h10 | C45: O Monitor Remoto | D45: todos | E45: mensagem sem origem | F45: direta | G45: Procurem quem abriu antes. | H45: prova | I45: Porta lateral às 6h36 e 7h06 | L45: toda casa | M45: não | T45: Rádio da Central, sem origem. Intenção: a porta lateral aberta antes das chegadas; o grupo lê como o Novato (efeito de pista falsa). Monitor é do bloco 'completa': na casa 6 a mensagem precisa chegar mesmo assim (ela é anônima).

Sheet Cap 2
A1: ID | B1: Hora | C1: Quem fala | D1: Com quem | E1: Canal | F1: Tipo | G1: Fala original | H1: Função | I1: Prova | J1: Ajuste | K1: Variação G / V | L1: Condição (casa mínima) | M1: Sai se ausente | N1: Explosivo | O1: Calmo opaco | P1: Ingênuo | Q1: Leal cego | R1: Evasivo | S1: Burocrata | T1: Nota
A2: c2-001 | B2: 8h18 | C2: O Subgerente | D2: seguranca_interno | E2: registro | F2: direta | G2: Porta lateral. Possível tentativa. | H2: prova | I2: A ordem saiu da Gerência (estabilizador) | L2: casa ≥ 8 | M2: não | T2: Gravação do rádio reserva (7h58:05) reproduzida pela Operadora. Falante = impostor sorteado (G: gerente; V: caixa_veterano); voz irreconhecível; não marcado como ponto de ajuste.
A3: c2-002 | B3: ~8h18 | C3: O Operador de Rádio | D3: todos | E3: rádio | F3: direta | G3: A base não transmitiu. Nosso canal com vocês encerrou às sete e quarenta e nove. | H3: prova | I3: A ordem saiu da Gerência (estabilizador) | L3: toda casa | M3: não | T3: Vigia, mas do bloco 'completa': sem ele na casa 6, o Motorista pode dizer o mesmo.
A4: c2-003 | B4: ~8h18 | C4: O Gerente | D4: tecnico | E4: presencial | F4: indireta | G4: Esse áudio pode ter sido adulterado? | H4: ambiente | L4: toda casa | M4: não
A5: c2-004 | B5: ~8h18 | C5: O Técnico | D5: gerente | E5: presencial | F5: indireta | G5: Tudo pode; o problema é o rastro. | H5: ambiente | L5: toda casa | M5: não
A6: c2-005 | B6: ~8h19 | C6: O Técnico | D6: todos | E6: presencial | F6: direta | G6: É o estabilizador da impressora de etiquetas, o da Gerência. Fui eu que instalei. Pulsa assim desde o primeiro dia. | H6: prova | I6: A ordem saiu da Gerência (estabilizador) | L6: toda casa | M6: não | T6: Fonte primária.
A7: c2-006 | B7: ~8h19 | C7: A Estagiária | D7: todos | E7: presencial | F7: indireta | G7: Confirmo: é o estabilizador da Gerência. | H7: reforço | I7: A ordem saiu da Gerência (estabilizador) | L7: casa ≥ 12 | M7: sim | T7: Confirmação só com a cabeça.
A8: c2-007 | B8: ~8h20 | C8: O Segurança Interno | D8: todos | E8: presencial | F8: indireta | G8: Corri da Antecâmara à porta lateral. Pelo vidro, vi um homem de capa, de costas, conversando com um motoboy que tinha uma caixa no bagageiro. Bati no vidro; o homem ergueu a mão sem se virar. Não abri a porta. Esperei o motoboy partir, registrei 'sem tentativa' e voltei à Antecâmara. O malote estava na plataforma, lacrado. | H8: prova | I8: O Técnico estava fora | L8: toda casa | M8: não | T8: Plantação da exclusão do Técnico (colhida no Cap. 6); aqui a 'capa' ecoa a figura das 6h28 e funciona como pista falsa.
A9: c2-008 | B9: ~8h20 | C9: O Gerente | D9: seguranca_interno | E9: presencial | F9: direta | G9: E o rádio? Estava onde? | H9: ambiente | L9: toda casa | M9: não
A10: c2-009 | B10: ~8h20 | C10: O Segurança Interno | D10: gerente | E10: presencial | F10: direta | G10: No aparador da Gerência. Fora do carregador. | H10: prova | L10: toda casa | M10: não
A11: c2-010 | B11: ~8h20 | C11: O Gerente | D11: seguranca_interno | E11: presencial | F11: direta | G11: Um erro seu abriu a janela. | H11: ambiente | L11: toda casa | M11: não
A12: c2-011 | B12: ~8h20 | C12: O Segurança Interno | D12: gerente | E12: presencial | F12: direta | G12: E alguém estava esperando por ela. | H12: ambiente | L12: toda casa | M12: não
A13: c2-012 | B13: ~8h21 | C13: A Operadora da Central | D13: todos | E13: presencial | F13: direta | G13: Testei o rádio ontem, às dezenove e doze. | H13: pista falsa | L13: toda casa | M13: não | T13: Explica a lasca de esmalte lilás no botão.
A14: c2-013 | B14: ~8h21 | C14: O Gerente | D14: operadora | E14: presencial | F14: direta | G14: E não registrou por quê? | H14: subtrama | L14: toda casa | M14: não
A15: c2-014 | B15: ~8h21 | C15: A Operadora da Central | D15: gerente | E15: presencial | F15: indireta | G15: Foi a bateria, a rotina, a pressa. | H15: subtrama | L15: toda casa | M15: não | T15: Respostas verdadeiras que cobrem a omissão.
A16: c2-015 | B16: ~8h21 | C16: A Auditora | D16: operadora | E16: presencial | F16: indireta | G16: Entregue-me o seu bloco particular. | H16: subtrama | L16: toda casa | M16: não
A17: c2-016 | B17: ~8h22 | C17: A Cliente do Cofre | D17: gerente | E17: presencial | F17: indireta | G17: Preciso ir ao banheiro. | H17: subtrama | L17: toda casa | M17: não
A18: c2-017 | B18: ~8h22 | C18: O Gerente | D18: cliente_cofre | E18: presencial | F18: indireta | G18: Não. | H18: subtrama | L18: toda casa | M18: não
A19: c2-018 | B19: ~8h22 | C19: A Cliente do Cofre | D19: gerente | E19: presencial | F19: indireta | G19: Não sou funcionária nem suspeita. | H19: subtrama | L19: toda casa | M19: não
A20: c2-019 | B20: ~8h22 | C20: A Auditora | D20: cliente_cofre | E20: presencial | F20: indireta | G20: Neste momento, todos são testemunhas retidas, inclusive eu. | H20: ambiente | L20: toda casa | M20: não
A21: c2-020 | B21: ~8h22 | C21: O Caixa Novato | D21: todos | E21: presencial | F21: indireta | G21: Vi outro fio de lã vermelha, igual a esse, perto do saco. | H21: pista falsa | L21: toda casa | M21: não
A22: c2-021 | B22: ~8h22 | C22: O Gerente | D22: cliente_cofre | E22: presencial | F22: direta | G22: Abra a pasta. | H22: subtrama | L22: toda casa | M22: não
A23: c2-022 | B23: ~8h22 | C23: A Cliente do Cofre | D23: gerente | E23: presencial | F23: direta | G23: Não. | H23: subtrama | L23: toda casa | M23: não
A24: c2-023 | B24: ~8h22 | C24: O Gerente | D24: cliente_cofre | E24: presencial | F24: direta | G24: Se não há nada relacionado... | H24: subtrama | L24: toda casa | M24: não
A25: c2-024 | B25: ~8h22 | C25: A Cliente do Cofre | D25: gerente | E25: presencial | F25: direta | G25: Há coisas que não têm relação com o senhor e ainda assim são da minha vida. | H25: subtrama | L25: toda casa | M25: não
A26: c2-025 | B26: ~8h23 | C26: A Auditora | D26: todos | E26: presencial | F26: indireta | G26: A pasta será preservada, fechada, até existir um nexo real. | H26: subtrama | L26: toda casa | M26: não
A27: c2-026 | B27: ~8h23 | C27: A Cliente do Cofre | D27: auditora | E27: presencial | F27: indireta | G27: Obrigada. | H27: subtrama | L27: toda casa | M27: não | T27: 'Agradeceu sem gratidão'.
A28: c2-027 | B28: ~8h24 | C28: Registro / sistema | D28: todos | E28: registro | F28: indireta | G28: Rádio reserva pareado às 7h57:55 por cartão de proximidade da faixa administrativa; dois últimos dígitos corrompidos. | H28: prova | L28: toda casa | M28: não | T28: Histórico do rádio lido pela Estagiária (bloco 3) na Central. Na casa 6 precisa ser lido pela Operadora. Plantação de A7 (cartão), que fecha no Cap. 7.
A29: c2-028 | B29: ~8h24 | C29: A Auditora | D29: estagiaria | E29: presencial | F29: direta | G29: Quem tem cartão nessa faixa? | H29: prova | L29: toda casa | M29: não
A30: c2-029 | B30: ~8h24 | C30: A Estagiária | D30: auditora | E30: presencial | F30: direta | G30: O Gerente, o Subgerente, o tesoureiro e a manutenção. | H30: prova | L30: casa ≥ 12 | M30: não | T30: Fonte única da composição da faixa administrativa. SEM FONTE PRIMÁRIA NA CASA 6 (passar à Operadora). Nas casas sem Subgerente, ele continua citado (existe no mundo).
A31: c2-030 | B31: ~8h24 | C31: O Técnico | D31: todos | E31: presencial | F31: indireta | G31: O meu cartão está na maleta. | H31: pista falsa | L31: toda casa | M31: não
A32: c2-031 | B32: ~8h24 | C32: O Gerente | D32: todos | E32: presencial | F32: indireta | G32: Busquem a maleta e deixem-na fechada sobre a Mesa. | H32: pista falsa | L32: toda casa | M32: não | T32: Maleta fica 'sob os olhos do Segurança do Veículo' (bloco 2).
A33: c2-032 | B33: ~8h25 | C33: O Subgerente | D33: todos | E33: presencial | F33: direta | G33: Talvez tenham clonado algum. | H33: pista falsa | L33: casa ≥ 8 | M33: sim | T33: Sai nas casas sem Subgerente (canone.md).
A34: c2-033 | B34: ~8h25 | C34: O Técnico | D34: subgerente | E34: presencial | F34: direta | G34: Possível. Com equipamento. | H34: pista falsa | L34: toda casa | M34: não | T34: Réplica ao Subgerente: sem ele, fica órfã e o peso sobre a maleta precisa de outro gatilho.
A35: c2-034 | B35: ~8h26 | C35: A Farmacêutica | D35: subgerente | E35: presencial | F35: direta | G35: Cortou-se? | H35: reforço | I35: Fita estreita A3 | J35: A3 | K35: G: pergunta ao Gerente (fita estreita no indicador do Gerente); V: ao Caixa Veterano (indicador do Caixa Veterano). | L35: casa ≥ 12 | M35: sim | T35: Plantação da fita estreita depende só da Farmacêutica (bloco 3): nas casas 6 e 8 não há plantação no Cap. 2.
A36: c2-035 | B36: ~8h26 | C36: O Subgerente | D36: farmaceutica | E36: presencial | F36: direta | G36: Numa caixa de papelão. | H36: reforço | I36: Fita estreita A3 | J36: A3 | K36: G: responde o Gerente; V: responde o Caixa Veterano. | L36: casa ≥ 8 | M36: sim | T36: Na referência, o Subgerente; nas partidas G/V o falante é de núcleo, mas a fala só existe se a Farmacêutica perguntar.
A37: c2-036 | B37: ~8h26 | C37: A Farmacêutica | D37: caixa_novato | E37: presencial | F37: direta | G37: E você? | H37: reforço | I37: Fita estreita A3 | L37: casa ≥ 12 | M37: sim
A38: c2-037 | B38: ~8h26 | C38: O Caixa Novato | D38: farmaceutica | E38: presencial | F38: direta | G38: Numa nota nova. Peguei a fita no kit da Gerência. | H38: pista falsa | I38: Fita estreita A3 | L38: toda casa | M38: não | T38: Fita larga do kit (colhida no Cap. 7, cupom × kit). Depende da pergunta da Farmacêutica: na casa 6 precisa de outro interlocutor.
A39: c2-038 | B39: 8h29 | C39: O Operador de Rádio | D39: todos | E39: rádio | F39: indireta | G39: Envio o registro bruto da antecipação: chamada às seis e cinquenta e dois, de ramal interno, com código de tesouraria, quarenta e três segundos, sem gravação de voz. Origem: o telefone da Sala da Gerência. | H39: prova | L39: toda casa | M39: não | T39: Âncora 8h29. Operador de Rádio é do bloco 'completa': na casa 6 o registro precisa chegar por outro canal (Motorista/registro).
A40: c2-039 | B40: ~8h30 | C40: Registro / sistema | D40: todos | E40: registro | F40: indireta | G40: Crachás da Porta Giratória: Segurança Interno e Funcionário da Limpeza 7h10; Gerente 7h12; Subgerente 7h16; Caixa Veterano 7h21. | H40: prova | L40: toda casa | M40: não | T40: Lido pela Operadora. Não lista Operadora, Estagiária, Caixa Novato nem o Técnico (porta lateral 7h40).
A41: c2-040 | B41: ~8h30 | C41: A Auditora | D41: todos | E41: presencial | F41: direta | G41: Então às seis e cinquenta e dois alguém estava na Gerência, antes de qualquer crachá do dia. | H41: prova | L41: toda casa | M41: não
A42: c2-041 | B42: ~8h31 | C42: A Operadora da Central | D42: auditora | E42: presencial | F42: direta | G42: Tem mais uma coisa. | H42: subtrama | L42: toda casa | M42: não
A43: c2-042 | B43: ~8h31 | C43: A Operadora da Central | D43: auditora | E43: presencial | F43: direta | G43: Se isso aparecer amanhã, não cai só você. | H43: subtrama | L43: toda casa | M43: não | T43: Leitura da frase apagada na véspera (falante original não atribuído).
A44: c2-043 | B44: ~8h31 | C44: A Auditora | D44: todos | E44: presencial | F44: direta | G44: Era sobre o quê? | H44: subtrama | L44: toda casa | M44: não
A45: c2-044 | B45: ~8h31 | C45: O Gerente | D45: auditora | E45: presencial | F45: direta | G45: Manutenção. | H45: subtrama | L45: toda casa | M45: não | T45: Sem o Subgerente, perde-se o contraste das 'duas respostas'.
A46: c2-045 | B46: ~8h31 | C46: O Subgerente | D46: auditora | E46: presencial | F46: direta | G46: Pessoal. | H46: subtrama | L46: casa ≥ 8 | M46: sim | T46: Sai nas casas sem Subgerente (canone.md); o parágrafo 'Duas respostas para uma única conversa' precisa ser reescrito.
A47: c2-046 | B47: 8h35 | C47: Registro / sistema | D47: todos | E47: registro | F47: indireta | G47: ML-8847 | H47: prova | L47: toda casa | M47: não | T47: Impressora da Gerência imprime sozinha uma faixa branca e a etiqueta ML-8847; autoria oculta: reimpressão remota do Monitor Remoto (origem 'rede de segurança regional').

Sheet Cap 3
A1: ID | B1: Hora | C1: Quem fala | D1: Com quem | E1: Canal | F1: Tipo | G1: Fala original | H1: Função | I1: Prova | J1: Ajuste | K1: Variação G / V | L1: Condição (casa mínima) | M1: Sai se ausente | N1: Explosivo | O1: Calmo opaco | P1: Ingênuo | Q1: Leal cego | R1: Evasivo | S1: Burocrata | T1: Nota
A2: c3-001 | B2: ~8h35 | C2: O Gerente | D2: todos | E2: presencial | F2: indireta | G2: Recolham todos os cartões de acesso. | H2: subtrama | L2: toda casa | M2: não
A3: c3-002 | B3: ~8h35 | C3: A Auditora | D3: gerente | E3: presencial | F3: indireta | G3: Recuso. Sem registrar quem entrega qual cartão e a que horas, a coleta destrói a cadeia de prova. | H3: subtrama | L3: toda casa | M3: não
A4: c3-003 | B4: ~8h36 | C4: O Caixa Veterano | D4: todos | E4: presencial | F4: direta | G4: Houve uma reimpressão naquela noite. Com o sistema fechado. | H4: prova | L4: toda casa | M4: não | T4: Pista genuína fora da tabela de cobertura (planta a duplicidade de onze dias antes).
A5: c3-004 | B5: 8h38 | C5: A Operadora da Central | D5: todos | E5: presencial | F5: indireta | G5: Na fila deste terminal: a etiqueta das 7h53 não foi impressa por ninguém às 7h53. Foi agendada às 6h58, neste mesmo terminal, pela conta admin.local. No mesmo minuto, a mesma conta alterou o registro da remessa: onde se lia ML-8842, passou a constar ML-8847. | H5: prova | I5: Tarefa das 6h58 e lacre trocado no registro | L5: toda casa | M5: não | T5: Fonte: fila do terminal da Gerência, lida pela Operadora com a Auditora anotando; no texto o conteúdo vem pelo narrador — atribuído à Operadora, fonte primária da tabela.
A6: c3-005 | B6: 8h38 | C6: A Operadora da Central | D6: todos | E6: presencial | F6: direta | G6: Por isso a tela da Mesa mostrava o lacre novo. O sistema já esperava por ele. | H6: prova | I6: Tarefa das 6h58 e lacre trocado no registro | L6: toda casa | M6: não
A7: c3-006 | B7: 8h38 | C7: Registro / sistema | D7: todos | E7: registro | F7: indireta | G7: Reimpressão das 8h35 — origem: "acesso remoto de suporte". Sem indicação de onde. | H7: prova | L7: toda casa | M7: não | T7: Registro da fila da impressora; a origem é o oculto (Monitor Remoto), não identificado. Pista genuína fora da tabela.
A8: c3-007 | B8: ~8h39 | C8: A Auditora | D8: todos | E8: presencial | F8: direta | G8: Quem conhece a senha dessa conta? | H8: prova | I8: Senha ditada diante da tesouraria | L8: toda casa | M8: não
A9: c3-008 | B9: ~8h39 | C9: O Técnico | D9: auditora | E9: presencial | F9: direta | G9: Ninguém deveria. Fui eu que a criei, para manutenção. Mas numa pane, meses atrás, ditei em voz alta para quem estava em volta: o Gerente, o Subgerente, o tesoureiro e a estagiária. | H9: prova | I9: Senha ditada diante da tesouraria | L9: toda casa | M9: não | T9: Fonte primária da senha.
A10: c3-009 | B10: ~8h39 | C10: O Caixa Novato | D10: todos | E10: presencial | F10: direta | G10: É esta? | H10: reforço | I10: Senha ditada diante da tesouraria | L10: toda casa | M10: não | T10: Mostra o papel dobrado da pasta azul trocada (apoio; fica em toda casa).
A11: c3-010 | B11: ~8h39 | C11: A Estagiária | D11: todos | E11: presencial | F11: indireta | G11: É esta, sim. Anotei porque ninguém me disse onde guardar, e nunca a usei. | H11: reforço | I11: Senha ditada diante da tesouraria | L11: casa ≥ 12 | M11: sim | T11: Sem a Estagiária, ninguém confirma de quem é a letra do papel; a fala seguinte da Auditora fica sem base na casa de 6.
A12: c3-011 | B12: ~8h40 | C12: A Auditora | D12: todos | E12: presencial | F12: direta | G12: Então cinco pessoas ouviram. E uma delas a escreveu num papel que passou a manhã com outra. | H12: prova | I12: Senha ditada diante da tesouraria | L12: toda casa | M12: não | T12: A 2ª frase depende da confirmação da Estagiária (bloco3); ajustar na casa de 6.
A13: c3-012 | B13: ~8h40 | C13: O Gerente | D13: todos | E13: presencial | F13: indireta | G13: Revistem a maleta do Técnico. | H13: pista falsa | L13: toda casa | M13: não | T13: Leva à falsa pista do roteador e dos adaptadores.
A14: c3-013 | B14: ~8h41 | C14: O Técnico | D14: gerente | E14: presencial | F14: direta | G14: Isso aí mantém esta agência de pé. Sem nota, sem orçamento, sem obrigado. | H14: subtrama | L14: toda casa | M14: não | T14: Segredo inocente: peças reaproveitadas sem nota.
A15: c3-014 | B15: ~8h41 | C15: O Técnico | D15: todos | E15: presencial | F15: indireta | G15: Esta é a fotografia das 7h45: o conector da câmera 3 estava puxado até o limite, ainda preso. | H15: prova | L15: toda casa | M15: não | T15: Pista genuína fora da tabela (conector preparado).
A16: c3-015 | B16: ~8h41 | C16: O Técnico | D16: todos | E16: presencial | F16: direta | G16: Não foi desgaste. Foi preparado para cair com a vibração do exaustor. Às sete e cinquenta e oito o ventilador acelera para a cópia local. Quem fez isso conhecia o ciclo. | H16: prova | L16: toda casa | M16: não | T16: Planta o ciclo do exaustor.
A17: c3-016 | B17: ~8h42 | C17: A Auditora | D17: tecnico | E17: presencial | F17: direta | G17: Quem conhece? | H17: prova | L17: toda casa | M17: não
A18: c3-017 | B18: ~8h42 | C18: O Técnico | D18: auditora | E18: presencial | F18: direta | G18: Eu. A Central. A tesouraria, que aprovou a rotina de economia. E quem monta os relatórios de energia. | H18: prova | L18: toda casa | M18: não
A19: c3-018 | B19: ~8h42 | C19: A Auditora | D19: tecnico | E19: presencial | F19: direta | G19: E onde o senhor estava quando a câmera caiu? | H19: pista falsa | L19: toda casa | M19: não
A20: c3-019 | B20: ~8h42 | C20: O Técnico | D20: auditora | E20: presencial | F20: direta | G20: No Rack. Olhando o conector. | H20: pista falsa | L20: toda casa | M20: não | T20: Mentira do falso culpado (estava fora, com o motoboy); desfeita no fim do Cap. 6.
A21: c3-020 | B21: 8h44 | C21: O Motorista | D21: todos | E21: rádio | F21: indireta | G21: O carro da esquina voltou e parou diante da Vaga Blindada. | H21: ambiente | L21: toda casa | M21: não
A22: c3-021 | B22: 8h44 | C22: O Gerente | D22: motorista | E22: rádio | F22: indireta | G22: Parta imediatamente. | H22: ambiente | L22: toda casa | M22: não | T22: Obstáculo: ordens incompatíveis.
A23: c3-022 | B23: 8h44 | C23: A Auditora | D23: motorista | E23: rádio | F23: indireta | G23: Fiquem. | H23: ambiente | L23: toda casa | M23: não
A24: c3-023 | B24: ~8h46 | C24: A Auditora | D24: todos | E24: presencial | F24: direta | G24: Antes de ele partir, quero o peso do malote. | H24: prova | I24: Peso de 7,0 kg e composição | L24: toda casa | M24: não
A25: c3-024 | B25: ~8h47 | C25: O Motorista | D25: todos | E25: rádio | F25: indireta | G25: Registro da balança embarcada, feito às oito horas, na entrada: sete quilos. | H25: prova | I25: Peso de 7,0 kg e composição | L25: toda casa | M25: não | T25: Fonte primária do peso: a balança, lida pelo Motorista (apoio).
A26: c3-025 | B26: ~8h47 | C26: O Caixa Veterano | D26: todos | E26: presencial | F26: indireta | G26: Pela guia: quarenta e um maços de cem, doze de cinquenta, cinco de vinte. Cinco mil e oitocentas cédulas. Com o saco, o fecho e o lacre, a conta dá sete quilos. | H26: prova | I26: Peso de 7,0 kg e composição | L26: toda casa | M26: não | T26: Fonte primária da composição. A conclusão 'a conta dava sete quilos' está no narrador; atribuída a ele.
A27: c3-026 | B27: ~8h47 | C27: O Gerente | D27: todos | E27: presencial | F27: direta | G27: Pode ser papel cortado no tamanho. | H27: pista falsa | L27: toda casa | M27: não
A28: c3-027 | B28: ~8h47 | C28: O Caixa Veterano | D28: gerente | E28: presencial | F28: direta | G28: Papel não tem o mesmo peso de cédula maço por maço. Mas só a contagem prova. | H28: prova | I28: Peso de 7,0 kg e composição | L28: toda casa | M28: não
A29: c3-028 | B29: 8h48 | C29: O Transportador | D29: auditora | E29: rádio | F29: indireta | G29: Peço licença para pegar o malote. | H29: ambiente | L29: casa ≥ 13 | M29: sim | T29: Dentro do compartimento do carro-forte.
A30: c3-029 | B30: 8h48 | C30: O Transportador | D30: todos | E30: rádio | F30: direta | G30: Pesa o que pesava às oito. E às oito pesava o que a guia diz. Papel cortado não assenta assim no fundo. | H30: reforço | I30: Peso de 7,0 kg e composição | L30: casa ≥ 13 | M30: sim | T30: Reforço da balança (fonte primária: Motorista). A virada do fim do terço cita 'a balança e a mão do Transportador'; na casa sem ele a virada fica só com a balança e o Caixa Veterano.
A31: c3-030 | B31: ~8h49 | C31: A Auditora | D31: operador_radio | E31: rádio | F31: indireta | G31: Peço à base que receba o volume sob quarentena, filme a abertura e conte maço por maço. | H31: prova | L31: toda casa | M31: não | T31: Prepara a contagem da base (Cap. 5).
A32: c3-031 | B32: ~8h49 | C32: O Operador de Rádio | D32: auditora | E32: rádio | F32: indireta | G32: Autorizado. | H32: prova | L32: toda casa | M32: não | T32: Operador de Rádio é da casa 'completa', mas aqui é fonte primária usada em toda casa; precisa estar disponível (ou ter voz substituta) na casa de 6.
A33: c3-032 | B33: ~8h50 | C33: O Caixa Novato | D33: todos | E33: presencial | F33: direta | G33: Então ninguém roubou. | H33: ambiente | L33: toda casa | M33: não
A34: c3-033 | B34: ~8h50 | C34: A Auditora | D34: caixa_novato | E34: presencial | F34: direta | G34: Então alguém arriscou tudo para trocar um saco. E não levou um centavo. | H34: prova | L34: toda casa | M34: não | T34: Fecha a virada (queda da leitura de roubo).
A35: c3-034 | B35: ~8h50 | C35: Registro / sistema | D35: todos | E35: registro | F35: indireta | G35: Verso da etiqueta das 7h53, contra a luz: 96.000 (números transferidos de outro papel ainda quente). Na fila da impressora, logo abaixo da etiqueta, uma segunda página impressa no mesmo minuto: arquivo ajuste_96. | H35: prova | L35: toda casa | M35: não | T35: Observação narrada sem falante; no jogo precisa de um portador (Auditora ou Operadora). Pista genuína fora da tabela.

Sheet Cap 4
A1: ID | B1: Hora | C1: Quem fala | D1: Com quem | E1: Canal | F1: Tipo | G1: Fala original | H1: Função | I1: Prova | J1: Ajuste | K1: Variação G / V | L1: Condição (casa mínima) | M1: Sai se ausente | N1: Explosivo | O1: Calmo opaco | P1: Ingênuo | Q1: Leal cego | R1: Evasivo | S1: Burocrata | T1: Nota
A2: c4-001 | B2: ~8h52 | C2: O Técnico | D2: todos | E2: presencial | F2: direta | G2: Isso não foi há oitenta e sete segundos. Isso foi agora há pouco. Com a gente trancado aqui. | H2: prova | L2: toda casa | M2: não | T2: Cabo queimado às 8h31 (encobrimento do Gerente, fixo). Pista fora da tabela.
A3: c4-002 | B3: ~8h53 | C3: O Gerente | D3: todos | E3: presencial | F3: indireta | G3: Quero revistar todos. | H3: subtrama | L3: toda casa | M3: não
A4: c4-003 | B4: ~8h53 | C4: A Auditora | D4: gerente | E4: presencial | F4: indireta | G4: Recuso uma humilhação coletiva sem método. Proponho interrogar o lugar antes das pessoas. | H4: subtrama | L4: toda casa | M4: não
A5: c4-004 | B5: 9h05 | C5: O Técnico | D5: todos | E5: presencial | F5: indireta | G5: Da Mesa de Recebimento até a porta do Arquivo Morto: vinte e seis segundos sem pressa, dezoito correndo. Do Arquivo à Antecâmara, seis. | H5: prova | L5: toda casa | M5: não | T5: Tempos do mapa (fora da tabela de cobertura, mas essenciais para a simulação).
A6: c4-005 | B6: 9h05 | C6: A Auditora | D6: tecnico | E6: presencial | F6: indireta | G6: Simule a troca com um saco de reserva e blocos de papel: abrir, passar o conteúdo, fechar, colar a etiqueta. | H6: prova | L6: toda casa | M6: não
A7: c4-006 | B7: 9h05 | C7: O Técnico | D7: todos | E7: presencial | F7: indireta | G7: Quarenta segundos. Somado tudo, ida, troca, descarte e volta, a rota pelo corredor passa de noventa segundos. | H7: prova | L7: toda casa | M7: não | T7: Soma atribuída ao Técnico; no texto vem pelo narrador.
A8: c4-007 | B8: ~9h06 | C8: O Técnico | D8: todos | E8: presencial | F8: direta | G8: Não cabe. Pelo corredor, quem fizesse isso estaria na frente da câmera quando ela voltou. | H8: prova | L8: toda casa | M8: não
A9: c4-008 | B9: ~9h07 | C9: O Funcionário da Limpeza | D9: auditora | E9: presencial | F9: direta | G9: Alguém pisou aqui depois que eu passei. | H9: reforço | I9: Pegadas até o fundo do Rack | L9: casa ≥ 8 | M9: sim | T9: A descrição das meias-luas até o fundo do Rack está no narrador; a Auditora (fonte primária) só tem a pergunta seguinte. Na casa 6 falta uma fala dela que descreva as pegadas.
A10: c4-009 | B10: ~9h07 | C10: A Auditora | D10: tecnico | E10: presencial | F10: direta | G10: Para onde vai uma pegada que termina numa parede? | H10: prova | I10: Pegadas até o fundo do Rack | L10: toda casa | M10: não | T10: Fonte primária das pegadas, mas só em forma de pergunta; precisa de fala descritiva (lanterna rasante, meias-luas saindo do cesto até o Nicho do Rack).
A11: c4-010 | B11: ~9h08 | C11: O Técnico | D11: todos | E11: presencial | F11: direta | G11: Eu uso quando a porta do Rack emperra. Hoje cedo vi a poeira riscada aqui no fundo. Achei que tinha sido eu. | H11: prova | I11: A passagem | L11: toda casa | M11: não | T11: Abre a passagem; colhe a poeira riscada do prólogo.
A12: c4-011 | B12: ~9h09 | C12: O Técnico | D12: todos | E12: presencial | F12: indireta | G12: Pela passagem: da Gerência ao Rack, quinze segundos, sem câmera. Do Rack ao Arquivo, quatro. Exposto à câmera, só o trecho entre o Arquivo e a Antecâmara, menos de setenta segundos. Cabe. | H12: prova | I12: A passagem | L12: toda casa | M12: não
A13: c4-012 | B13: ~9h10 | C13: A Auditora | D13: todos | E13: presencial | F13: indireta | G13: Cada um diga onde esteve durante a janela. Vou escrever numa coluna separada: declarações, não fatos. | H13: prova | I13: Quem estava onde na janela A5 | L13: toda casa | M13: não
A14: c4-013 | B14: ~9h10 | C14: O Gerente | D14: auditora | E14: presencial | F14: indireta | G14: Eu estava com a senhora e com a Cliente do Cofre diante da Porta Giratória. | H14: prova | I14: Quem estava onde na janela A5 | J14: A5 | K14: S (referência) e V: igual, verdadeira (Auditora, Cliente, câmera 1). G: diz 'Ao telefone' — mentira (ramal da Gerência sem chamada entre 7h50 e 8h10; câmera 1 o mostra entrando na divisória às 7h57:50). | L14: toda casa | M14: não | T14: Não marcada ^A5^ no texto, mas muda na partida G (Gerente impostor).
A15: c4-014 | B15: ~9h10 | C15: O Caixa Veterano | D15: auditora | E15: presencial | F15: indireta | G15: Eu estava na Mesa de Recebimento, esperando o malote. | H15: prova | I15: Quem estava onde na janela A5 | J15: A5 | K15: S e G: igual, verdadeira (câmera 2). V: mesma frase, mas é a mentira (câmera 2 mostra a Mesa vazia até 8h00:02; reforço: Segurança do Veículo). | L15: toda casa | M15: não | T15: Não marcada ^A5^ no texto; o texto é igual nas três partidas, mas na V é a mentira.
A16: c4-015 | B16: ~9h10 | C16: O Subgerente | D16: auditora | E16: presencial | F16: indireta | G16: Eu estava nos Guichês, buscando a guia impressa. | H16: prova | I16: Quem estava onde na janela A5 | J16: A5 | K16: S (referência): mentira (câmera 2 só o mostra às 8h00:05; reforço: Estagiária). G e V: mesma frase, verdadeira (câmera 2). Nas casas sem o Subgerente (casa 6 de G e V) a fala sai. | L16: casa ≥ 8 | M16: sim | T16: Ponto marcado ^A5^. Na referência é a mentira desmentida no Cap. 7 pela câmera 2.
A17: c4-016 | B17: ~9h10 | C17: A Estagiária | D17: auditora | E17: presencial | F17: indireta | G17: Eu estava recolhendo folhas atrás dos Guichês. | H17: ambiente | L17: casa ≥ 12 | M17: sim
A18: c4-017 | B18: ~9h10 | C18: A Operadora da Central | D18: auditora | E18: presencial | F18: indireta | G18: Eu estava na Central. | H18: ambiente | L18: toda casa | M18: não
A19: c4-018 | B19: ~9h10 | C19: O Funcionário da Limpeza | D19: auditora | E19: presencial | F19: indireta | G19: Eu estava no Saguão, com o balde. | H19: ambiente | L19: casa ≥ 8 | M19: sim
A20: c4-019 | B20: ~9h10 | C20: O Técnico | D20: auditora | E20: presencial | F20: direta | G20: No Rack. | H20: pista falsa | L20: toda casa | M20: não | T20: Mentira do falso culpado; única declaração na boca da passagem.
A21: c4-020 | B21: ~9h11 | C21: O Caixa Novato | D21: auditora | E21: presencial | F21: indireta | G21: Eu estava no almoxarifado. | H21: pista falsa | L21: toda casa | M21: não | T21: Mentira: não existe almoxarifado no corredor.
A22: c4-021 | B22: ~9h11 | C22: O Caixa Novato | D22: auditora | E22: presencial | F22: indireta | G22: Menti. Durante a janela, estive trancado no banheiro dos funcionários, tentando não vomitar. | H22: subtrama | L22: toda casa | M22: não
A23: c4-022 | B23: ~9h11 | C23: O Gerente | D23: caixa_novato | E23: presencial | F23: direta | G23: Você tinha a chave, a senha e não sabe dizer onde estava. | H23: pista falsa | L23: toda casa | M23: não
A24: c4-023 | B24: ~9h11 | C24: O Caixa Novato | D24: gerente | E24: presencial | F24: direta | G24: Eu sei. Estava sentado no chão do banheiro. E a parede raspou. Duas vezes. | H24: prova | I24: A parede raspou duas vezes | L24: toda casa | M24: não | T24: Fonte primária (apoio).
A25: c4-024 | B25: ~9h11 | C25: O Gerente | D25: caixa_novato | E25: presencial | F25: direta | G25: Raspou? | H25: prova | I25: A parede raspou duas vezes | L25: toda casa | M25: não | T25: Falante não identificado no texto; atribuído ao Gerente pelo fluxo da cena.
A26: c4-025 | B26: ~9h11 | C26: O Caixa Novato | D26: todos | E26: presencial | F26: direta | G26: Como uma gaveta pesada. Uma vez logo que o rádio chamou. Outra quase dois minutos depois, logo depois de a imagem voltar. | H26: prova | I26: A parede raspou duas vezes | L26: toda casa | M26: não | T26: Pela rota do cânone, a volta pela Gerência é às 7h59:54 (1 min 48 s depois da ordem), não 'quase um minuto e meio'.
A27: c4-026 | B27: ~9h12 | C27: A Farmacêutica | D27: todos | E27: presencial | F27: indireta | G27: Assumo: entreguei as cápsulas sem receita. Reconheço uma crise quando vejo uma. | H27: subtrama | L27: casa ≥ 12 | M27: sim
A28: c4-027 | B28: ~9h12 | C28: O Segurança Interno | D28: farmaceutica | E28: presencial | F28: indireta | G28: Por que a senhora protegeria um rapaz quase desconhecido? | H28: subtrama | L28: toda casa | M28: não | T28: Apoio, mas a fala só existe se a Farmacêutica (bloco3) estiver na casa.
A29: c4-028 | B29: ~9h12 | C29: O Funcionário da Limpeza | D29: todos | E29: presencial | F29: indireta | G29: Confesso: emprestei a chave 17-B, das sete e trinta e cinco às sete e quarenta e sete. | H29: subtrama | L29: casa ≥ 8 | M29: sim | T29: Na casa sem o 1º bloco o empréstimo acontece sem ser dito.
A30: c4-029 | B30: ~9h12 | C30: O Subgerente | D30: todos | E30: presencial | F30: indireta | G30: Confirmo. Fui buscar no armário do Arquivo um espelho antigo, de um reprocessamento, para conferir antes da auditoria. | H30: subtrama | L30: casa ≥ 8 | M30: sim | T30: Segredo inocente do Subgerente (na referência, o impostor).
A31: c4-030 | B31: ~9h12 | C31: O Gerente | D31: limpeza | E31: presencial | F31: indireta | G31: Isso é caso de demissão. | H31: subtrama | L31: toda casa | M31: não
A32: c4-031 | B32: ~9h12 | C32: O Funcionário da Limpeza | D32: gerente | E32: presencial | F32: indireta | G32: O banco aceitou durante anos os meus favores não registrados e só chama de irregularidade o favor que deixa rastro. | H32: subtrama | L32: casa ≥ 8 | M32: sim
A33: c4-032 | B33: 9h12 | C33: O Padeiro | D33: auditora | E33: telefone | F33: indireta | G33: Às seis e vinte e oito, uma figura de capa e guarda-chuva de cabo claro atravessou minha porta de serviço com uma sacola pesada. Demorei a contar porque vendo café por ali antes da hora. | H33: prova | L33: casa ≥ 10 | M33: não | T33: Figura das 6h28 só vem do Padeiro (bloco2); não consta da tabela de cobertura — SEM FONTE PRIMÁRIA NA CASA 6 para a figura/sacola e para a falsa pista do guarda-chuva que vem a seguir.
A34: c4-033 | B34: ~9h13 | C34: O Gerente | D34: todos | E34: presencial | F34: direta | G34: Cabo claro. | H34: pista falsa | L34: toda casa | M34: não | T34: Depende da fala do Padeiro; sem ele a falsa pista da farinha no guarda-chuva perde o gatilho.
A35: c4-034 | B35: ~9h13 | C35: A Auditora | D35: gerente | E35: presencial | F35: direta | G35: Comprei café às sete e trinta e oito. Pela frente. | H35: pista falsa | L35: toda casa | M35: não | T35: Explica a farinha na ponteira do guarda-chuva (falsa pista).
A36: c4-035 | B36: ~9h13 | C36: O Gerente | D36: auditora | E36: presencial | F36: direta | G36: E às seis e vinte e oito? | H36: pista falsa | L36: toda casa | M36: não
A37: c4-036 | B37: ~9h13 | C37: A Auditora | D37: gerente | E37: presencial | F37: direta | G37: Dormindo. Sozinha. Sem testemunha. | H37: pista falsa | L37: toda casa | M37: não
A38: c4-037 | B38: ~9h14 | C38: O Gerente | D38: todos | E38: presencial | F38: indireta | G38: A auditoria pode ter criado a crise para confirmar as próprias suspeitas. | H38: pista falsa | L38: toda casa | M38: não
A39: c4-038 | B39: ~9h14 | C39: A Auditora | D39: gerente | E39: presencial | F39: direta | G39: A Gerência é a sua sala. A ordem saiu de lá. A passagem começa lá. | H39: prova | I39: A passagem | L39: toda casa | M39: não
A40: c4-039 | B40: ~9h14 | C40: O Gerente | D40: auditora | E40: presencial | F40: direta | G40: Minha sala não é minha culpa. | H40: ambiente | L40: toda casa | M40: não
A41: c4-040 | B41: 9h25 | C41: O Operador de Rádio | D41: todos | E41: rádio | F41: direta | G41: A base abriu o malote 41 sob filmagem. Contagem em andamento. | H41: prova | L41: toda casa | M41: não | T41: Operador de Rádio é da casa 'completa', mas aqui é fonte primária usada em toda casa; precisa estar disponível (ou ter voz substituta) na casa de 6.

Sheet Cap 5
A1: ID | B1: Hora | C1: Quem fala | D1: Com quem | E1: Canal | F1: Tipo | G1: Fala original | H1: Função | I1: Prova | J1: Ajuste | K1: Variação G / V | L1: Condição (casa mínima) | M1: Sai se ausente | N1: Explosivo | O1: Calmo opaco | P1: Ingênuo | Q1: Leal cego | R1: Evasivo | S1: Burocrata | T1: Nota
A2: c5-001 | B2: 9h31 | C2: O Operador de Rádio | D2: todos | E2: rádio | F2: direta | G2: Quatrocentos e oitenta mil. Composição idêntica à guia. Todas verdadeiras. | H2: prova | L2: toda casa | M2: não | T2: Operador de Rádio é da casa 'completa', mas aqui é fonte primária usada em toda casa; precisa estar disponível (ou ter voz substituta) na casa de 6. A contagem da base é cânone fixo, mas não consta da tabela de cobertura.
A3: c5-002 | B3: ~9h31 | C3: O Caixa Novato | D3: todos | E3: presencial | F3: direta | G3: E se alguém colocou? | H3: prova | I3: "E se alguém colocou?" | L3: toda casa | M3: não | T3: Fonte primária (apoio). O reforço da Farmacêutica não tem fala no texto (só o olhar).
A4: c5-003 | B4: ~9h31 | C4: O Gerente | D4: caixa_novato | E4: presencial | F4: direta | G4: Ninguém põe dinheiro num banco escondido. | H4: ambiente | L4: toda casa | M4: não
A5: c5-004 | B5: ~9h32 | C5: O Caixa Novato | D5: gerente | E5: presencial | F5: direta | G5: Põe. Quando o caixa não fecha. Eu já pus vinte reais do meu bolso no primeiro mês, para ninguém saber que eu tinha errado. | H5: prova | I5: "E se alguém colocou?" | L5: toda casa | M5: não
A6: c5-005 | B6: ~9h33 | C6: A Operadora da Central | D6: todos | E6: presencial | F6: indireta | G6: Nas consolidações do Cofre, a sequência está limpa, dia após dia, exceto por um degrau de noventa e seis mil reais, onze dias atrás. O depósito do frigorífico aparece duas vezes: às 18h54 e às 19h11. | H6: prova | I6: Duplicidade de R$ 96.000 | L6: toda casa | M6: não | T6: Lido em conjunto com o Caixa Veterano no terminal dos Guichês; conteúdo vem pelo narrador.
A7: c5-006 | B7: ~9h33 | C7: O Gerente | D7: todos | E7: presencial | F7: direta | G7: Dois depósitos? | H7: prova | I7: Duplicidade de R$ 96.000 | L7: toda casa | M7: não
A8: c5-007 | B8: ~9h33 | C8: O Caixa Veterano | D8: gerente | E8: presencial | F8: direta | G8: Um recibo. Fui eu que contei. Noventa e seis mil, uma vez. | H8: prova | I8: Duplicidade de R$ 96.000 | L8: toda casa | M8: não
A9: c5-008 | B9: ~9h34 | C9: A Operadora da Central | D9: todos | E9: presencial | F9: indireta | G9: Desde aquela noite, o sistema guarda noventa e seis mil reais que nenhuma mão tocou. | H9: prova | I9: Duplicidade de R$ 96.000 | L9: toda casa | M9: não | T9: Liga a duplicidade ao '96.000' fantasma do Cap. 3.
A10: c5-009 | B10: ~9h35 | C10: A Operadora da Central | D10: todos | E10: presencial | F10: indireta | G10: Silêncio. Vou pôr no alto-falante o microfone ambiente da Central. | H10: ambiente | L10: toda casa | M10: não
A11: c5-010 | B11: ~9h35 | C11: Registro / sistema | D11: todos | E11: registro | F11: indireta | G11: Microfone ambiente da Central: 7h58:05, a ordem. 7h58:12, um estalo seco quando a imagem cai. Depois, quase nada: o ventilador do Rack, a chuva no telhado. 7h59:24, um clangor curto de metal. | H11: prova | I11: Tampa do cesto às 7h59:24 | L11: toda casa | M11: não | T11: Gravação reproduzida pela Operadora.
A12: c5-011 | B12: ~9h35 | C12: A Operadora da Central | D12: todos | E12: presencial | F12: direta | G12: A tampa do cesto do Arquivo. Ouço esse som toda manhã, quando a limpeza esvazia. | H12: prova | I12: Tampa do cesto às 7h59:24 | L12: toda casa | M12: não | T12: Fonte primária.
A13: c5-012 | B13: ~9h35 | C13: O Funcionário da Limpeza | D13: operadora | E13: presencial | F13: indireta | G13: Confirmo. | H13: reforço | I13: Tampa do cesto às 7h59:24 | L13: casa ≥ 8 | M13: sim | T13: No texto é só um aceno de cabeça.
A14: c5-013 | B14: ~9h35 | C14: Registro / sistema | D14: todos | E14: registro | F14: indireta | G14: Microfone ambiente da Central: 7h59:39, a imagem volta. | H14: prova | I14: Tampa do cesto às 7h59:24 | L14: toda casa | M14: não
A15: c5-014 | B15: ~9h36 | C15: O Caixa Novato | D15: todos | E15: presencial | F15: indireta | G15: O primeiro raspado veio logo depois da ordem. O segundo, logo depois de a imagem voltar. | H15: prova | I15: A parede raspou duas vezes | L15: toda casa | M15: não | T15: Contradiz o cânone: o retorno à Gerência é às 7h59:54, depois de a imagem voltar (7h59:39).
A16: c5-015 | B16: ~9h36 | C16: A Auditora | D16: todos | E16: presencial | F16: direta | G16: Então alguém saiu da parede, foi ao Arquivo, ao cesto, e voltou para a parede. Com a câmera cega o tempo todo em que esteve à vista dela. | H16: prova | L16: toda casa | M16: não
A17: c5-016 | B17: ~9h37 | C17: A Auditora | D17: operadora | E17: presencial | F17: indireta | G17: Quero o registro do sensor da porta lateral. | H17: prova | I17: Porta lateral às 6h36 e 7h06 | L17: toda casa | M17: não | T17: A ligação com 'Procurem quem abriu antes' é pensamento da Auditora, não fala.
A18: c5-017 | B18: 9h40 | C18: Registro / sistema | D18: todos | E18: registro | F18: indireta | G18: Sensor da porta lateral (central regional): 6h36, aberta por fora, com chave mecânica. 7h06, aberta por dentro, pela barra. 7h40, por fora, com chave. 7h55, aberta por dentro, pela barra; depois, repetido até 7h59:51: porta não travada. | H18: prova | I18: Porta lateral às 6h36 e 7h06 | L18: toda casa | M18: não | T18: Fonte primária: sensor, relatado pela Operadora (registro só recebido pela central regional).
A19: c5-018 | B19: ~9h40 | C19: O Técnico | D19: todos | E19: presencial | F19: direta | G19: Com chuva, a lingueta não trava sozinha. | H19: prova | L19: toda casa | M19: não
A20: c5-019 | B20: ~9h41 | C20: A Auditora | D20: todos | E20: presencial | F20: indireta | G20: Às 6h36, nenhum crachá do dia tinha passado pela Porta Giratória. Alguém abriu antes. | H20: prova | I20: Porta lateral às 6h36 e 7h06 | L20: toda casa | M20: não | T20: No texto é discurso indireto livre (pensamento); precisa ser verbalizado no jogo.
A21: c5-020 | B21: ~9h41 | C21: A Auditora | D21: todos | E21: presencial | F21: direta | G21: Quem tem chave da porta lateral? | H21: prova | L21: toda casa | M21: não
A22: c5-021 | B22: ~9h41 | C22: O Subgerente | D22: auditora | E22: presencial | F22: direta | G22: A escala de abertura. O Gerente, eu e o tesoureiro. | H22: reforço | L22: casa ≥ 8 | M22: sim | T22: Fala do Subgerente que sai nas casas sem ele (canone.md). Sem substituto: na casa 6 ninguém lista a escala de abertura como portadora da chave.
A23: c5-022 | B23: ~9h41 | C23: O Funcionário da Limpeza | D23: auditora | E23: presencial | F23: direta | G23: Eu. | H23: reforço | L23: casa ≥ 8 | M23: sim | T23: Sai sem o 1º bloco; na casa 6 só o Técnico responde.
A24: c5-023 | B24: ~9h41 | C24: O Técnico | D24: auditora | E24: presencial | F24: direta | G24: Eu. | H24: prova | L24: toda casa | M24: não
A25: c5-024 | B25: 9h43 | C25: O Padeiro | D25: auditora | E25: registro | F25: indireta | G25: Envio duas fotografias da câmera da minha porta de serviço: às 6h36, uma figura de capa e guarda-chuva de cabo claro diante da porta lateral da agência, com uma sacola esportiva; às 7h06, a mesma figura saindo, sem a sacola. O guarda-chuva cobre o rosto nas duas. | H25: reforço | I25: Porta lateral às 6h36 e 7h06 | L25: casa ≥ 10 | M25: sim | T25: Fotografias enviadas pelo Padeiro. Reforço do sensor, mas a sacola só aparece aqui.
A26: c5-025 | B26: ~9h43 | C26: A Auditora | D26: todos | E26: presencial | F26: direta | G26: A sacola ficou lá dentro. Onde? | H26: prova | I26: Dinheiro na caixa de 1998 | L26: toda casa | M26: não | T26: Depende das fotografias do Padeiro (bloco2): na casa 6 ninguém mencionou sacola — ajustar.
A27: c5-026 | B27: ~9h44 | C27: O Funcionário da Limpeza | D27: todos | E27: presencial | F27: indireta | G27: Às sete e quarenta e seis ela estava dois dedos para fora, e eu a empurrei de volta. | H27: reforço | I27: Dinheiro na caixa de 1998 | L27: casa ≥ 8 | M27: sim
A28: c5-027 | B28: ~9h44 | C28: O Caixa Veterano | D28: todos | E28: presencial | F28: direta | G28: Cinta de maço. De cem. | H28: prova | I28: Dinheiro na caixa de 1998 | L28: toda casa | M28: não | T28: Fonte primária. A caixa vazia, o anel de umidade e a tira 'R$ 10.000' estão no narrador.
A29: c5-028 | B29: ~9h46 | C29: A Operadora da Central | D29: todos | E29: presencial | F29: indireta | G29: Na noite de onze dias atrás, o sistema congelou às 19h03, durante uma atualização remota. O usuário era admin.local. | H29: pista falsa | L29: toda casa | M29: não | T29: Fato do cânone usado como falsa pista de autoria contra o Técnico.
A30: c5-029 | B30: ~9h46 | C30: O Técnico | D30: todos | E30: presencial | F30: direta | G30: Fui eu. Atualizei de casa, porque não havia orçamento para vir. O sistema travou. Quando voltou, alguém reprocessou a fila. | H30: pista falsa | L30: toda casa | M30: não
A31: c5-030 | B31: ~9h46 | C31: A Auditora | D31: tecnico | E31: presencial | F31: direta | G31: E o senhor sabia que a duplicidade tinha nascido do seu travamento? | H31: pista falsa | L31: toda casa | M31: não
A32: c5-031 | B32: ~9h46 | C32: O Técnico | D32: auditora | E32: presencial | F32: direta | G32: Soube agora. | H32: pista falsa | L32: toda casa | M32: não
A33: c5-032 | B33: ~9h48 | C33: O Gerente | D33: todos | E33: presencial | F33: indireta | G33: A conta é do Técnico. A chave da porta lateral também. Ele conhece a passagem e o ciclo do exaustor, tem um cartão na faixa administrativa e diz ter estado no Rack durante a janela. E tem um motivo: o próprio remendo criou o dinheiro sem corpo. | H33: pista falsa | L33: toda casa | M33: não
A34: c5-033 | B34: ~9h48 | C34: O Gerente | D34: todos | E34: presencial | F34: direta | G34: Quem quisesse esconder o erro teria pressa em cobri-lo. | H34: pista falsa | L34: toda casa | M34: não
A35: c5-034 | B35: ~9h49 | C35: A Auditora | D35: todos | E35: presencial | F35: direta | G35: Ainda não sabemos de onde vieram noventa e seis mil reais em espécie. | H35: prova | L35: toda casa | M35: não
A36: c5-035 | B36: 9h56 | C36: O Operador de Rádio | D36: todos | E36: rádio | F36: direta | G36: Encontrei um registro na rota de ontem. Às dezesseis horas, a transportadora levou um suprimento extraordinário de noventa e seis mil reais à agência 0392, para um saque agendado em espécie. O beneficiário é funcionário da agência 0688. O nome não consta no nosso sistema. | H36: prova | I36: Suprimento à 0392 | L36: toda casa | M36: não | T36: Operador de Rádio é da casa 'completa', mas aqui é fonte primária usada em toda casa; precisa estar disponível (ou ter voz substituta) na casa de 6.
A37: c5-036 | B37: ~9h56 | C37: O Caixa Novato | D37: todos | E37: presencial | F37: direta | G37: Alguém daqui tirou noventa e seis mil ontem. | H37: prova | I37: Suprimento à 0392 | L37: toda casa | M37: não

Sheet Cap 6
A1: ID | B1: Hora | C1: Quem fala | D1: Com quem | E1: Canal | F1: Tipo | G1: Fala original | H1: Função | I1: Prova | J1: Ajuste | K1: Variação G / V | L1: Condição (casa mínima) | M1: Sai se ausente | N1: Explosivo | O1: Calmo opaco | P1: Ingênuo | Q1: Leal cego | R1: Evasivo | S1: Burocrata | T1: Nota
A2: c6-001 | B2: 10h04 | C2: Registro / sistema | D2: todos | E2: registro | F2: indireta | G2: Arquivo ajuste_96 recuperado por cópia automática do servidor, que guarda tudo o que passa pela impressora. Planilha pequena com as colunas "valor", "origem", "malote" e "cofre"; na linha da origem, só uma palavra: "própria". | H2: revelação | L2: toda casa | M2: não | T2: Peça central do Cap. 6; não consta da tabela de cobertura. Registro do servidor da impressora (no quadro, a Estagiária está no terminal às 10h04, mas não fala).
A3: c6-002 | B3: ~10h04 | C3: A Operadora da Central | D3: todos | E3: presencial | F3: direta | G3: 19h00, G sai, autoriza por telefone. 19h03, trava. 19h11, reprocesso. 19h20, assinatura sem contagem. | H3: revelação | L3: toda casa | M3: não | T3: Leitura em voz alta da cronologia do ajuste_96 (texto do arquivo, lido pela Operadora, parando no fim de cada linha).
A4: c6-003 | B4: ~10h04 | C4: O Gerente | D4: todos | E4: presencial | F4: indireta | G4: Saí às dezenove porque um cliente ameaçava denunciar um favorecimento numa concessão de crédito, e eu precisava encontrá-lo antes que ele procurasse a regional. Autorizei o fechamento por telefone. | H4: subtrama | L4: toda casa | M4: não | T4: Segredo inocente do Gerente (saída das 19h00). Fixa em todas as partidas; na G é também parte do motivo.
A5: c6-004 | B5: ~10h04 | C5: A Auditora | D5: operadora | E5: presencial | F5: direta | G5: Era sobre isso a conversa de ontem? | H5: subtrama | L5: toda casa | M5: não | T5: Dirigida à Operadora (olhando para ela), mas quem responde é o Gerente. Colhe a frase omitida "não cai só você".
A6: c6-005 | B6: ~10h04 | C6: O Gerente | D6: auditora | E6: presencial | F6: direta | G6: Era. Não tinha nada a ver com dinheiro. | H6: subtrama | L6: toda casa | M6: não | T6: Efeito teia: "não cai só você" deixa de ligar o Subgerente ao malote. A frase é interior da Operadora no texto, não dita.
A7: c6-006 | B7: ~10h04 | C7: O Subgerente | D7: todos | E7: presencial | F7: indireta | G7: Confirmo o reprocessamento das dezenove e onze. Fiz o que o procedimento mandava quando o sistema volta de uma trava: reenviar a fila. Não conferi o que ela trazia. | H7: subtrama | L7: casa ≥ 8 | M7: sim | T7: Bloco 1. Nas casas sem o Subgerente a fala sai; o reprocessamento fica só na linha "19h11, reprocesso" do ajuste_96.
A8: c6-007 | B8: ~10h04 | C8: O Caixa Veterano | D8: todos | E8: presencial | F8: direta | G8: Às dezenove e vinte, eu assinei sem recontar. Tinham me ligado dizendo que um colega daquela foto tinha morrido. Eu queria chegar ao velório antes de fecharem o caixão. | H8: subtrama | L8: toda casa | M8: não | T8: Segredo inocente do Veterano (assinatura sem recontagem). Acompanha o gesto da fotografia virada sobre o balcão.
A9: c6-008 | B9: ~10h04 | C9: A Auditora | D9: todos | E9: presencial | F9: direta | G9: Quem escreveu este arquivo conhecia aquela noite por dentro. E chamou o dinheiro de próprio. | H9: revelação | L9: toda casa | M9: não | T9: A coluna "falhas" e a coluna vazia "atos" são escrita da Auditora, não fala.
A10: c6-009 | B10: ~10h12 | C10: O Caixa Novato | D10: todos | E10: presencial | F10: indireta | G10: Por que o saco vazio estava no chão, e não escondido? | H10: subtrama | L10: toda casa | M10: não
A11: c6-010 | B11: 10h12 | C11: A Operadora da Central | D11: todos | E11: presencial | F11: indireta | G11: Às oito e um, a câmera 3 já funcionava. Na borda da imagem, junto à porta do Arquivo, aparece uma perna e a roda de um balde. | H11: prova | L11: toda casa | M11: não | T11: Imagem parcial das 8h01. Em casas sem a Limpeza, é a única explicação do saco no chão (a fala da Limpeza sai).
A12: c6-011 | B12: 10h12 | C12: O Funcionário da Limpeza | D12: todos | E12: presencial | F12: direta | G12: Fui eu. | H12: subtrama | L12: casa ≥ 8 | M12: sim
A13: c6-012 | B13: 10h12 | C13: O Funcionário da Limpeza | D13: todos | E13: presencial | F13: indireta | G13: Às oito e um, voltei ao Arquivo para buscar o balde. A tampa do cesto estava torta e havia lona saindo dela. Puxei e vi o lacre rompido. Pensei que alguém tinha descartado uma coisa sigilosa usando a chave que eu emprestei. Pensei na demissão, na minha irmã. Ouvi passos no corredor, larguei o saco no chão e saí para o fundo, para o Nicho do Rack, onde ninguém me veria. | H13: subtrama | L13: casa ≥ 8 | M13: sim | T13: Explica o saco no chão (ato fixo das 8h01). Sem a Limpeza na casa (casa de 6 em G/V), sobra só a imagem parcial da Operadora; não há quem verbalize a explicação.
A14: c6-013 | B14: 10h12 | C14: O Gerente | D14: limpeza | E14: presencial | F14: direta | G14: Então foi você quem montou a cena do roubo. | H14: subtrama | L14: toda casa | M14: não | T14: Resposta à Limpeza; nas casas sem a Limpeza fica sem interlocutor e deve sair junto.
A15: c6-014 | B15: 10h12 | C15: O Funcionário da Limpeza | D15: gerente | E15: presencial | F15: direta | G15: Eu deixei um saco no chão. Quem criou o roubo foi o grito. | H15: subtrama | L15: casa ≥ 8 | M15: sim
A16: c6-015 | B16: ~10h12 | C16: A Auditora | D16: limpeza | E16: presencial | F16: indireta | G16: Tragam o cesto. | H16: ambiente | L16: toda casa | M16: não | T16: Pedido da Auditora; no texto quem traz é a Limpeza (casas sem ela: outro personagem traz).
A17: c6-016 | B17: ~10h12 | C17: A Auditora | D17: todos | E17: presencial | F17: indireta | G17: No fundo do cesto, debaixo de papéis da véspera, há uma luva de procedimento tamanho G, rasgada no indicador, com uma mancha escura de sangue seco. Colado a ela pela umidade, um cupom da farmácia da esquina: seis e trinta e um, luvas de procedimento G, fita microporosa de 1,2 cm, pago em dinheiro. | H17: prova | I17: Luva e cupom da farmácia | L17: toda casa | M17: não | T17: No texto é narração da descoberta; atribuída à Auditora, fonte primária pela tabela (cesto). Planta a pista genuína.
A18: c6-017 | B18: ~10h12 | C18: A Auditora | D18: todos | E18: presencial | F18: direta | G18: A grapa do lacre foi cortada. Quem cortou se feriu através da luva. | H18: prova | I18: Luva e cupom da farmácia | L18: toda casa | M18: não
A19: c6-018 | B19: ~10h12 | C19: O Gerente | D19: tecnico | E19: presencial | F19: direta | G19: Tire. | H19: pista falsa | L19: toda casa | M19: não | T19: Gerente aponta a fita isolante nos dedos do Técnico (falsa pista do capítulo). Embaixo: calos e queimadura antiga, nenhum corte.
A20: c6-019 | B20: ~10h12 | C20: O Gerente | D20: todos | E20: presencial | F20: indireta | G20: Ele podia ter usado a outra mão. | H20: pista falsa | L20: toda casa | M20: não | T20: Logo depois, a Farmacêutica reconhece o próprio cupom em silêncio (sem fala; reforço mudo, bloco 3).
A21: c6-020 | B21: ~10h12 | C21: O Gerente | D21: todos | E21: presencial | F21: indireta | G21: O Técnico criou a conta, travou o sistema, tem chave da porta lateral, conhece a passagem e disse ter estado no Rack durante a janela. | H21: pista falsa | L21: toda casa | M21: não | T21: Lista de acusação do falso culpado fixo.
A22: c6-021 | B22: ~10h12 | C22: A Auditora | D22: tecnico | E22: presencial | F22: direta | G22: Onde o senhor estava às sete e cinquenta e oito? | H22: subtrama | L22: toda casa | M22: não
A23: c6-022 | B23: ~10h12 | C23: O Segurança Interno | D23: tecnico | E23: presencial | F23: direta | G23: O homem de capa. Lá fora, com o motoboy. Eu bati no vidro e ele levantou a mão sem se virar. Era o senhor. | H23: prova | I23: O Técnico estava fora | L23: toda casa | M23: não | T23: Fonte primária (apoio). Colhe o homem de capa do Cap. 2; gatilho: a capa pingando e a caixa do aplicativo ao lado da porta lateral.
A24: c6-023 | B24: ~10h12 | C24: A Auditora | D24: tecnico | E24: presencial | F24: indireta | G24: Me dê o seu telefone. | H24: ambiente | L24: toda casa | M24: não
A25: c6-024 | B25: ~10h12 | C25: Registro / sistema | D25: todos | E25: registro | F25: indireta | G25: Entrega recebida às 7h58:51, com a fotografia do motoboy como prova: a porta lateral da agência, a calçada molhada, as mãos do Técnico segurando a caixa. | H25: prova | I25: O Técnico estava fora | L25: toda casa | M25: não | T25: Registro do aplicativo de entregas no telefone do Técnico (fonte primária). Colhe a mensagem "chego em quinze" do prólogo.
A26: c6-025 | B26: 10h21 | C26: O Padeiro | D26: todos | E26: telefone | F26: indireta | G26: Procurei nas imagens da minha porta de serviço sem ninguém pedir. Mando duas: às sete e cinquenta e oito e quarenta e sete, o homem de capa recebendo a caixa; às sete e cinquenta e nove e cinquenta e um, o mesmo homem empurrando a porta com o ombro, o capuz caído. | H26: reforço | I26: O Técnico estava fora | L26: casa ≥ 10 | M26: sim | T26: Bloco 2, reforço. A identificação "Era o Técnico" é do narrador, não do Padeiro (ficha: nunca descreve rosto que não viu). A ficha do capítulo chama esta de "virada" pelas fotografias do Padeiro, mas a exclusão na casa de 6 já vem do Segurança Interno e do aplicativo.
A27: c6-026 | B27: 10h21 | C27: O Técnico | D27: todos | E27: presencial | F27: direta | G27: Era uma placa de vídeo usada, sem nota. Para esta agência. Eu menti que estava no Rack porque não podia explicar a caixa. | H27: revelação | L27: toda casa | M27: não | T27: Segredo inocente do falso culpado; virada do fim do Cap. 6.
A28: c6-027 | B28: 10h21 | C28: A Auditora | D28: tecnico | E28: presencial | F28: direta | G28: Então alguém passou da Gerência para o Rack enquanto o senhor estava lá fora. | H28: revelação | L28: toda casa | M28: não | T28: A pergunta seguinte (cabo derretido; Técnico sob vigilância desde 8h25) é narração, "ninguém quis fazer em voz alta"; não virou fala.

Sheet Cap 7
A1: ID | B1: Hora | C1: Quem fala | D1: Com quem | E1: Canal | F1: Tipo | G1: Fala original | H1: Função | I1: Prova | J1: Ajuste | K1: Variação G / V | L1: Condição (casa mínima) | M1: Sai se ausente | N1: Explosivo | O1: Calmo opaco | P1: Ingênuo | Q1: Leal cego | R1: Evasivo | S1: Burocrata | T1: Nota
A2: c7-001 | B2: 10h28 | C2: A Auditora | D2: todos | E2: presencial | F2: direta | G2: Funções dizem o que cada um podia fazer. Medos dizem o que cada um escolheu esconder. | H2: ambiente | L2: toda casa | M2: não | T2: Escreve quinze funções no quadro e se recusa a escrever nomes.
A3: c7-002 | B3: ~10h28 | C3: A Operadora da Central | D3: todos | E3: presencial | F3: indireta | G3: Na câmera 1: às oito e trinta e um, o Gerente entrou atrás da divisória da própria sala e só saiu cinquenta e quatro segundos depois. | H3: revelação | L3: toda casa | M3: não | T3: Encobrimento das 8h31. "Da Gerência ao Rack, pela passagem, eram quinze segundos" é narração (sem dono).
A4: c7-003 | B4: ~10h28 | C4: O Gerente | D4: todos | E4: presencial | F4: indireta | G4: Abri a fila da impressora para ver o que gemeu às sete e cinquenta e três e li, na tela, a minha própria saída de onze dias antes. | H4: revelação | L4: toda casa | M4: não | T4: Na partida G, esta explicação é verdadeira e também encobre a autoria.
A5: c7-004 | B5: ~10h28 | C5: O Gerente | D5: todos | E5: presencial | F5: direta | G5: Pensei que a auditoria ia levar aquilo como prova contra mim. Encostei o cabo. Não toquei no malote. | H5: revelação | L5: toda casa | M5: não | T5: Na partida G, "Não toquei no malote" é mentira do impostor; a fala é fixa (sem marca A#). Ver problemas.
A6: c7-005 | B6: ~10h28 | C6: A Cliente do Cofre | D6: todos | E6: presencial | F6: indireta | G6: Esta é a planta, dobrada em oito, com carimbo de 1987 e a assinatura do meu pai, o engenheiro da obra. Atrás da parede do banheiro, a lápis, uma linha estreita liga o armário da Gerência ao fundo do Rack. Grampeada à planta, uma folha datilografada de 1990: "O caminho do painel é de conhecimento exclusivo das três chaves da tesouraria." | H6: prova | I6: Passagem só da tesouraria | L6: toda casa | M6: não | T6: No texto a Cliente só abre a pasta (narração); reescrito como fala para levar a prova ao canal. Fonte primária (núcleo).
A7: c7-006 | B7: ~10h28 | C7: A Cliente do Cofre | D7: todos | E7: presencial | F7: direta | G7: Meu pai recebeu por fora para construir isso. Para um gerente que guardava dinheiro que não constava em lugar nenhum. Eu vim tirar estas cartas daqui antes que alguém as lesse. | H7: subtrama | I7: Passagem só da tesouraria | L7: toda casa | M7: não | T7: Segredo inocente da Cliente.
A8: c7-007 | B8: ~10h28 | C8: A Auditora | D8: todos | E8: presencial | F8: direta | G8: O Técnico descobriu sozinho. Os outros receberam de herança. | H8: prova | I8: Passagem só da tesouraria | L8: toda casa | M8: não | T8: Efeito teia: a passagem deixa de ser indício do Técnico. A frase seguinte (as três chaves; o Veterano não ergue os olhos) é narração.
A9: c7-008 | B9: ~10h30 | C9: A Auditora | D9: todos | E9: presencial | F9: indireta | G9: Digam não o que viram, mas o que esperavam ver quando olharam. | H9: ambiente | L9: toda casa | M9: não
A10: c7-009 | B10: ~10h30 | C10: O Segurança Interno | D10: auditora | E10: presencial | F10: indireta | G10: Eu esperava uma invasão e transformei um motoboy em ameaça. | H10: ambiente | L10: toda casa | M10: não
A11: c7-010 | B11: ~10h30 | C11: O Técnico | D11: auditora | E11: presencial | F11: indireta | G11: Eu esperava uma falha humana e desconfiei do conector, não da parede. | H11: ambiente | L11: toda casa | M11: não
A12: c7-011 | B12: ~10h30 | C12: A Farmacêutica | D12: auditora | E12: presencial | F12: indireta | G12: Eu esperava uma crise e notei respirações antes de notar mentiras. | H12: ambiente | L12: casa ≥ 12 | M12: sim
A13: c7-012 | B13: ~10h30 | C13: A Auditora | D13: todos | E13: presencial | F13: indireta | G13: Agora, as declarações: quero confirmações. | H13: ambiente | L13: toda casa | M13: não
A14: c7-013 | B14: ~10h30 | C14: A Cliente do Cofre | D14: todos | E14: presencial | F14: direta | G14: Às sete e cinquenta e sete, entraram dois na Gerência para assinar o livro. Saiu um, quase em seguida, e foi para a Mesa. O outro ficou. Depois disso, ninguém mais entrou naquela sala até o malote atravessar. | H14: prova | I14: Dois entraram na Gerência, um saiu | J14: A4 | K14: Variante G: Às sete e cinquenta e sete, entraram dois na Gerência para assinar o livro e saíram os dois. Logo depois, o Gerente deixou a Auditora "para um telefonema" e entrou sozinho. Depois disso, ninguém mais entrou naquela sala até o malote atravessar. | Variante V: Às sete e cinquenta e sete, entraram dois na Gerência para assinar o livro. Saiu um, quase em seguida, e foi para os Guichês. O outro ficou. Depois disso, ninguém mais entrou naquela sala até o malote atravessar. | L14: toda casa | M14: não | T14: Fonte primária (núcleo). Antes da fala, narração: estivera junto à Porta Giratória contando silhuetas. Na G a variação foi montada da tabela A4 + Variante G (o texto não traz a fala pronta); a prova deixa de ser "dois entraram, um saiu".
A15: c7-014 | B15: ~10h30 | C15: A Operadora da Central | D15: todos | E15: presencial | F15: indireta | G15: A câmera 1, que vê a divisória por fora, confirma a conta. | H15: prova | I15: Dois entraram na Gerência, um saiu | J15: A4 | K15: Variante G: a câmera 1 confirma que os dois saíram e mostra o Gerente entrando na divisória às 7h57:50. | Variante V: a câmera 1 confirma a conta (dois entraram, um saiu). | L15: toda casa | M15: não | T15: Fonte primária (câmera 1, Operadora).
A16: c7-015 | B16: ~10h30 | C16: A Farmacêutica | D16: todos | E16: presencial | F16: indireta | G16: Confirmo a conta. Conto pessoas sem querer, como conto comprimidos. | H16: reforço | I16: Dois entraram na Gerência, um saiu | J16: A4 | K16: Variante G: confirma que os dois saíram e que o Gerente entrou sozinho depois. | Variante V: igual à referência. | L16: casa ≥ 12 | M16: sim | T16: Bloco 3, reforço.
A17: c7-016 | B17: ~10h30 | C17: A Operadora da Central | D17: todos | E17: presencial | F17: indireta | G17: Na câmera 2, que vê os Guichês e a Mesa e não caiu em momento algum: o Caixa Veterano chega à Mesa às sete e cinquenta e sete e cinquenta e cinco e não sai dali. | H17: prova | I17: Quem estava onde na janela | J17: A5b | K17: Variante G: igual (Caixa Veterano na Mesa, câmera 2). | Variante V: a câmera 2 mostra a Mesa vazia até 8h00:02 (o Caixa Veterano, que disse estar na Mesa, não está). | L17: toda casa | M17: não | T17: Fonte primária (câmera 2). Na V, o ponto vira A5 (desmentido).
A18: c7-017 | B18: ~10h30 | C18: O Segurança do Veículo | D18: todos | E18: presencial | F18: indireta | G18: Da Eclusa, pelo vidro, eu o vi do mesmo jeito, na Mesa. | H18: reforço | I18: Quem estava onde na janela | J18: A5b | K18: Variante G: igual. | Variante V: Da Eclusa, pelo vidro, vi a Mesa vazia até as oito e zero zero e dois. | L18: casa ≥ 10 | M18: sim | T18: Bloco 2, reforço. Na V a Variante do Cap. 8 cita o Segurança do Veículo como quem viu; na casa de 6 ele não está, e a fonte tem de ser a câmera 2.
A19: c7-018 | B19: ~10h30 | C19: A Operadora da Central | D19: todos | E19: presencial | F19: indireta | G19: O Gerente esteve junto à Porta Giratória o tempo todo. | H19: prova | I19: Quem estava onde na janela | J19: A5b | K19: Variante G: a câmera 1 mostra o Gerente entrando na divisória às 7h57:50; o ramal da Gerência não tem chamada entre 7h50 e 8h10 (A5, desmentido do "telefonema"). | Variante V: igual à referência. | L19: toda casa | M19: não | T19: No texto a fonte não é nomeada nesta frase; pela tabela A5b é a câmera 1 (Operadora).
A20: c7-019 | B20: ~10h30 | C20: A Auditora | D20: todos | E20: presencial | F20: indireta | G20: Confirmo: o Gerente esteve junto à Porta Giratória. | H20: prova | I20: Quem estava onde na janela | J20: A5b | K20: Variante G: O Gerente me deixou "para um telefonema" e entrou na sala às sete e cinquenta e sete e cinquenta. | Variante V: igual à referência. | L20: toda casa | M20: não
A21: c7-020 | B21: ~10h30 | C21: A Cliente do Cofre | D21: todos | E21: presencial | F21: indireta | G21: Confirmo: o Gerente esteve junto à Porta Giratória. | H21: prova | I21: Quem estava onde na janela | J21: A5b | K21: Variante G: O Gerente deixou a Auditora e entrou sozinho na Gerência. | Variante V: igual à referência. | L21: toda casa | M21: não
A22: c7-021 | B22: ~10h30 | C22: A Operadora da Central | D22: todos | E22: presencial | F22: indireta | G22: Nos Guichês, a Estagiária recolhia folhas sozinha. O Subgerente, que disse estar ali buscando a guia, só entra no quadro às oito e zero cinco. | H22: prova | I22: Quem estava onde na janela | J22: A5 | K22: Variante G: Nos Guichês, a Estagiária recolhia folhas e o Subgerente buscava a guia; a câmera 2 o mostra ali (A5b). | Variante V: Nos Guichês, a Estagiária recolhia folhas e o Subgerente buscava a guia (A5b); quem falta é o Caixa Veterano, ausente da Mesa até 8h00:02. | L22: toda casa | M22: não | T22: Fonte primária (câmera 2). Na S a casa mínima é 8, onde a mentira cai pela câmera 2 e pela contagem da Cliente.
A23: c7-022 | B23: ~10h30 | C23: A Estagiária | D23: todos | E23: presencial | F23: indireta | G23: Confirmo. Eu estava nos Guichês o tempo todo. | H23: reforço | I23: Quem estava onde na janela | J23: A5 | K23: Variante G: confirma o Subgerente nos Guichês. | Variante V: confirma o Subgerente nos Guichês (a Mesa vazia é com a câmera 2 / Segurança do Veículo). | L23: casa ≥ 12 | M23: sim | T23: No texto é gesto (olhou para o chão e confirmou com a cabeça), não fala. Bloco 3, reforço.
A24: c7-023 | B24: ~10h30 | C24: A Operadora da Central | D24: todos | E24: presencial | F24: indireta | G24: Na câmera interna da Central: do começo ao fim da janela, eu estava no console, com a mão no rádio. A câmera 1 mostra o Funcionário da Limpeza e o carrinho no Saguão, e a Cliente, a Farmacêutica e a Auditora juntas na Porta Giratória. | H24: prova | I24: Quem estava onde na janela | L24: toda casa | M24: não | T24: Fonte primária (câmera da Central e câmera 1). Situa inocentes; fixa em todas as partidas (não cita o Gerente).
A25: c7-024 | B25: ~10h35 | C25: A Operadora da Central | D25: todos | E25: presencial | F25: indireta | G25: No livro de lacres: o ML-8842 foi aplicado na véspera, às quinze e cinquenta, com duas assinaturas, a do Subgerente, que contou, e a do Caixa Veterano. | H25: prova | I25: Livro de lacres, titular, cartão | J25: A2 | K25: Variante G: ... com duas assinaturas, a do Gerente, que contou, e a do Subgerente. | Variante V: ... com duas assinaturas, a do Caixa Veterano, que contou, e a do Subgerente. | L25: toda casa | M25: não | T25: Fonte primária (Operadora).
A26: c7-025 | B26: ~10h35 | C26: O Caixa Veterano | D26: todos | E26: presencial | F26: direta | G26: Eu assinei sem contar. De novo. Achei que a guia bastava. | H26: prova | I26: Livro de lacres, titular, cartão | J26: A2 | K26: Variante G e V: a confissão passa ao Subgerente (o ajudante): "Eu assinei sem contar. Achei que a guia bastava." | L26: toda casa | M26: não | T26: Na S é núcleo. Em G/V o ajudante é o Subgerente, ausente na casa de 6: a fala sai e só o livro (Operadora) sustenta. "De novo" só vale para quem assinou a consolidação das 19h20 (Veterano e Subgerente).
A27: c7-026 | B27: ~10h37 | C27: A Auditora | D27: todos | E27: presencial | F27: indireta | G27: A fita vendida às seis e trinta e um tem 1,2 centímetro. A do kit de primeiros socorros da Gerência, 2,5, a mesma que o Caixa Novato usa no indicador. E há uma tira estreita no indicador do Subgerente. | H27: prova | I27: Fita estreita | J27: A3 | K27: Variante G: ... no indicador do Gerente (tabela A3; a Variante G do Cap. 8 diz "indicador"). | Variante V: ... no indicador do Caixa Veterano. | L27: toda casa | M27: não | T27: Fonte primária (Auditora: cupom × kit). No texto a última frase é um olhar, não fala.
A28: c7-027 | B28: ~10h37 | C28: A Farmacêutica | D28: todos | E28: presencial | F28: indireta | G28: Vendi luvas tamanho G e fita estreita a alguém de capa e guarda-chuva de cabo claro, que pagou em dinheiro e não tirou o capuz. | H28: reforço | I28: Fita estreita | L28: casa ≥ 12 | M28: sim | T28: Bloco 3, reforço (acompanha o envelope deixado no balcão).
A29: c7-028 | B29: ~10h37 | C29: A Farmacêutica | D29: todos | E29: presencial | F29: direta | G29: Eu vi às oito e vinte. Não disse porque teria de contar o resto. | H29: subtrama | L29: casa ≥ 12 | M29: sim | T29: Ambíguo: não diz o que viu às 8h20 (a fita estreita no dedo do impostor? o cupom? a figura?). Se for a fita, deveria ser ponto de ajuste.
A30: c7-029 | B30: ~10h38 | C30: A Auditora | D30: todos | E30: presencial | F30: indireta | G30: Comprei café pela frente, onde o chão do balcão é de farinha fina, que gruda na ponteira de um guarda-chuva. Quem atravessa a porta de serviço, onde os sacos ficam empilhados na altura do joelho, sai com a barra branca. | H30: prova | I30: Farinha na barra | L30: toda casa | M30: não | T30: Desfaz a falsa pista da farinha da própria Auditora; fonte primária.
A31: c7-030 | B31: ~10h38 | C31: A Cliente do Cofre | D31: todos | E31: presencial | F31: indireta | G31: Há uma faixa branca e seca na barra da calça do Subgerente. | H31: prova | I31: Farinha na barra | J31: A6 | K31: Variante G: ... na barra da calça do Gerente. | Variante V: ... na barra da calça do Caixa Veterano. | L31: toda casa | M31: não | T31: Fonte primária (núcleo). No texto ela aponta.
A32: c7-031 | B32: ~10h38 | C32: O Padeiro | D32: todos | E32: telefone | F32: indireta | G32: Ali ninguém passa sem roçar os sacos. | H32: reforço | I32: Farinha na barra | L32: casa ≥ 10 | M32: sim | T32: Bloco 2, reforço.
A33: c7-032 | B33: 10h41 | C33: Registro / sistema | D33: auditora | E33: registro | F33: indireta | G33: O saque agendado de noventa e seis mil reais, retirado em espécie na véspera, às dezesseis e trinta, na agência 0392, tem um titular: o Subgerente, com garantia de joias de família empenhadas cinco dias antes. | H33: prova | I33: Livro de lacres, titular, cartão | J33: A8 | K33: Variante G: ... tem um titular: o Gerente, com recursos do resgate antecipado da previdência privada. | Variante V: ... tem um titular: o Caixa Veterano, com as economias guardadas para a aposentadoria. | L33: toda casa | M33: não | T33: Resposta da regional ao pedido da Auditora (fonte: regional, pela Auditora). Canal: registro/mensagem institucional.
A34: c7-033 | B34: 10h46 | C34: A Operadora da Central | D34: todos | E34: presencial | F34: indireta | G34: Chegou o retorno do fornecedor do rádio: o registro completo do pareamento das sete e cinquenta e sete e cinquenta e cinco, com os dígitos recuperados. Comparando com os cartões sobre o balcão, pertencem ao cartão do Subgerente. | H34: prova | I34: Livro de lacres, titular, cartão | J34: A7 | K34: Variante G: ... pertencem ao cartão do Gerente. | Variante V: ... pertencem ao cartão do Caixa Veterano. | L34: toda casa | M34: não | T34: Fonte primária. O texto diz "quase no mesmo minuto" (10h41), mas a ficha e o quadro dão 10h46 ao checksum.
A35: c7-034 | B35: 10h46 | C35: A Operadora da Central | D35: todos | E35: presencial | F35: indireta | G35: Junto veio outra informação: a reimpressão das oito e trinta e cinco não saiu de dentro da agência. A origem é a rede de segurança regional. | H35: revelação | L35: toda casa | M35: não | T35: Planta a presença do oculto.
A36: c7-035 | B36: 10h46 | C36: A Operadora da Central | D36: todos | E36: presencial | F36: direta | G36: Alguém nos vê de longe. Desde cedo. | H36: revelação | L36: toda casa | M36: não | T36: A releitura da mensagem das 8h10 ("Procurem quem abriu antes") e a pergunta "por que alguém que vê tudo precisa se esconder?" são pensamento/caderno da Auditora, não falas.
A37: c7-036 | B37: ~10h50 | C37: O Subgerente | D37: todos | E37: presencial | F37: direta | G37: Antes que escrevam qualquer coisa, eu quero ouvir a soma inteira. | H37: revelação | J37: A9 | K37: Variante G: a mesma fala, dita pelo Gerente. | Variante V: a mesma fala, dita pelo Caixa Veterano. | L37: casa ≥ 8 | M37: não | T37: Fala do impostor (marca A9 no nome). Antes, gesto: ajeita a fita no dedo (A3; em G "indicador"/indicador, em V base do indicador).

Sheet Cap 8
A1: ID | B1: Hora | C1: Quem fala | D1: Com quem | E1: Canal | F1: Tipo | G1: Fala original | H1: Função | I1: Prova | J1: Ajuste | K1: Variação G / V | L1: Condição (casa mínima) | M1: Sai se ausente | N1: Explosivo | O1: Calmo opaco | P1: Ingênuo | Q1: Leal cego | R1: Evasivo | S1: Burocrata | T1: Nota
A2: c8-001 | B2: 10h52 | C2: O Gerente | D2: todos | E2: presencial | F2: indireta | G2: Exijo uma acusação formal. | H2: ambiente | L2: toda casa | M2: não | T2: Na partida G, o próprio impostor exige a acusação.
A3: c8-002 | B3: 10h52 | C3: A Operadora da Central | D3: todos | E3: presencial | F3: indireta | G3: Abro uma página nova na ata. Cada um diga de quem desconfiou. | H3: ambiente | L3: toda casa | M3: não | T3: No texto, a Operadora só abre a página; o convite é implícito.
A4: c8-003 | B4: 10h52 | C4: O Segurança Interno | D4: todos | E4: presencial | F4: indireta | G4: Desconfiei da Operadora, pelo esmalte. Desculpe. | H4: pista falsa | L4: toda casa | M4: não | T4: Acusação de todos. Pede desculpas antes de terminar.
A5: c8-004 | B5: 10h52 | C5: A Cliente do Cofre | D5: todos | E5: presencial | F5: indireta | G5: Desconfiei do Gerente, pela frase de ontem. | H5: pista falsa | J5: A9 | K5: Variante G: a Cliente mantém a desconfiança do Gerente (mesmo texto, agora acerta). | Variante V: igual à referência. | L5: toda casa | M5: não | T5: Sem marca ^A^ no texto; mudança vem da Variante G ("mudanças na acusação").
A6: c8-005 | B6: 10h52 | C6: O Motorista | D6: todos | E6: rádio | F6: indireta | G6: Desconfiei do Técnico, pela câmera. | H6: pista falsa | L6: toda casa | M6: não
A7: c8-006 | B7: 10h52 | C7: A Estagiária | D7: todos | E7: presencial | F7: indireta | G7: Eu também desconfiei do Técnico. | H7: pista falsa | L7: casa ≥ 12 | M7: sim | T7: Fica vermelha.
A8: c8-007 | B8: 10h52 | C8: A Farmacêutica | D8: todos | E8: presencial | F8: indireta | G8: Desconfiei do Caixa Novato... não, me corrijo. | H8: pista falsa | L8: casa ≥ 12 | M8: sim
A9: c8-008 | B9: 10h52 | C9: O Caixa Novato | D9: todos | E9: presencial | F9: indireta | G9: Desconfiei de mim mesmo. | H9: pista falsa | L9: toda casa | M9: não | T9: "O momento mais cruel da manhã"; aponta para si.
A10: c8-009 | B10: 10h52 | C10: O Técnico | D10: todos | E10: presencial | F10: direta | G10: A parede. | H10: pista falsa | L10: toda casa | M10: não | T10: Discurso direto sem travessão no texto.
A11: c8-010 | B11: 10h52 | C11: O Segurança do Veículo | D11: todos | E11: presencial | F11: direta | G11: Eu, que deixei passar. | H11: subtrama | L11: casa ≥ 10 | M11: sim
A12: c8-011 | B12: 10h52 | C12: O Funcionário da Limpeza | D12: todos | E12: presencial | F12: indireta | G12: Desconfiei do saco, não de gente. | H12: ambiente | L12: casa ≥ 8 | M12: sim
A13: c8-012 | B13: 10h52 | C13: O Padeiro | D13: todos | E13: telefone | F13: direta | G13: De quem atravessou minha porta sem comprar nada. | H13: reforço | L13: casa ≥ 10 | M13: sim
A14: c8-013 | B14: 10h52 | C14: O Operador de Rádio | D14: todos | E14: rádio | F14: indireta | G14: Não identifico pessoas, só códigos. E o código era de tesouraria. | H14: prova | L14: toda casa | M14: não | T14: Vigia de fora; pertence ao bloco "completa" (ver problemas: casa de 6 sem o vigia).
A15: c8-014 | B15: 10h52 | C15: O Gerente | D15: todos | E15: presencial | F15: indireta | G15: Desconfio do Técnico. | H15: pista falsa | J15: A9 | K15: Variante G: o Gerente aponta o Técnico com mais força ("Foi o Técnico."). | Variante V: igual à referência (sem convicção). | L15: toda casa | M15: não | T15: Repete o Técnico sem convicção. Sem marca no texto; mudança vem da Variante G.
A16: c8-015 | B16: 10h52 | C16: O Caixa Veterano | D16: todos | E16: presencial | F16: indireta | G16: (não diz nome) | H16: ambiente | J16: A9 | K16: Variante G: igual à referência. | Variante V (jogo, 05/10): na acusação não diz nome; diz "Fui eu", em voz baixa, durante a reconstrução da Auditora (c8-023). | L16: toda casa | M16: não | T16: Silêncio no texto; registrado para manter uma entrada por personagem. Sem marca; mudança vem da Variante V.
A17: c8-016 | B17: 10h52 | C17: O Subgerente | D17: todos | E17: presencial | F17: indireta | G17: Desconfiei de todos, porque é o meu trabalho. | H17: pista falsa | L17: casa ≥ 8 | M17: sim | T17: Na S é a fala do impostor na acusação. Nas casas sem o Subgerente (G/V casa 6), sai.
A18: c8-017 | B18: 10h52 | C18: O Transportador | D18: todos | E18: rádio | F18: direta | G18: Eu disse às oito e quarenta e oito: pesava o certo. Ninguém tirou. Alguém pôs. | H18: reforço | I18: Peso de 7,0 kg e composição | L18: casa ≥ 13 | M18: não (sem ele, o Motorista repete a frase pelo rádio) | T18: Bloco completo, reforço. A conclusão "Alguém pôs" fica sem dono na casa de 6; precisa vir do Motorista (balança) ou da Auditora.
A19: c8-018 | B19: 10h54 | C19: A Auditora | D19: todos | E19: presencial | F19: indireta | G19: O saco do Arquivo era o malote da véspera, esvaziado e largado no chão por um homem com medo de uma chave emprestada. A voz a mais saiu da Gerência. A etiqueta nasceu às seis e cinquenta e oito, antes de qualquer pane. A rota era a parede. Nos oitenta e sete segundos, o dinheiro entrou. O número sem corpo nasceu de quatro falhas numa noite de chuva. E as outras mentiras protegiam vergonhas verdadeiras e pequenas. | H19: revelação | L19: toda casa | M19: não | T19: As sete grandes questões, em ordem.
A20: c8-019 | B20: ~10h53 | C20: A Auditora | D20: todos | E20: presencial | F20: indireta | G20: Oito dias antes, ao reler o espelho do reprocessamento, o Subgerente percebeu que o depósito do frigorífico entrou duas vezes, e calou. | H20: revelação | J20: A1 | K20: Variante G: Oito dias antes, ao assinar o balancete semanal do Cofre, o Gerente percebeu que o depósito do frigorífico entrou duas vezes, e calou. | Variante V: Oito dias antes, ao refazer de cabeça a soma do frigorífico, numa noite sem sono, o Caixa Veterano percebeu que o depósito entrou duas vezes, e calou. | L20: toda casa | M20: não
A21: c8-020 | B21: ~10h53 | C21: A Auditora | D21: todos | E21: presencial | F21: indireta | G21: Na véspera, às quinze e cinquenta, ele contou o excedente, encontrou trezentos e oitenta e quatro mil onde a guia pedia quatrocentos e oitenta, e lacrou assim mesmo. O Caixa Veterano assinou sem contar. Era o que ele sabia: o malote sairia curto e a base descobriria. | H21: revelação | J21: A2 | K21: Variante G: ... o Gerente contou ... e lacrou assim mesmo. O Subgerente assinou sem contar. ... | Variante V: ... o Caixa Veterano contou ... e lacrou assim mesmo. O Subgerente assinou sem contar. ... | L21: toda casa | M21: não
A22: c8-021 | B22: ~10h53 | C22: A Auditora | D22: todos | E22: presencial | F22: indireta | G22: Por onde foi: da Gerência para a passagem, da passagem para o Rack, do Rack para o Arquivo e para a Antecâmara, e de volta, sem atravessar o Saguão. | H22: revelação | L22: toda casa | M22: não | T22: Rota fixa nas três partidas.
A23: c8-022 | B23: ~10h53 | C23: A Auditora | D23: todos | E23: presencial | F23: indireta | G23: Quem o viu não estar: a câmera 2, que mostra os Guichês sem ele até as oito e zero cinco, e a Estagiária, que estava lá; a Cliente do Cofre e a câmera 1, que viram dois entrarem na Gerência e um sair. | H23: revelação | I23: Quem estava onde na janela | J23: A5 | K23: Variante G: o ramal da Gerência, sem chamada entre 7h50 e 8h10, e a câmera 1, que o mostra entrando na divisória às 7h57:50. | Variante V: a câmera 2, que mostra a Mesa vazia até 8h00:02, e o Segurança do Veículo, que via a Mesa da Eclusa; a Cliente do Cofre e a câmera 1, que viram dois entrarem na Gerência e um sair. | L23: toda casa | M23: não | T23: Cita a Estagiária (bloco 3), ausente na casa de 8 da partida S; e, na V, o Segurança do Veículo (bloco 2), ausente na casa de 6.
A24: c8-023 | B24: ~10h53 | C24: A Auditora | D24: todos | E24: presencial | F24: indireta | G24: O que o registro desmente: o sensor da porta lateral, aberta às seis e trinta e seis, quando nenhum crachá tinha passado, e o crachá dele, às sete e dezesseis, que pretendia ser a chegada; os dígitos do cartão dele no rádio; o saque em nome dele na 0392; a fita da farmácia no indicador e a luva rasgada no cesto. | H24: revelação | I24: Livro de lacres, titular, cartão | J24: A5, A7, A8, A3 | K24: Variante G: "dele" = Gerente; saque do resgate da previdência; fita no indicador (Variante G) ou indicador (tabela A3); o horário do crachá não tem valor definido para a G. | Variante V: "dele" = Caixa Veterano; saque das economias da aposentadoria; fita no indicador; horário do crachá não definido para a V. | L24: toda casa | M24: não | T24: O crachá das 7h16 não aparece no cânone nem na tabela de ajuste (marcado A5 sem valor para G/V).
A25: c8-024 | B25: ~10h53 | C25: A Auditora | D25: todos | E25: presencial | F25: indireta | G25: Quem ajudou, sem saber: o Caixa Veterano, que assinou sem contar; o Segurança Interno, que deixou o rádio fora do carregador; o Segurança do Veículo, que conferiu a tela; o Funcionário da Limpeza, que transformou o descarte numa cena. | H25: revelação | J25: A2 | K25: Variante G e V: ... o Subgerente, que assinou sem contar; ... (demais iguais). | L25: toda casa | M25: não
A26: c8-025 | B26: ~10h53 | C26: A Auditora | D26: todos | E26: presencial | F26: indireta | G26: E por que os outros pareceram culpados: o Técnico tinha a conta, a chave e o segredo de uma caixa sem nota; o Caixa Novato tinha uma pasta trocada e um pânico sem testemunha; a Estagiária guardava uma senha e uma cópia; a Operadora tinha um esmalte e uma omissão; a Cliente, uma planta; a própria Auditora, um guarda-chuva e um passado. O Gerente tinha um cabo queimado, que era seu de fato, mas era outra coisa. | H26: revelação | K26: Variante G: a última frase vira "E o cabo queimado das oito e trinta e um não era outra coisa: era o mesmo plano, agora escondendo a si mesmo." | L26: toda casa | M26: não | T26: Sem marca de ajuste, mas na G a frase final sobre o Gerente é falsa (o cabo é encobrimento e autoria). Também falta, em G/V, a explicação inocente do Subgerente (chave 17-B/espelho).
A27: c8-026 | B27: ~10h55 | C27: O Subgerente | D27: todos | E27: presencial | F27: direta | G27: Eu descobri três dias depois. Se comunicasse, viria a regional. Meu reprocessamento, a assinatura dele, a saída do Gerente, a trava do Técnico. Seria uma fila de gente. Empenhei as joias da minha mãe. Agendei o saque. Fechei o malote curto porque não tinha o dinheiro às quinze e cinquenta, e ia pôr o que faltava antes de ele sair. Auditoria surpresa costuma chegar com a abertura, às oito. Antecipei a coleta para as sete e cinquenta. Vocês chegaram às sete e quarenta e sete. | H27: revelação | J27: A9 | K27: Variante G (Gerente): Eu saí às sete naquela noite porque um homem ia me denunciar. Quando vi o número, entendi que a minha saída estava dentro dele. Se a regional viesse, viria por tudo: pela saída, pelo crédito, por mim. Resgatei a previdência. Fechei o malote curto e ia completar antes da coleta. Queimei o cabo porque o arquivo dizia 'G sai'. Eu mesmo escrevi isso, para não esquecer quem eu tinha sido naquela noite. | Variante V (Caixa Veterano): Eu assinei sem contar para ir enterrar um amigo. Vinte e sete anos sem uma diferença, e a primeira foi minha. Tirei o dinheiro da aposentadoria. Não era para ninguém pagar por isso, nem eu, nem o nome desta agência. Fechei o malote curto porque às quinze e cinquenta eu ainda não tinha o dinheiro. Pensei que ninguém nunca saberia que eu tinha errado. | L27: casa ≥ 8 | M27: não | T27: Confissão do impostor. "três dias depois" = oito dias antes do crime (coerente com A1). Na S o Subgerente está sempre presente (casa mínima 8).
A28: c8-027 | B28: ~10h55 | C28: A Auditora | D28: subgerente | E28: presencial | F28: direta | G28: E a voz no rádio? | H28: revelação | J28: A9 | K28: Variante G: dirigida ao Gerente. | Variante V: dirigida ao Caixa Veterano. | L28: toda casa | M28: não | T28: Sem marca; o destinatário é o impostor da partida.
A29: c8-028 | B29: ~10h55 | C29: O Subgerente | D29: auditora | E29: presencial | F29: direta | G29: Eu precisava do corredor sem ninguém. | H29: revelação | J29: A9 | K29: Variante G: a mesma fala, dita pelo Gerente. | Variante V: a mesma fala, dita pelo Caixa Veterano. | L29: casa ≥ 8 | M29: não | T29: Sem marca no texto, mas é fala do impostor; as Variantes G/V não reescrevem estas respostas.
A30: c8-029 | B30: ~10h55 | C30: A Auditora | D30: subgerente | E30: presencial | F30: direta | G30: E a câmera? | H30: revelação | J30: A9 | K30: Variante G: dirigida ao Gerente. | Variante V: dirigida ao Caixa Veterano. | L30: toda casa | M30: não
A31: c8-030 | B31: ~10h55 | C31: O Subgerente | D31: auditora | E31: presencial | F31: direta | G31: Para que ninguém visse dinheiro entrando e achasse que era dinheiro saindo. | H31: revelação | J31: A9 | K31: Variante G: a mesma fala, dita pelo Gerente. | Variante V: a mesma fala, dita pelo Caixa Veterano. | L31: casa ≥ 8 | M31: não
A32: c8-031 | B32: ~10h55 | C32: O Caixa Novato | D32: todos | E32: presencial | F32: direta | G32: Foi exatamente o que achamos. Eu achei. Em voz alta. | H32: subtrama | L32: toda casa | M32: não
A33: c8-032 | B33: ~10h56 | C33: O Gerente | D33: todos | E33: presencial | F33: indireta | G33: Isto é fraude. | H33: ambiente | K33: Variante G: "Alguém falou em fraude." (o Gerente é o impostor) | L33: toda casa | M33: não | T33: No texto: "quis falar de fraude" e a Auditora não deixa. Na partida G o Gerente é o impostor e acabou de confessar: a fala fica incoerente e não tem ajuste.
A34: c8-033 | B34: ~10h56 | C34: A Auditora | D34: todos | E34: presencial | F34: direta | G34: Ninguém roubou. Uma pessoa falsificou a realidade para que ela obedecesse a um registro falso. E, para isso, usou o descuido e o medo de todos nós. | H34: revelação | L34: toda casa | M34: não
A35: c8-034 | B35: 10h57 | C35: A Auditora | D35: todos | E35: presencial | F35: indireta | G35: Para a ata: [a função de quem trocou o malote] responderá pela custódia violada, pelo uso indevido de credencial, pela sabotagem da câmera, pela ordem falsa e pela exposição dos colegas… | H35: revelação | K35: Sem a palavra "impostor" (05/10). Variante G: o Gerente responde também pela destruição de evidência e pela saída daquela noite. Todas: o ajudante, pela assinatura sem contagem. | L35: toda casa | M35: não | T35: Hora pelo quadro (11h05); no texto vem antes da contagem das 10h58. Usa a palavra "impostor" (vocabulário do guia, vetado no texto público). Não inclui o ajudante que assinou sem contar.
A36: c8-035 | B36: 10h58 | C36: O Operador de Rádio | D36: auditora | E36: rádio | F36: indireta | G36: A base confirma a contagem final. | H36: prova | I36: Peso de 7,0 kg e composição | L36: toda casa | M36: não | T36: O texto diz só "a base confirmou a contagem final"; o cânone fixa R$ 480.000, composição idêntica à guia, cédulas verdadeiras. Atribuída ao Operador de Rádio (base); em casa sem ele, registro da base.
A37: c8-036 | B37: dia seguinte ~10h00 | C37: O Caixa Veterano | D37: caixa_novato | E37: presencial | F37: direta | G37: Não é magia. É atenção. | H37: ambiente | J37: A10 | K37: Variante G: igual. | Variante V (jogo, 05/10): o Subgerente ensina; o Caixa Novato diz a frase, repetindo quem lhe ensinara primeiro. | L37: toda casa | M37: não | T37: Epílogo. Na V o Subgerente (bloco 1) não está na casa de 6: a cena do ensino precisa de outro par.
A38: c8-037 | B38: dia seguinte 8h10 | C38: O Monitor Remoto | D38: operadora | E38: mensagem sem origem | F38: direta | G38: Onze dias atrás. Dezenove e vinte. Alarme de fechamento sem contagem. Posto vazio. Silenciado depois. Por isso a auditoria. | H38: revelação | L38: toda casa | M38: não | T38: Última mensagem do oculto, no terminal da Central; a Operadora registra na ocorrência e não apaga. Hora 8h10 da manhã seguinte, mas o texto diz que a agência abriu às dez: a cena das 8h10 aparece depois da abertura na ordem do texto.
A39: c8-038 | B39: dia seguinte | C39: A Auditora | D39: todos | E39: registro | F39: direta | G39: Quando alguém sacrifica o que é seu para corrigir em segredo um erro que não o enriqueceu, o que deve pesar mais: a intenção de reparar, os meios escolhidos ou o risco imposto aos outros? | H39: ambiente | L39: toda casa | M39: não | T39: Pergunta de valor escrita no relatório (não dita).

Sheet Variantes Cap 8
A1: Partida | B1: Impostor | C1: Ajudante | D1: Confissão | E1: Saída (A10) | F1: Mudanças na acusação | G1: Mudanças no epílogo
A2: S | B2: O Subgerente | C2: O Caixa Veterano | D2: Eu descobri três dias depois. Se comunicasse, viria a regional. Meu reprocessamento, a assinatura dele, a saída do Gerente, a trava do Técnico. Seria uma fila de gente. Empenhei as joias da minha mãe. Agendei o saque. Fechei o malote curto porque não tinha o dinheiro às quinze e cinquenta, e ia pôr o que faltava antes de ele sair. Auditoria surpresa costuma chegar com a abertura, às oito. Antecipei a coleta para as sete e cinquenta. Vocês chegaram às sete e quarenta e sete. [Auditora: E a voz no rádio?] Eu precisava do corredor sem ninguém. [Auditora: E a câmera?] Para que ninguém visse dinheiro entrando e achasse que era dinheiro saindo. | E2: O Subgerente saiu acompanhado e deixou sobre o balcão o rolo de fita que trazia no bolso. | F2: Referência: o Subgerente diz que desconfiou de todos, porque era o seu trabalho; o Gerente repete o Técnico sem convicção; o Caixa Veterano não diz nome; a Cliente aponta o Gerente pela frase de ontem. | G2: Texto público: o Caixa Veterano pendura a fotografia de volta, ensina o Novato a ouvir o Cofre e diz "Não é magia. É atenção."; o Gerente trabalha com a porta aberta, sem o anel.
A3: G | B3: O Gerente | C3: O Subgerente | D3: Eu saí às sete naquela noite porque um homem ia me denunciar. Quando vi o número, entendi que a minha saída estava dentro dele. Se a regional viesse, viria por tudo: pela saída, pelo crédito, por mim. Resgatei a previdência. Fechei o malote curto e ia completar antes da coleta. Queimei o cabo porque o arquivo dizia 'G sai'. Eu mesmo escrevi isso, para não esquecer quem eu tinha sido naquela noite. | E3: Tira o anel, deixa o crachá sobre a mesa e sai acompanhado. A frase "Sem o anel, a mão parecia menor" passa para a cena de saída. | F3: O Gerente aponta o Técnico com mais força; a Cliente do Cofre mantém a desconfiança dele. Jogo (05/10): "Alguém falou em fraude" (no lugar do Gerente); "o cabo queimado das oito e trinta e um não era outra coisa: era o mesmo plano, agora escondendo a si mesmo"; na separação dos atos, o Gerente responde também pela destruição de evidência e pela saída daquela noite. | G3: A sala do Gerente fica com a porta aberta e sem ninguém; sai do epílogo o Gerente trabalhando o dia inteiro.
A4: V | B4: O Caixa Veterano | C4: O Subgerente | D4: Eu assinei sem contar para ir enterrar um amigo. Vinte e sete anos sem uma diferença, e a primeira foi minha. Tirei o dinheiro da aposentadoria. Não era para ninguém pagar por isso, nem eu, nem o nome desta agência. Fechei o malote curto porque às quinze e cinquenta eu ainda não tinha o dinheiro. Pensei que ninguém nunca saberia que eu tinha errado. | E4: Pendura a fotografia de volta na parede e sai acompanhado. | F4: Docx: o Caixa Veterano diz o próprio nome em voz baixa antes de a Auditora terminar. Jogo (05/10): na acusação não diz nome, como na S; diz "Fui eu", em voz baixa, durante a reconstrução, antes de a Auditora terminar. | G4: O Caixa Novato aprende a ouvir o Cofre com o Subgerente; a fala "Não é magia. É atenção" fica como lembrança do Veterano, dita pelo Novato. Sai do epílogo o Veterano pendurando a fotografia antes de ir (passa para a saída). Jogo (05/10): o Caixa Novato diz "Não é magia. É atenção.", repetindo quem lhe ensinara primeiro.

Sheet Pendências
A1: Prioridade | B1: Tema | C1: Onde | D1: Problema | E1: Proposta | F1: Decisão (Mario)
A2: Alta | B2: Ajudante fora da casa de 6 (G e V) | C2: Cânone, Pontos de ajuste A2; Cap. 7; pergunta final "quem ajudou" | D2: Nas partidas G e V o ajudante (cossignatário A2) é o Subgerente, do 1º bloco. Na casa de 6 ele não existe: some a confissão "assinei sem contar" e a pergunta final "quem o ajudou?" fica sem resposta possível. | E2: Opção 1: casa mínima de G e V passa a 8 (as três partidas ficam com casa 8). Opção 2: em G e V o cossignatário é o Caixa Veterano/Gerente (núcleo) — exige revisar A2. Opção 3: a pergunta final do ajudante aceita o Segurança Interno (apoio, sempre presente). | F2: DECIDIDO 05/10 (opção 1): G e V passam a casa mínima 8, como a S.
A3: Alta | B3: Fita no dedo × luva rasgada | C3: A3 (Caps. 2, 7, 8); luva do Cap. 6 | D3: A luva tem o rasgo e o sangue no INDICADOR, mas a fita do impostor está no POLEGAR (S e V; a tabela A3 também diz polegar para G, enquanto a Variante G diz indicador). | E3: Unificar: corte e fita no mesmo dedo nas três partidas (ou rasgo no polegar, ou fita no indicador). Lembrar que o Caixa Novato usa fita larga no indicador — o contraste largura 1,2 × 2,5 cm continua a pista. | F3: DECIDIDO 05/10: fita estreita no INDICADOR do impostor nas três partidas (mesmo dedo do rasgo da luva).
A4: Alta | B4: Segundo raspado da parede | C4: Caps. 4 e 5 (Caixa Novato) | D4: Pela rota, o impostor volta à Gerência às 7h59:54 (+109 s), depois de a câmera voltar (7h59:39). O Novato diz "quase dois minutos depois, logo depois de a imagem voltar" (Cap. 4) e "logo depois de a imagem voltar" (Cap. 5). | E4: Mudar a fala para "quase dois minutos depois" / "logo depois de a imagem voltar", ou o raspado vir do fundo do Rack ao reentrar (7h59:39). A grade da janela precisa fechar antes da narração. | F4: DECIDIDO 05/10: "quase dois minutos depois, logo depois de a imagem voltar" (Caps. 4 e 5).
A5: Alta | B5: Oculto e vigia: bloco "Completa" × "sempre presentes" | C5: Tabela "As quinze funções" | D5: A tabela põe o Monitor Remoto e o Operador de Rádio no bloco "Completa", mas o Guia (4.3) e a própria cobertura os tratam como presentes em toda casa (mensagem 8h10, reimpressão, 6h52, 8h29, 9h31, 9h56). | E5: Corrigir a tabela: "Completa" só para o Transportador; oculto e vigia "Sempre" (do sistema, nunca humanos). A matriz já segue assim. | F5: APLICADO 05/10: oculto e vigia sempre presentes, do sistema.
A6: Média | B6: Faixa administrativa lida só pela Estagiária | C6: Cap. 2 | D6: O histórico do rádio (pareamento 7h57:55) e a lista de quem tem cartão na faixa só são ditos pela Estagiária (3º bloco). Na casa de 6, a pergunta secundária do Cap. 2 fica sem fonte. | E6: A Operadora lê o histórico em toda casa; a Estagiária fica como reforço (ela já está na Central). | F6: APLICADO 05/10 (Cap. 2): sem a Estagiária, a Operadora lê.
A7: Média | B7: Quem tem chave da porta lateral, na casa de 6 | C7: Cap. 5 | D7: A lista da escala é dita pelo Subgerente e o "Eu" pela Limpeza (1º bloco). Na casa de 6 só o Técnico responde. | E7: Na ausência do Subgerente, a lista da escala sai do Gerente ou do Caixa Veterano; a chave da Limpeza vem do registro de chaves (Operadora). | F7: RESOLVIDO 05/10 pela casa mínima 8: o Subgerente e a Limpeza estão sempre na casa. A chave da Limpeza também consta no registro de chaves (Operadora).
A8: Média | B8: Plantação da fita estreita no Cap. 2 | C8: Cap. 2 (Farmacêutica) | D8: A observação das duas fitas (larga no Novato, estreita no impostor) só existe pela Farmacêutica (3º bloco). Nas casas de 6 a 10 a pista do Cap. 7 não tem plantação. | E8: Passar a observação à Auditora ou à Cliente do Cofre (que repara em detalhes) nas casas sem a Farmacêutica. | F8: APLICADO 05/10 (Cap. 2): sem a Farmacêutica, a Auditora vê.
A9: Média | B9: Falas fixas do Cap. 8 que contradizem a partida G | C9: Cap. 8 (narração da Auditora); Cap. 7 ("Não toquei no malote") | D9: "O Gerente tinha um cabo queimado… mas era outra coisa" e "O Gerente quis falar de fraude" não servem quando o Gerente é o impostor. "Não toquei no malote" é mentira essencial em G — precisa ser desmontada. | E9: Marcar esses trechos como pontos de ajuste (A9/A11) com variante G. | F9: APLICADO 05/10 (jogo, Cap. 8): na G, "Alguém falou em fraude" e "o cabo queimado das oito e trinta e um não era outra coisa: era o mesmo plano, agora escondendo a si mesmo". Cap. 7, "Não toquei no malote": mantido; na G é mentira do próprio impostor (permitida). Falta aplicar no docx (aba Mudanças no docx).
A10: Média | B10: Palavra "impostor" no texto público | C10: Cap. 8 (separação dos atos) | D10: "O impostor responderia pela custódia violada…" usa vocabulário do guia no texto público. | E10: Trocar por "Quem trocou o malote responderia…" ou pela função. | F10: APLICADO 05/10 (jogo, Cap. 8): a função entra no lugar ("O Subgerente responderia…"). Falta aplicar no docx.
A11: Média | B11: Respostas que perdem o par quando o Subgerente sai | C11: Caps. 2 e 4 | D11: "Possível. Com equipamento." (Técnico) responde a "Talvez tenham clonado algum"; "Duas respostas para uma única conversa" depende do "Pessoal". | E11: Nas casas sem Subgerente: a sugestão do clone passa ao Caixa Veterano; a resposta dupla vira silêncio do Gerente + versão da Operadora. | F11: APLICADO 05/10 (Cap. 2): clone com o Caixa Veterano; só o Gerente responde "Manutenção".
A12: Média | B12: Perguntas do núcleo a personagens de bloco | C12: Cap. 1 (Gerente → Limpeza; Auditora → Segurança do Veículo) | D12: Sem a Limpeza ou o Segurança do Veículo, as perguntas ficam sem resposta e a mentira da chave não acontece. | E12: Na casa sem o personagem, a pergunta sai do roteiro (condição de presença na coluna "Condição"). | F12: APLICADO 05/10 (jogo, Cap. 1): a Limpeza está sempre na casa (casa mínima 8); sem o Segurança do Veículo, a pergunta da Auditora sai do roteiro.
... A18: Baixa | B18: "Não imprimi nada" (Caixa Veterano, Cap. 1) | C18: Cap. 1 | D18: Na partida V ele é o impostor e agendou a impressão às 6h58. Literalmente verdade (ninguém imprimiu às 7h53), mas convém conferir a voz. | E18: Manter; registrar como mentira por omissão permitida. | F18: MANTIDO 05/10: mentira por omissão permitida na partida V (ninguém imprimiu às 7h53; a impressão foi agendada às 6h58).
A19: Decisão | B19: Personalidades (6 versões por fala) | C19: Todas as abas de falas | D19: As colunas Explosivo…Burocrata estão vazias: é a próxima passada, como na Matriz de falas da Casa da Costa. | E19: Escrever as 6 versões depois de fechar as pendências acima (a fala original pode mudar).
A20: Decisão | B20: Gerente humano | C20: Elenco; Caps. 4, 6, 7 | D20: O Gerente faz o encobrimento das 8h31 em toda partida. | E20: DECIDIDO 05/10: o Gerente é sempre do sistema (como o ajudante consciente). | F20: DECIDIDO 05/10
A21: Decisão | B21: Pegadas sem a Limpeza | C21: Cap. 4 | D21: Sem o Funcionário da Limpeza, ninguém descreve as pegadas. | E21: A Auditora diz a frase. | F21: APLICADO 05/10
A22: Média | B22: Caixa Veterano se denuncia antes das perguntas (V) | C22: Cap. 8, acusação (Variante V) | D22: Na Variante V, o Caixa Veterano diz o próprio nome na rodada da acusação, antes da pergunta final "Quem é o impostor?": entregaria a resposta. | E22: Na rodada da acusação ele não diz nome (como na S); diz "Fui eu", em voz baixa, durante a reconstrução da Auditora, "antes de a Auditora terminar". | F22: APLICADO 05/10 (jogo, Cap. 8). Falta aplicar no docx.
A23: Baixa | B23: "Não é magia. É atenção." na partida V | C23: Cap. 8, epílogo | D23: Na V o Caixa Veterano já saiu; a fala precisa de outro dono. | E23: O Subgerente ensina o Novato a ouvir o Cofre; o Caixa Novato diz a frase, repetindo quem lhe ensinara primeiro. | F23: APLICADO 05/10 (jogo, Cap. 8).
A24: Baixa | B24: Pergunta secundária S2 do Cap. 6 | C24: Aba Perguntas; Cap. 6 | D24: "Quem assinou sem contagem?" não tinha resposta completa no texto do capítulo. | E24: Trocar por "O que aconteceu às 19h03?" (a trava). | F24: APLICADO 05/10 (jogo, Cap. 6).
A25: Baixa | B25: Substituições por ausência (casas de 8 a 12) | C25: Caps. 1 a 8 | D25: Falas que dependem de personagens de bloco somem nas casas menores. | E25: Regras de substituição usadas no jogo: rádio lido pela Operadora (sem a Estagiária); fitas vistas pela Auditora (sem a Farmacêutica); clone sugerido pelo Caixa Veterano (sem o Subgerente); pegadas ditas pela Auditora (sem a Limpeza); sem o Padeiro, sai a cena do guarda-chuva e a Auditora pergunta pela sacola; sem a Limpeza no Cap. 6, a Auditora deduz o saco pela tampa (7h59:24), o balde (8h01) e o saco (8h02); sem o Transportador, o Motorista repete "Ninguém tirou. Alguém pôs." | F25: APLICADO 05/10 (jogo). No docx, vale registrar na nota interna de cada capítulo.
A26: Decisão | B26: Pontuação final | C26: Cap. 8; Guia técnico | D26: A pergunta final tem pesos diferentes. | E26: Impostor ×3, ajudante ×2, mecanismo e intenção ×1; secundária vale metade. Com certeza ±4; sem certeza +2/−1; não sei 0. Apostas por capítulo não pontuam: aparecem no placar. | F26: APLICADO 05/10 (jogo, placar).

Sheet Mudanças no docx
A1: Nº | B1: Capítulo / seção | C1: Onde | D1: Texto atual (revisão 2) | E1: Texto novo (proposta para a revisão 3) | F1: Motivo / decisão
A2: 1 | B2: Notas internas · Pontos de ajuste | C2: Tabela A3 | D2: A3. O corte coberto por fita microporosa estreita (1,2 cm): No polegar do Subgerente | No polegar do Gerente | No polegar do Caixa Veterano | E2: … No indicador do Subgerente | No indicador do Gerente | No indicador do Caixa Veterano | F2: Decisão 05/10: fita no indicador nas três partidas (mesmo dedo do rasgo da luva).
A3: 2 | B3: Notas internas · Quem nunca é o impostor | C3: Tabela "Nunca é o impostor" | D3: (sem linha para o Gerente humano) | E3: Acrescentar: "O Gerente (vestido por humano) · Nunca recebe humano: faz o encobrimento das 8h31 em toda partida, ato consciente que um jogador não pode ser obrigado a fazer." | F3: Decisão 05/10: o Gerente é sempre do sistema.
A4: 3 | B4: Notas internas · As quinze funções | C4: Tabela das funções e blocos | D4: Completa · O oculto · O Monitor Remoto / Completa · O vigia de fora · O Operador de Rádio | E4: Sempre (do sistema) · O oculto · O Monitor Remoto / Sempre (do sistema) · O vigia de fora · O Operador de Rádio. "Completa" fica só para o Transportador. | F4: Aplicado 05/10: oculto e vigia presentes em toda casa.
A5: 4 | B5: Notas internas · Casa mínima por partida | C5: Parágrafo "Casa mínima por partida" | D5: Partida G (Gerente) e partida V (Caixa Veterano): casa de 6. Partida S (Subgerente): casa de 8, a primeira que o inclui; […] Nas casas em que o Subgerente não está, as ações fixas dele […] saem. | E5: As três partidas têm casa mínima de 8: o Subgerente é o impostor na S e o ajudante (cossignatário A2) na G e na V, e por isso precisa estar na casa. Na casa de 8 entram também o Funcionário da Limpeza. (Apagar a frase sobre as casas sem o Subgerente.) | F5: Decisão 05/10 (opção 1).
A6: 5 | B6: Notas internas · A conta do caso | C6: Parágrafo "A conta do caso" | D6: Mesas: de 1 a 5 humanos na casa de 6 (G e V), e assim por diante pelos blocos; o impostor nunca recebe humano. | E6: Mesas: a partir da casa de 8, com 1 a 6 humanos nas partidas S e V e 1 a 7 na G, e assim por diante pelos blocos; o impostor e o Gerente nunca recebem humano. | F6: Consequência da casa mínima 8 e do Gerente sempre do sistema.
A7: 6 | B7: Cap. 2 | C7: A Farmacêutica observa mãos | D7: uma tira estreita e limpa no polegar do Subgerente^A3^. | E7: uma tira estreita e limpa no indicador do Subgerente^A3^. | F7: Decisão 05/10 (A3).
A8: 7 | B8: Cap. 4 | C8: O Caixa Novato no banheiro | D8: — Como uma gaveta pesada. Uma vez logo que o rádio chamou. Outra quase um minuto e meio depois. | E8: — Como uma gaveta pesada. Uma vez logo que o rádio chamou. Outra quase dois minutos depois, logo depois de a imagem voltar. | F8: Decisão 05/10: pela rota, o impostor volta à Gerência às 7h59:54, depois de a câmera voltar (7h59:39).
A9: 8 | B9: Cap. 4 | C9: Quadro interno, 8h51 | D9: Estagiária no terminal; Técnico corre ao Rack | E9: Operadora no terminal; Técnico corre ao Rack | F9: Na narrativa é a Operadora.
A10: 9 | B10: Cap. 5 | C10: O Caixa Novato conta nos dedos | D10: O primeiro raspado viera logo depois da ordem. O segundo, pouco antes de a imagem voltar. | E10: O primeiro raspado viera logo depois da ordem. O segundo, logo depois de a imagem voltar. | F10: Decisão 05/10 (mesma correção do Cap. 4).
A11: 10 | B11: Cap. 5 | C11: Quadro interno, 6h36 e 7h06 | D11: Duas aberturas por chave mecânica | E11: 6h36: aberta por chave mecânica; 7h06: aberta pela barra, por dentro | F11: O registro do sensor (Cap. 5) diz que às 7h06 a porta foi aberta pela barra.
A12: 11 | B12: Cap. 5 | C12: Ficha, "Subtrama que avança" | D12: O Técnico admite a atualização; a Limpeza encontra a cinta na caixa | E12: O Técnico admite a atualização; o Caixa Veterano encontra a cinta na caixa de 1998 (a Limpeza conta que a empurrara de volta às 7h46) | F12: No texto, quem puxa a caixa e lê a cinta é o Caixa Veterano.
A13: 12 | B13: Cap. 6 | C13: Quadro interno, 10h04 | D13: Estagiária no terminal; todos no Saguão | E13: Operadora no terminal; todos no Saguão | F13: Na narrativa é a Operadora.
... A23: 22 | B23: Todos os capítulos | C23: Nota interna de cada capítulo | D23: (sem regras de ausência) | E23: Registrar as substituições por ausência usadas no jogo (aba Pendências, linha "Substituições por ausência"). | F23: Para que o docx e o jogo digam a mesma coisa nas casas de 8 a 12.
